Lua 5.3.5  Copyright (C) 1994-2018 Lua.org, PUC-Rio

main <canvas.lua:0,0> (574 instructions at 0000029B16946080)
0+ params, 3 slots, 1 upvalue, 0 locals, 185 constants, 176 functions
	1	[-]	GETTABUP 	0 0 -1	; _ENV "__type"
	2	[-]	TESTSET  	0 0 1
	3	[-]	JMP      	0 2	; to 6
	4	[-]	GETTABUP 	0 0 -2	; _ENV "type"
	5	[-]	MOVE     	0 0
	6	[-]	SETTABUP 	0 -1 0	; _ENV "__type"
	7	[-]	GETTABUP 	0 0 -3	; _ENV "__instanceof"
	8	[-]	TESTSET  	0 0 1
	9	[-]	JMP      	0 2	; to 12
	10	[-]	CLOSURE  	0 0	; 0000029B16946C30
	11	[-]	MOVE     	0 0
	12	[-]	SETTABUP 	0 -3 0	; _ENV "__instanceof"
	13	[-]	GETTABUP 	0 0 -4	; _ENV "__get_static_call__"
	14	[-]	TESTSET  	0 0 1
	15	[-]	JMP      	0 2	; to 18
	16	[-]	CLOSURE  	0 1	; 0000029B16946500
	17	[-]	MOVE     	0 0
	18	[-]	SETTABUP 	0 -4 0	; _ENV "__get_static_call__"
	19	[-]	GETTABUP 	0 0 -5	; _ENV "__set_static_call__"
	20	[-]	TESTSET  	0 0 1
	21	[-]	JMP      	0 2	; to 24
	22	[-]	CLOSURE  	0 2	; 0000029B16954FD0
	23	[-]	MOVE     	0 0
	24	[-]	SETTABUP 	0 -5 0	; _ENV "__set_static_call__"
	25	[-]	GETTABUP 	0 0 -6	; _ENV "__get_call__"
	26	[-]	TESTSET  	0 0 1
	27	[-]	JMP      	0 2	; to 30
	28	[-]	CLOSURE  	0 3	; 0000029B16955050
	29	[-]	MOVE     	0 0
	30	[-]	SETTABUP 	0 -6 0	; _ENV "__get_call__"
	31	[-]	GETTABUP 	0 0 -7	; _ENV "__set_call__"
	32	[-]	TESTSET  	0 0 1
	33	[-]	JMP      	0 2	; to 36
	34	[-]	CLOSURE  	0 4	; 0000029B1695BCF0
	35	[-]	MOVE     	0 0
	36	[-]	SETTABUP 	0 -7 0	; _ENV "__set_call__"
	37	[-]	GETTABUP 	0 0 -8	; _ENV "__wrapper"
	38	[-]	TESTSET  	0 0 1
	39	[-]	JMP      	0 2	; to 42
	40	[-]	CLOSURE  	0 5	; 0000029B1695BEB0
	41	[-]	MOVE     	0 0
	42	[-]	SETTABUP 	0 -8 0	; _ENV "__wrapper"
	43	[-]	GETTABUP 	0 0 -9	; _ENV "__bind"
	44	[-]	TESTSET  	0 0 1
	45	[-]	JMP      	0 2	; to 48
	46	[-]	CLOSURE  	0 6	; 0000029B16959DD0
	47	[-]	MOVE     	0 0
	48	[-]	SETTABUP 	0 -9 0	; _ENV "__bind"
	49	[-]	GETTABUP 	0 0 -10	; _ENV "require"
	50	[-]	LOADK    	1 -11	; "webgl"
	51	[-]	CALL     	0 2 2
	52	[-]	SETTABUP 	0 -12 0	; _ENV "gl"
	53	[1]	NEWTABLE 	0 171 0
	54	[1]	LOADK    	1 -13	; "constructor"
	55	[1]	CLOSURE  	2 7	; 0000029B16959FC0
	56	[1]	SETTABLE 	0 1 2
	57	[1]	LOADK    	1 -14	; "addEventListener"
	58	[1]	CLOSURE  	2 8	; 0000029B1695A040
	59	[1]	SETTABLE 	0 1 2
	60	[1]	LOADK    	1 -15	; "drawArraysInstanced"
	61	[1]	CLOSURE  	2 9	; 0000029B1695A0C0
	62	[1]	SETTABLE 	0 1 2
	63	[1]	LOADK    	1 -16	; "drawElementsInstanced"
	64	[1]	CLOSURE  	2 10	; 0000029B1695A1C0
	65	[1]	SETTABLE 	0 1 2
	66	[1]	LOADK    	1 -17	; "vertexAttribDivisor"
	67	[1]	CLOSURE  	2 11	; 0000029B1695E1A0
	68	[1]	SETTABLE 	0 1 2
	69	[1]	LOADK    	1 -18	; "createVertexArray"
	70	[1]	CLOSURE  	2 12	; 0000029B1695DEA0
	71	[1]	SETTABLE 	0 1 2
	72	[1]	LOADK    	1 -19	; "bindVertexArray"
	73	[1]	CLOSURE  	2 13	; 0000029B1695E220
	74	[1]	SETTABLE 	0 1 2
	75	[1]	LOADK    	1 -20	; "deleteVertexArray"
	76	[1]	CLOSURE  	2 14	; 0000029B1695E2A0
	77	[1]	SETTABLE 	0 1 2
	78	[1]	LOADK    	1 -21	; "blitFramebuffer"
	79	[1]	CLOSURE  	2 15	; 0000029B1695D9A0
	80	[1]	SETTABLE 	0 1 2
	81	[1]	LOADK    	1 -22	; "renderbufferStorageMultisample"
	82	[1]	CLOSURE  	2 16	; 0000029B1695E4A0
	83	[1]	SETTABLE 	0 1 2
	84	[1]	LOADK    	1 -23	; "bindBufferBase"
	85	[1]	CLOSURE  	2 17	; 0000029B1695E320
	86	[1]	SETTABLE 	0 1 2
	87	[1]	LOADK    	1 -24	; "getUniformBlockIndex"
	88	[1]	CLOSURE  	2 18	; 0000029B1695DC20
	89	[1]	SETTABLE 	0 1 2
	90	[1]	LOADK    	1 -25	; "uniformBlockBinding"
	91	[1]	CLOSURE  	2 19	; 0000029B1695DA20
	92	[1]	SETTABLE 	0 1 2
	93	[1]	LOADK    	1 -26	; "createQuery"
	94	[1]	CLOSURE  	2 20	; 0000029B1695E420
	95	[1]	SETTABLE 	0 1 2
	96	[1]	LOADK    	1 -27	; "deleteQuery"
	97	[1]	CLOSURE  	2 21	; 0000029B1695E520
	98	[1]	SETTABLE 	0 1 2
	99	[1]	LOADK    	1 -28	; "beginQuery"
	100	[1]	CLOSURE  	2 22	; 0000029B1695DD20
	101	[1]	SETTABLE 	0 1 2
	102	[1]	LOADK    	1 -29	; "endQuery"
	103	[1]	CLOSURE  	2 23	; 0000029B1695D820
	104	[1]	SETTABLE 	0 1 2
	105	[1]	LOADK    	1 -30	; "getQueryParameter"
	106	[1]	CLOSURE  	2 24	; 0000029B1695D8A0
	107	[1]	SETTABLE 	0 1 2
	108	[1]	LOADK    	1 -31	; "getQuery"
	109	[1]	CLOSURE  	2 25	; 0000029B1695DFA0
	110	[1]	SETTABLE 	0 1 2
	111	[1]	LOADK    	1 -32	; "drawBuffers"
	112	[1]	CLOSURE  	2 26	; 0000029B1695DE20
	113	[1]	SETTABLE 	0 1 2
	114	[1]	LOADK    	1 -33	; "readBuffer"
	115	[1]	CLOSURE  	2 27	; 0000029B16960150
	116	[1]	SETTABLE 	0 1 2
	117	[1]	LOADK    	1 -34	; "texImage3D"
	118	[1]	CLOSURE  	2 28	; 0000029B16961CD0
	119	[1]	SETTABLE 	0 1 2
	120	[1]	LOADK    	1 -35	; "compressedTexImage3D"
	121	[1]	CLOSURE  	2 29	; 0000029B16961750
	122	[1]	SETTABLE 	0 1 2
	123	[1]	LOADK    	1 -36	; "createTransformFeedback"
	124	[1]	CLOSURE  	2 30	; 0000029B16960550
	125	[1]	SETTABLE 	0 1 2
	126	[1]	LOADK    	1 -37	; "deleteTransformFeedback"
	127	[1]	CLOSURE  	2 31	; 0000029B16961150
	128	[1]	SETTABLE 	0 1 2
	129	[1]	LOADK    	1 -38	; "bindTransformFeedback"
	130	[1]	CLOSURE  	2 32	; 0000029B16960350
	131	[1]	SETTABLE 	0 1 2
	132	[1]	LOADK    	1 -39	; "beginTransformFeedback"
	133	[1]	CLOSURE  	2 33	; 0000029B16961350
	134	[1]	SETTABLE 	0 1 2
	135	[1]	LOADK    	1 -40	; "endTransformFeedback"
	136	[1]	CLOSURE  	2 34	; 0000029B169610D0
	137	[1]	SETTABLE 	0 1 2
	138	[1]	LOADK    	1 -41	; "transformFeedbackVaryings"
	139	[1]	CLOSURE  	2 35	; 0000029B169601D0
	140	[1]	SETTABLE 	0 1 2
	141	[1]	LOADK    	1 -42	; "clearBufferfv"
	142	[1]	CLOSURE  	2 36	; 0000029B16960250
	143	[1]	SETTABLE 	0 1 2
	144	[1]	LOADK    	1 -43	; "clearBufferiv"
	145	[1]	CLOSURE  	2 37	; 0000029B16960950
	146	[1]	SETTABLE 	0 1 2
	147	[1]	LOADK    	1 -44	; "clearBufferuiv"
	148	[1]	CLOSURE  	2 38	; 0000029B16960D50
	149	[1]	SETTABLE 	0 1 2
	150	[1]	LOADK    	1 -45	; "clearBufferfi"
	151	[1]	CLOSURE  	2 39	; 0000029B169600D0
	152	[1]	SETTABLE 	0 1 2
	153	[1]	LOADK    	1 -46	; "activeTexture"
	154	[1]	CLOSURE  	2 40	; 0000029B169602D0
	155	[1]	SETTABLE 	0 1 2
	156	[1]	LOADK    	1 -47	; "attachShader"
	157	[1]	CLOSURE  	2 41	; 0000029B16960850
	158	[1]	SETTABLE 	0 1 2
	159	[1]	LOADK    	1 -48	; "bindAttribLocation"
	160	[1]	CLOSURE  	2 42	; 0000029B16960AD0
	161	[1]	SETTABLE 	0 1 2
	162	[1]	LOADK    	1 -49	; "bindBuffer"
	163	[1]	CLOSURE  	2 43	; 0000029B16960450
	164	[1]	SETTABLE 	0 1 2
	165	[1]	LOADK    	1 -50	; "bindFramebuffer"
	166	[1]	CLOSURE  	2 44	; 0000029B16961DD0
	167	[1]	SETTABLE 	0 1 2
	168	[1]	LOADK    	1 -51	; "bindRenderbuffer"
	169	[1]	CLOSURE  	2 45	; 0000029B16961850
	170	[1]	SETTABLE 	0 1 2
	171	[1]	LOADK    	1 -52	; "bindTexture"
	172	[1]	CLOSURE  	2 46	; 0000029B16961950
	173	[1]	SETTABLE 	0 1 2
	174	[1]	LOADK    	1 -53	; "blendColor"
	175	[1]	CLOSURE  	2 47	; 0000029B16961C50
	176	[1]	SETTABLE 	0 1 2
	177	[1]	LOADK    	1 -54	; "blendEquation"
	178	[1]	CLOSURE  	2 48	; 0000029B16960B50
	179	[1]	SETTABLE 	0 1 2
	180	[1]	LOADK    	1 -55	; "blendEquationSeparate"
	181	[1]	CLOSURE  	2 49	; 0000029B169608D0
	182	[1]	SETTABLE 	0 1 2
	183	[1]	LOADK    	1 -56	; "blendFunc"
	184	[1]	CLOSURE  	2 50	; 0000029B16960E50
	185	[1]	SETTABLE 	0 1 2
	186	[1]	LOADK    	1 -57	; "blendFuncSeparate"
	187	[1]	CLOSURE  	2 51	; 0000029B16961ED0
	188	[1]	SETTABLE 	0 1 2
	189	[1]	LOADK    	1 -58	; "bufferData"
	190	[1]	CLOSURE  	2 52	; 0000029B169619D0
	191	[1]	SETTABLE 	0 1 2
	192	[1]	LOADK    	1 -59	; "bufferSubData"
	193	[1]	CLOSURE  	2 53	; 0000029B16961A50
	194	[1]	SETTABLE 	0 1 2
	195	[1]	LOADK    	1 -60	; "checkFramebufferStatus"
	196	[1]	CLOSURE  	2 54	; 0000029B169604D0
	197	[1]	SETTABLE 	0 1 2
	198	[1]	LOADK    	1 -61	; "clear"
	199	[1]	CLOSURE  	2 55	; 0000029B169607D0
	200	[1]	SETTABLE 	0 1 2
	201	[1]	LOADK    	1 -62	; "clearColor"
	202	[1]	CLOSURE  	2 56	; 0000029B16960ED0
	203	[1]	SETTABLE 	0 1 2
	204	[1]	LOADK    	1 -63	; "clearDepth"
	205	[1]	CLOSURE  	2 57	; 0000029B16961050
	206	[1]	SETTABLE 	0 1 2
	207	[1]	LOADK    	1 -64	; "clearStencil"
	208	[1]	CLOSURE  	2 58	; 0000029B16966C60
	209	[1]	SETTABLE 	0 1 2
	210	[1]	LOADK    	1 -65	; "colorMask"
	211	[1]	CLOSURE  	2 59	; 0000029B16967C60
	212	[1]	SETTABLE 	0 1 2
	213	[1]	LOADK    	1 -66	; "compileShader"
	214	[1]	CLOSURE  	2 60	; 0000029B16967AE0
	215	[1]	SETTABLE 	0 1 2
	216	[1]	LOADK    	1 -67	; "compressedTexImage2D"
	217	[1]	CLOSURE  	2 61	; 0000029B169672E0
	218	[1]	SETTABLE 	0 1 2
	219	[1]	LOADK    	1 -68	; "compressedTexSubImage2D"
	220	[1]	CLOSURE  	2 62	; 0000029B169674E0
	221	[1]	SETTABLE 	0 1 2
	222	[1]	LOADK    	1 -69	; "copyTexImage2D"
	223	[1]	CLOSURE  	2 63	; 0000029B16965F60
	224	[1]	SETTABLE 	0 1 2
	225	[1]	LOADK    	1 -70	; "copyTexSubImage2D"
	226	[1]	CLOSURE  	2 64	; 0000029B16967160
	227	[1]	SETTABLE 	0 1 2
	228	[1]	LOADK    	1 -71	; "createBuffer"
	229	[1]	CLOSURE  	2 65	; 0000029B16967460
	230	[1]	SETTABLE 	0 1 2
	231	[1]	LOADK    	1 -72	; "createFramebuffer"
	232	[1]	CLOSURE  	2 66	; 0000029B169661E0
	233	[1]	SETTABLE 	0 1 2
	234	[1]	LOADK    	1 -73	; "createProgram"
	235	[1]	CLOSURE  	2 67	; 0000029B16966DE0
	236	[1]	SETTABLE 	0 1 2
	237	[1]	LOADK    	1 -74	; "createRenderbuffer"
	238	[1]	CLOSURE  	2 68	; 0000029B16966960
	239	[1]	SETTABLE 	0 1 2
	240	[1]	LOADK    	1 -75	; "createShader"
	241	[1]	CLOSURE  	2 69	; 0000029B16965FE0
	242	[1]	SETTABLE 	0 1 2
	243	[1]	LOADK    	1 -76	; "createTexture"
	244	[1]	CLOSURE  	2 70	; 0000029B16966060
	245	[1]	SETTABLE 	0 1 2
	246	[1]	LOADK    	1 -77	; "cullFace"
	247	[1]	CLOSURE  	2 71	; 0000029B16966260
	248	[1]	SETTABLE 	0 1 2
	249	[1]	LOADK    	1 -78	; "deleteBuffer"
	250	[1]	CLOSURE  	2 72	; 0000029B169669E0
	251	[1]	SETTABLE 	0 1 2
	252	[1]	LOADK    	1 -79	; "deleteFramebuffer"
	253	[1]	CLOSURE  	2 73	; 0000029B16967B60
	254	[1]	SETTABLE 	0 1 2
	255	[1]	LOADK    	1 -80	; "deleteProgram"
	256	[1]	CLOSURE  	2 74	; 0000029B169665E0
	257	[1]	SETTABLE 	0 1 2
	258	[1]	LOADK    	1 -81	; "deleteRenderbuffer"
	259	[1]	CLOSURE  	2 75	; 0000029B16966B60
	260	[1]	SETTABLE 	0 1 2
	261	[1]	LOADK    	1 -82	; "deleteShader"
	262	[1]	CLOSURE  	2 76	; 0000029B16967BE0
	263	[1]	SETTABLE 	0 1 2
	264	[1]	LOADK    	1 -83	; "deleteTexture"
	265	[1]	CLOSURE  	2 77	; 0000029B169675E0
	266	[1]	SETTABLE 	0 1 2
	267	[1]	LOADK    	1 -84	; "depthFunc"
	268	[1]	CLOSURE  	2 78	; 0000029B16966660
	269	[1]	SETTABLE 	0 1 2
	270	[1]	LOADK    	1 -85	; "depthMask"
	271	[1]	CLOSURE  	2 79	; 0000029B16966560
	272	[1]	SETTABLE 	0 1 2
	273	[1]	LOADK    	1 -86	; "depthRange"
	274	[1]	CLOSURE  	2 80	; 0000029B169663E0
	275	[1]	SETTABLE 	0 1 2
	276	[1]	LOADK    	1 -87	; "detachShader"
	277	[1]	CLOSURE  	2 81	; 0000029B16967660
	278	[1]	SETTABLE 	0 1 2
	279	[1]	LOADK    	1 -88	; "disable"
	280	[1]	CLOSURE  	2 82	; 0000029B16967860
	281	[1]	SETTABLE 	0 1 2
	282	[1]	LOADK    	1 -89	; "disableVertexAttribArray"
	283	[1]	CLOSURE  	2 83	; 0000029B169679E0
	284	[1]	SETTABLE 	0 1 2
	285	[1]	LOADK    	1 -90	; "drawArrays"
	286	[1]	CLOSURE  	2 84	; 0000029B16966D60
	287	[1]	SETTABLE 	0 1 2
	288	[1]	LOADK    	1 -91	; "drawElements"
	289	[1]	CLOSURE  	2 85	; 0000029B16966E60
	290	[1]	SETTABLE 	0 1 2
	291	[1]	LOADK    	1 -92	; "enable"
	292	[1]	CLOSURE  	2 86	; 0000029B16966EE0
	293	[1]	SETTABLE 	0 1 2
	294	[1]	LOADK    	1 -93	; "enableVertexAttribArray"
	295	[1]	CLOSURE  	2 87	; 0000029B16966F60
	296	[1]	SETTABLE 	0 1 2
	297	[1]	LOADK    	1 -94	; "finish"
	298	[1]	CLOSURE  	2 88	; 0000029B169677E0
	299	[1]	SETTABLE 	0 1 2
	300	[1]	LOADK    	1 -95	; "flush"
	301	[1]	CLOSURE  	2 89	; 0000029B16965E60
	302	[1]	SETTABLE 	0 1 2
	303	[1]	LOADK    	1 -96	; "framebufferRenderbuffer"
	304	[1]	CLOSURE  	2 90	; 0000029B1696C590
	305	[1]	SETTABLE 	0 1 2
	306	[1]	LOADK    	1 -97	; "framebufferTexture2D"
	307	[1]	CLOSURE  	2 91	; 0000029B1696C910
	308	[1]	SETTABLE 	0 1 2
	309	[1]	LOADK    	1 -98	; "frontFace"
	310	[1]	CLOSURE  	2 92	; 0000029B1696C090
	311	[1]	SETTABLE 	0 1 2
	312	[1]	LOADK    	1 -99	; "generateMipmap"
	313	[1]	CLOSURE  	2 93	; 0000029B1696BD90
	314	[1]	SETTABLE 	0 1 2
	315	[1]	LOADK    	1 -100	; "getActiveAttrib"
	316	[1]	CLOSURE  	2 94	; 0000029B1696B010
	317	[1]	SETTABLE 	0 1 2
	318	[1]	LOADK    	1 -101	; "getActiveUniform"
	319	[1]	CLOSURE  	2 95	; 0000029B1696B910
	320	[1]	SETTABLE 	0 1 2
	321	[1]	LOADK    	1 -102	; "getAttachedShaders"
	322	[1]	CLOSURE  	2 96	; 0000029B1696B990
	323	[1]	SETTABLE 	0 1 2
	324	[1]	LOADK    	1 -103	; "getAttribLocation"
	325	[1]	CLOSURE  	2 97	; 0000029B1696B890
	326	[1]	SETTABLE 	0 1 2
	327	[1]	LOADK    	1 -104	; "getBufferParameter"
	328	[1]	CLOSURE  	2 98	; 0000029B1696C490
	329	[1]	SETTABLE 	0 1 2
	330	[1]	LOADK    	1 -105	; "getContextAttributes"
	331	[1]	CLOSURE  	2 99	; 0000029B1696B810
	332	[1]	SETTABLE 	0 1 2
	333	[1]	LOADK    	1 -106	; "getError"
	334	[1]	CLOSURE  	2 100	; 0000029B1696CC90
	335	[1]	SETTABLE 	0 1 2
	336	[1]	LOADK    	1 -107	; "getExtension"
	337	[1]	CLOSURE  	2 101	; 0000029B1696CD10
	338	[1]	SETTABLE 	0 1 2
	339	[1]	LOADK    	1 -108	; "getFramebufferAttachmentParameter"
	340	[1]	CLOSURE  	2 102	; 0000029B1696BB90
	341	[1]	SETTABLE 	0 1 2
	342	[1]	LOADK    	1 -109	; "getParameter"
	343	[1]	CLOSURE  	2 103	; 0000029B1696CB10
	344	[1]	SETTABLE 	0 1 2
	345	[1]	LOADK    	1 -110	; "getProgramInfoLog"
	346	[1]	CLOSURE  	2 104	; 0000029B1696C890
	347	[1]	SETTABLE 	0 1 2
	348	[1]	LOADK    	1 -111	; "getProgramParameter"
	349	[1]	CLOSURE  	2 105	; 0000029B1696C790
	350	[1]	SETTABLE 	0 1 2
	351	[1]	LOADK    	1 -112	; "getRenderbufferParameter"
	352	[1]	CLOSURE  	2 106	; 0000029B1696C210
	353	[1]	SETTABLE 	0 1 2
	354	[1]	LOADK    	1 -113	; "getShaderInfoLog"
	355	[1]	CLOSURE  	2 107	; 0000029B1696B490
	356	[1]	SETTABLE 	0 1 2
	357	[1]	LOADK    	1 -114	; "getShaderParameter"
	358	[1]	CLOSURE  	2 108	; 0000029B1696C810
	359	[1]	SETTABLE 	0 1 2
	360	[1]	LOADK    	1 -115	; "getShaderPrecisionFormat"
	361	[1]	CLOSURE  	2 109	; 0000029B1696CD90
	362	[1]	SETTABLE 	0 1 2
	363	[1]	LOADK    	1 -116	; "getShaderSource"
	364	[1]	CLOSURE  	2 110	; 0000029B1696BB10
	365	[1]	SETTABLE 	0 1 2
	366	[1]	LOADK    	1 -117	; "getSupportedExtensions"
	367	[1]	CLOSURE  	2 111	; 0000029B1696CE10
	368	[1]	SETTABLE 	0 1 2
	369	[1]	LOADK    	1 -118	; "getTexParameter"
	370	[1]	CLOSURE  	2 112	; 0000029B1696B090
	371	[1]	SETTABLE 	0 1 2
	372	[1]	LOADK    	1 -119	; "getUniform"
	373	[1]	CLOSURE  	2 113	; 0000029B1696B790
	374	[1]	SETTABLE 	0 1 2
	375	[1]	LOADK    	1 -120	; "getUniformLocation"
	376	[1]	CLOSURE  	2 114	; 0000029B1696BF10
	377	[1]	SETTABLE 	0 1 2
	378	[1]	LOADK    	1 -121	; "getVertexAttrib"
	379	[1]	CLOSURE  	2 115	; 0000029B1696BF90
	380	[1]	SETTABLE 	0 1 2
	381	[1]	LOADK    	1 -122	; "getVertexAttribOffset"
	382	[1]	CLOSURE  	2 116	; 0000029B1696B110
	383	[1]	SETTABLE 	0 1 2
	384	[1]	LOADK    	1 -123	; "hint"
	385	[1]	CLOSURE  	2 117	; 0000029B1696C990
	386	[1]	SETTABLE 	0 1 2
	387	[1]	LOADK    	1 -124	; "isBuffer"
	388	[1]	CLOSURE  	2 118	; 0000029B1696C390
	389	[1]	SETTABLE 	0 1 2
	390	[1]	LOADK    	1 -125	; "isContextLost"
	391	[1]	CLOSURE  	2 119	; 0000029B1696CB90
	392	[1]	SETTABLE 	0 1 2
	393	[1]	LOADK    	1 -126	; "isEnabled"
	394	[1]	CLOSURE  	2 120	; 0000029B1696B310
	395	[1]	SETTABLE 	0 1 2
	396	[1]	LOADK    	1 -127	; "isFramebuffer"
	397	[1]	CLOSURE  	2 121	; 0000029B1696B390
	398	[1]	SETTABLE 	0 1 2
	399	[1]	LOADK    	1 -128	; "isProgram"
	400	[1]	CLOSURE  	2 122	; 0000029B1696B590
	401	[1]	SETTABLE 	0 1 2
	402	[1]	LOADK    	1 -129	; "isRenderbuffer"
	403	[1]	CLOSURE  	2 123	; 0000029B1696B710
	404	[1]	SETTABLE 	0 1 2
	405	[1]	LOADK    	1 -130	; "isShader"
	406	[1]	CLOSURE  	2 124	; 0000029B169719D0
	407	[1]	SETTABLE 	0 1 2
	408	[1]	LOADK    	1 -131	; "isTexture"
	409	[1]	CLOSURE  	2 125	; 0000029B16970850
	410	[1]	SETTABLE 	0 1 2
	411	[1]	LOADK    	1 -132	; "lineWidth"
	412	[1]	CLOSURE  	2 126	; 0000029B16971DD0
	413	[1]	SETTABLE 	0 1 2
	414	[1]	LOADK    	1 -133	; "linkProgram"
	415	[1]	CLOSURE  	2 127	; 0000029B16970E50
	416	[1]	SETTABLE 	0 1 2
	417	[1]	LOADK    	1 -134	; "pixelStorei"
	418	[1]	CLOSURE  	2 128	; 0000029B16970950
	419	[1]	SETTABLE 	0 1 2
	420	[1]	LOADK    	1 -135	; "polygonOffset"
	421	[1]	CLOSURE  	2 129	; 0000029B16971E50
	422	[1]	SETTABLE 	0 1 2
	423	[1]	LOADK    	1 -136	; "readPixels"
	424	[1]	CLOSURE  	2 130	; 0000029B16972450
	425	[1]	SETTABLE 	0 1 2
	426	[1]	LOADK    	1 -137	; "renderbufferStorage"
	427	[1]	CLOSURE  	2 131	; 0000029B16971A50
	428	[1]	SETTABLE 	0 1 2
	429	[1]	LOADK    	1 -138	; "sampleCoverage"
	430	[1]	CLOSURE  	2 132	; 0000029B169717D0
	431	[1]	SETTABLE 	0 1 2
	432	[1]	LOADK    	1 -139	; "scissor"
	433	[1]	CLOSURE  	2 133	; 0000029B169720D0
	434	[1]	SETTABLE 	0 1 2
	435	[1]	LOADK    	1 -140	; "shaderSource"
	436	[1]	CLOSURE  	2 134	; 0000029B16972150
	437	[1]	SETTABLE 	0 1 2
	438	[1]	LOADK    	1 -141	; "stencilFunc"
	439	[1]	CLOSURE  	2 135	; 0000029B169716D0
	440	[1]	SETTABLE 	0 1 2
	441	[1]	LOADK    	1 -142	; "stencilFuncSeparate"
	442	[1]	CLOSURE  	2 136	; 0000029B16971CD0
	443	[1]	SETTABLE 	0 1 2
	444	[1]	LOADK    	1 -143	; "stencilMask"
	445	[1]	CLOSURE  	2 137	; 0000029B16971950
	446	[1]	SETTABLE 	0 1 2
	447	[1]	LOADK    	1 -144	; "stencilMaskSeparate"
	448	[1]	CLOSURE  	2 138	; 0000029B169718D0
	449	[1]	SETTABLE 	0 1 2
	450	[1]	LOADK    	1 -145	; "stencilOp"
	451	[1]	CLOSURE  	2 139	; 0000029B16970CD0
	452	[1]	SETTABLE 	0 1 2
	453	[1]	LOADK    	1 -146	; "stencilOpSeparate"
	454	[1]	CLOSURE  	2 140	; 0000029B169714D0
	455	[1]	SETTABLE 	0 1 2
	456	[1]	LOADK    	1 -147	; "texImage2D"
	457	[1]	CLOSURE  	2 141	; 0000029B16971650
	458	[1]	SETTABLE 	0 1 2
	459	[1]	LOADK    	1 -148	; "texParameterf"
	460	[1]	CLOSURE  	2 142	; 0000029B16972250
	461	[1]	SETTABLE 	0 1 2
	462	[1]	LOADK    	1 -149	; "texParameteri"
	463	[1]	CLOSURE  	2 143	; 0000029B16971850
	464	[1]	SETTABLE 	0 1 2
	465	[1]	LOADK    	1 -150	; "texSubImage2D"
	466	[1]	CLOSURE  	2 144	; 0000029B16970FD0
	467	[1]	SETTABLE 	0 1 2
	468	[1]	LOADK    	1 -151	; "uniform1f"
	469	[1]	CLOSURE  	2 145	; 0000029B16971550
	470	[1]	SETTABLE 	0 1 2
	471	[1]	LOADK    	1 -152	; "uniform1fv"
	472	[1]	CLOSURE  	2 146	; 0000029B16972050
	473	[1]	SETTABLE 	0 1 2
	474	[1]	LOADK    	1 -153	; "uniform1i"
	475	[1]	CLOSURE  	2 147	; 0000029B16972350
	476	[1]	SETTABLE 	0 1 2
	477	[1]	LOADK    	1 -154	; "uniform1iv"
	478	[1]	CLOSURE  	2 148	; 0000029B16971B50
	479	[1]	SETTABLE 	0 1 2
	480	[1]	LOADK    	1 -155	; "uniform2f"
	481	[1]	CLOSURE  	2 149	; 0000029B16971250
	482	[1]	SETTABLE 	0 1 2
	483	[1]	LOADK    	1 -156	; "uniform2fv"
	484	[1]	CLOSURE  	2 150	; 0000029B16971350
	485	[1]	SETTABLE 	0 1 2
	486	[1]	LOADK    	1 -157	; "uniform2i"
	487	[1]	CLOSURE  	2 151	; 0000029B16971450
	488	[1]	SETTABLE 	0 1 2
	489	[1]	LOADK    	1 -158	; "uniform2iv"
	490	[1]	CLOSURE  	2 152	; 0000029B16972750
	491	[1]	SETTABLE 	0 1 2
	492	[1]	LOADK    	1 -159	; "uniform3f"
	493	[1]	CLOSURE  	2 153	; 0000029B16971750
	494	[1]	SETTABLE 	0 1 2
	495	[1]	LOADK    	1 -160	; "uniform3fv"
	496	[1]	CLOSURE  	2 154	; 0000029B169711D0
	497	[1]	SETTABLE 	0 1 2
	498	[1]	LOADK    	1 -161	; "uniform3i"
	499	[1]	CLOSURE  	2 155	; 0000029B16975960
	500	[1]	SETTABLE 	0 1 2
	501	[1]	LOADK    	1 -162	; "uniform3iv"
	502	[1]	CLOSURE  	2 156	; 0000029B16975460
	503	[1]	SETTABLE 	0 1 2
	504	[1]	LOADK    	1 -163	; "uniform4f"
	505	[1]	CLOSURE  	2 157	; 0000029B16975860
	506	[1]	SETTABLE 	0 1 2
	507	[1]	LOADK    	1 -164	; "uniform4fv"
	508	[1]	CLOSURE  	2 158	; 0000029B16975560
	509	[1]	SETTABLE 	0 1 2
	510	[1]	LOADK    	1 -165	; "uniform4i"
	511	[1]	CLOSURE  	2 159	; 0000029B169744E0
	512	[1]	SETTABLE 	0 1 2
	513	[1]	LOADK    	1 -166	; "uniform4iv"
	514	[1]	CLOSURE  	2 160	; 0000029B16974F60
	515	[1]	SETTABLE 	0 1 2
	516	[1]	LOADK    	1 -167	; "uniformMatrix2fv"
	517	[1]	CLOSURE  	2 161	; 0000029B16974560
	518	[1]	SETTABLE 	0 1 2
	519	[1]	LOADK    	1 -168	; "uniformMatrix3fv"
	520	[1]	CLOSURE  	2 162	; 0000029B169758E0
	521	[1]	SETTABLE 	0 1 2
	522	[1]	LOADK    	1 -169	; "uniformMatrix4fv"
	523	[1]	CLOSURE  	2 163	; 0000029B16973EE0
	524	[1]	SETTABLE 	0 1 2
	525	[1]	LOADK    	1 -170	; "useProgram"
	526	[1]	CLOSURE  	2 164	; 0000029B16974660
	527	[1]	SETTABLE 	0 1 2
	528	[1]	LOADK    	1 -171	; "validateProgram"
	529	[1]	CLOSURE  	2 165	; 0000029B169745E0
	530	[1]	SETTABLE 	0 1 2
	531	[1]	LOADK    	1 -172	; "vertexAttrib1f"
	532	[1]	CLOSURE  	2 166	; 0000029B169754E0
	533	[1]	SETTABLE 	0 1 2
	534	[1]	LOADK    	1 -173	; "vertexAttrib1fv"
	535	[1]	CLOSURE  	2 167	; 0000029B16974960
	536	[1]	SETTABLE 	0 1 2
	537	[1]	LOADK    	1 -174	; "vertexAttrib2f"
	538	[1]	CLOSURE  	2 168	; 0000029B169746E0
	539	[1]	SETTABLE 	0 1 2
	540	[1]	LOADK    	1 -175	; "vertexAttrib2fv"
	541	[1]	CLOSURE  	2 169	; 0000029B16975060
	542	[1]	SETTABLE 	0 1 2
	543	[1]	LOADK    	1 -176	; "vertexAttrib3f"
	544	[1]	CLOSURE  	2 170	; 0000029B169756E0
	545	[1]	SETTABLE 	0 1 2
	546	[1]	LOADK    	1 -177	; "vertexAttrib3fv"
	547	[1]	CLOSURE  	2 171	; 0000029B16975D60
	548	[1]	SETTABLE 	0 1 2
	549	[1]	LOADK    	1 -178	; "vertexAttrib4f"
	550	[1]	CLOSURE  	2 172	; 0000029B169751E0
	551	[1]	SETTABLE 	0 1 2
	552	[1]	LOADK    	1 -179	; "vertexAttrib4fv"
	553	[1]	CLOSURE  	2 173	; 0000029B169759E0
	554	[1]	SETTABLE 	0 1 2
	555	[1]	LOADK    	1 -180	; "vertexAttribPointer"
	556	[1]	CLOSURE  	2 174	; 0000029B16975760
	557	[1]	SETTABLE 	0 1 2
	558	[1]	LOADK    	1 -181	; "viewport"
	559	[1]	CLOSURE  	2 175	; 0000029B16975BE0
	560	[1]	SETTABLE 	0 1 2
	561	[1]	LOADK    	1 -182	; "__proto"
	562	[1]	GETTABUP 	2 0 -12	; _ENV "gl"
	563	[1]	SETTABLE 	0 1 2
	564	[1]	LOADK    	1 -183	; "__index"
	565	[1]	GETTABUP 	2 0 -12	; _ENV "gl"
	566	[1]	SETTABLE 	0 1 2
	567	[1]	SETTABUP 	0 -184 0	; _ENV "Canvas"
	568	[1]	GETTABUP 	0 0 -185	; _ENV "setmetatable"
	569	[1]	GETTABUP 	1 0 -184	; _ENV "Canvas"
	570	[1]	GETTABUP 	2 0 -184	; _ENV "Canvas"
	571	[1]	CALL     	0 3 1
	572	[1]	GETTABUP 	0 0 -184	; _ENV "Canvas"
	573	[1]	RETURN   	0 2
	574	[1]	RETURN   	0 1
constants (185) for 0000029B16946080:
	1	"__type"
	2	"type"
	3	"__instanceof"
	4	"__get_static_call__"
	5	"__set_static_call__"
	6	"__get_call__"
	7	"__set_call__"
	8	"__wrapper"
	9	"__bind"
	10	"require"
	11	"webgl"
	12	"gl"
	13	"constructor"
	14	"addEventListener"
	15	"drawArraysInstanced"
	16	"drawElementsInstanced"
	17	"vertexAttribDivisor"
	18	"createVertexArray"
	19	"bindVertexArray"
	20	"deleteVertexArray"
	21	"blitFramebuffer"
	22	"renderbufferStorageMultisample"
	23	"bindBufferBase"
	24	"getUniformBlockIndex"
	25	"uniformBlockBinding"
	26	"createQuery"
	27	"deleteQuery"
	28	"beginQuery"
	29	"endQuery"
	30	"getQueryParameter"
	31	"getQuery"
	32	"drawBuffers"
	33	"readBuffer"
	34	"texImage3D"
	35	"compressedTexImage3D"
	36	"createTransformFeedback"
	37	"deleteTransformFeedback"
	38	"bindTransformFeedback"
	39	"beginTransformFeedback"
	40	"endTransformFeedback"
	41	"transformFeedbackVaryings"
	42	"clearBufferfv"
	43	"clearBufferiv"
	44	"clearBufferuiv"
	45	"clearBufferfi"
	46	"activeTexture"
	47	"attachShader"
	48	"bindAttribLocation"
	49	"bindBuffer"
	50	"bindFramebuffer"
	51	"bindRenderbuffer"
	52	"bindTexture"
	53	"blendColor"
	54	"blendEquation"
	55	"blendEquationSeparate"
	56	"blendFunc"
	57	"blendFuncSeparate"
	58	"bufferData"
	59	"bufferSubData"
	60	"checkFramebufferStatus"
	61	"clear"
	62	"clearColor"
	63	"clearDepth"
	64	"clearStencil"
	65	"colorMask"
	66	"compileShader"
	67	"compressedTexImage2D"
	68	"compressedTexSubImage2D"
	69	"copyTexImage2D"
	70	"copyTexSubImage2D"
	71	"createBuffer"
	72	"createFramebuffer"
	73	"createProgram"
	74	"createRenderbuffer"
	75	"createShader"
	76	"createTexture"
	77	"cullFace"
	78	"deleteBuffer"
	79	"deleteFramebuffer"
	80	"deleteProgram"
	81	"deleteRenderbuffer"
	82	"deleteShader"
	83	"deleteTexture"
	84	"depthFunc"
	85	"depthMask"
	86	"depthRange"
	87	"detachShader"
	88	"disable"
	89	"disableVertexAttribArray"
	90	"drawArrays"
	91	"drawElements"
	92	"enable"
	93	"enableVertexAttribArray"
	94	"finish"
	95	"flush"
	96	"framebufferRenderbuffer"
	97	"framebufferTexture2D"
	98	"frontFace"
	99	"generateMipmap"
	100	"getActiveAttrib"
	101	"getActiveUniform"
	102	"getAttachedShaders"
	103	"getAttribLocation"
	104	"getBufferParameter"
	105	"getContextAttributes"
	106	"getError"
	107	"getExtension"
	108	"getFramebufferAttachmentParameter"
	109	"getParameter"
	110	"getProgramInfoLog"
	111	"getProgramParameter"
	112	"getRenderbufferParameter"
	113	"getShaderInfoLog"
	114	"getShaderParameter"
	115	"getShaderPrecisionFormat"
	116	"getShaderSource"
	117	"getSupportedExtensions"
	118	"getTexParameter"
	119	"getUniform"
	120	"getUniformLocation"
	121	"getVertexAttrib"
	122	"getVertexAttribOffset"
	123	"hint"
	124	"isBuffer"
	125	"isContextLost"
	126	"isEnabled"
	127	"isFramebuffer"
	128	"isProgram"
	129	"isRenderbuffer"
	130	"isShader"
	131	"isTexture"
	132	"lineWidth"
	133	"linkProgram"
	134	"pixelStorei"
	135	"polygonOffset"
	136	"readPixels"
	137	"renderbufferStorage"
	138	"sampleCoverage"
	139	"scissor"
	140	"shaderSource"
	141	"stencilFunc"
	142	"stencilFuncSeparate"
	143	"stencilMask"
	144	"stencilMaskSeparate"
	145	"stencilOp"
	146	"stencilOpSeparate"
	147	"texImage2D"
	148	"texParameterf"
	149	"texParameteri"
	150	"texSubImage2D"
	151	"uniform1f"
	152	"uniform1fv"
	153	"uniform1i"
	154	"uniform1iv"
	155	"uniform2f"
	156	"uniform2fv"
	157	"uniform2i"
	158	"uniform2iv"
	159	"uniform3f"
	160	"uniform3fv"
	161	"uniform3i"
	162	"uniform3iv"
	163	"uniform4f"
	164	"uniform4fv"
	165	"uniform4i"
	166	"uniform4iv"
	167	"uniformMatrix2fv"
	168	"uniformMatrix3fv"
	169	"uniformMatrix4fv"
	170	"useProgram"
	171	"validateProgram"
	172	"vertexAttrib1f"
	173	"vertexAttrib1fv"
	174	"vertexAttrib2f"
	175	"vertexAttrib2fv"
	176	"vertexAttrib3f"
	177	"vertexAttrib3fv"
	178	"vertexAttrib4f"
	179	"vertexAttrib4fv"
	180	"vertexAttribPointer"
	181	"viewport"
	182	"__proto"
	183	"__index"
	184	"Canvas"
	185	"setmetatable"
locals (0) for 0000029B16946080:
upvalues (1) for 0000029B16946080:
	0	_ENV	1	0

main <canvas.lua:0,0> (60 instructions at 0000029B16946C30)
2 params, 6 slots, 1 upvalue, 3 locals, 9 constants, 0 functions
	1	[-]	MOVE     	2 0
	2	[-]	NOT      	2 2
	3	[-]	TEST     	2 0
	4	[-]	JMP      	0 2	; to 7
	5	[-]	LOADBOOL 	2 0 0
	6	[-]	RETURN   	2 2
	7	[-]	LOADNIL  	3 0
	8	[-]	MOVE     	2 3
	9	[-]	GETTABUP 	3 0 -1	; _ENV "__type"
	10	[-]	MOVE     	4 0
	11	[-]	CALL     	3 2 2
	12	[-]	LOADK    	4 -2	; "table"
	13	[-]	EQ       	1 3 4
	14	[-]	JMP      	0 1	; to 16
	15	[-]	JMP      	0 4	; to 20
	16	[-]	MOVE     	4 0
	17	[-]	GETTABLE 	4 4 -3	; "__proto"
	18	[-]	MOVE     	2 4
	19	[-]	JMP      	0 21	; to 41
	20	[-]	LOADK    	4 -4	; "number"
	21	[-]	EQ       	1 3 4
	22	[-]	JMP      	0 1	; to 24
	23	[-]	JMP      	0 3	; to 27
	24	[-]	GETTABUP 	4 0 -5	; _ENV "Number"
	25	[-]	MOVE     	2 4
	26	[-]	JMP      	0 14	; to 41
	27	[-]	LOADK    	4 -6	; "string"
	28	[-]	EQ       	1 3 4
	29	[-]	JMP      	0 1	; to 31
	30	[-]	JMP      	0 3	; to 34
	31	[-]	GETTABUP 	4 0 -7	; _ENV "String"
	32	[-]	MOVE     	2 4
	33	[-]	JMP      	0 7	; to 41
	34	[-]	LOADK    	4 -8	; "boolean"
	35	[-]	EQ       	1 3 4
	36	[-]	JMP      	0 1	; to 38
	37	[-]	JMP      	0 0	; to 38
	38	[-]	GETTABUP 	4 0 -9	; _ENV "Boolean"
	39	[-]	MOVE     	2 4
	40	[-]	JMP      	0 0	; to 41
	41	[-]	JMP      	0 13	; to 55
	42	[-]	MOVE     	3 1
	43	[-]	MOVE     	4 2
	44	[-]	EQ       	1 4 3
	45	[-]	JMP      	0 1	; to 47
	46	[-]	LOADBOOL 	3 0 1
	47	[-]	LOADBOOL 	3 1 0
	48	[-]	TEST     	3 0
	49	[-]	JMP      	0 2	; to 52
	50	[-]	LOADBOOL 	3 1 0
	51	[-]	RETURN   	3 2
	52	[-]	MOVE     	3 2
	53	[-]	GETTABLE 	3 3 -3	; "__proto"
	54	[-]	MOVE     	2 3
	55	[-]	MOVE     	3 2
	56	[-]	TEST     	3 1
	57	[-]	JMP      	0 -16	; to 42
	58	[-]	LOADBOOL 	3 0 0
	59	[-]	RETURN   	3 2
	60	[-]	RETURN   	0 1
constants (9) for 0000029B16946C30:
	1	"__type"
	2	"table"
	3	"__proto"
	4	"number"
	5	"Number"
	6	"string"
	7	"String"
	8	"boolean"
	9	"Boolean"
locals (3) for 0000029B16946C30:
	0	inst	1	62
	1	type	1	62
	2	mt	8	62
upvalues (1) for 0000029B16946C30:
	0	_ENV	0	0

main <canvas.lua:0,0> (34 instructions at 0000029B16946500)
2 params, 6 slots, 1 upvalue, 3 locals, 3 constants, 0 functions
	1	[-]	GETTABUP 	3 0 -1	; _ENV "rawget"
	2	[-]	MOVE     	4 0
	3	[-]	LOADK    	5 -2	; "__get__"
	4	[-]	CALL     	3 3 2
	5	[-]	MOVE     	4 1
	6	[-]	GETTABLE 	3 3 4
	7	[-]	MOVE     	2 3
	8	[-]	MOVE     	3 2
	9	[-]	TEST     	3 0
	10	[-]	JMP      	0 4	; to 15
	11	[-]	MOVE     	3 2
	12	[-]	MOVE     	4 0
	13	[-]	CALL     	3 2 2
	14	[-]	RETURN   	3 2
	15	[-]	GETTABUP 	3 0 -1	; _ENV "rawget"
	16	[-]	MOVE     	4 0
	17	[-]	MOVE     	5 1
	18	[-]	CALL     	3 3 2
	19	[-]	TESTSET  	3 3 1
	20	[-]	JMP      	0 12	; to 33
	21	[-]	GETTABUP 	3 0 -1	; _ENV "rawget"
	22	[-]	MOVE     	4 0
	23	[-]	LOADK    	5 -3	; "__proto"
	24	[-]	CALL     	3 3 2
	25	[-]	TESTSET  	3 3 0
	26	[-]	JMP      	0 5	; to 32
	27	[-]	MOVE     	3 0
	28	[-]	GETTABLE 	3 3 -3	; "__proto"
	29	[-]	MOVE     	4 1
	30	[-]	GETTABLE 	3 3 4
	31	[-]	MOVE     	3 3
	32	[-]	MOVE     	3 3
	33	[-]	RETURN   	3 2
	34	[-]	RETURN   	0 1
constants (3) for 0000029B16946500:
	1	"rawget"
	2	"__get__"
	3	"__proto"
locals (3) for 0000029B16946500:
	0	t	1	36
	1	k	1	36
	2	getmethod	2	36
upvalues (1) for 0000029B16946500:
	0	_ENV	0	0

main <canvas.lua:0,0> (21 instructions at 0000029B16954FD0)
3 params, 8 slots, 1 upvalue, 4 locals, 3 constants, 0 functions
	1	[-]	GETTABUP 	4 0 -1	; _ENV "rawget"
	2	[-]	MOVE     	5 0
	3	[-]	LOADK    	6 -2	; "__set__"
	4	[-]	CALL     	4 3 2
	5	[-]	MOVE     	5 1
	6	[-]	GETTABLE 	4 4 5
	7	[-]	MOVE     	3 4
	8	[-]	MOVE     	4 3
	9	[-]	TEST     	4 0
	10	[-]	JMP      	0 5	; to 16
	11	[-]	MOVE     	4 3
	12	[-]	MOVE     	5 0
	13	[-]	MOVE     	6 2
	14	[-]	CALL     	4 3 1
	15	[-]	RETURN   	0 1
	16	[-]	GETTABUP 	4 0 -3	; _ENV "rawset"
	17	[-]	MOVE     	5 0
	18	[-]	MOVE     	6 1
	19	[-]	MOVE     	7 2
	20	[-]	CALL     	4 4 1
	21	[-]	RETURN   	0 1
constants (3) for 0000029B16954FD0:
	1	"rawget"
	2	"__set__"
	3	"rawset"
locals (4) for 0000029B16954FD0:
	0	t	1	23
	1	k	1	23
	2	v	1	23
	3	setmethod	2	23
upvalues (1) for 0000029B16954FD0:
	0	_ENV	0	0

main <canvas.lua:0,0> (41 instructions at 0000029B16955050)
2 params, 7 slots, 1 upvalue, 5 locals, 3 constants, 0 functions
	1	[-]	MOVE     	3 0
	2	[-]	GETTABLE 	3 3 -1	; "__proto"
	3	[-]	MOVE     	2 3
	4	[-]	JMP      	0 21	; to 26
	5	[-]	MOVE     	4 2
	6	[-]	GETTABLE 	4 4 -2	; "__get__"
	7	[-]	MOVE     	3 4
	8	[-]	MOVE     	5 3
	9	[-]	TESTSET  	5 5 0
	10	[-]	JMP      	0 4	; to 15
	11	[-]	MOVE     	5 3
	12	[-]	MOVE     	6 1
	13	[-]	GETTABLE 	5 5 6
	14	[-]	MOVE     	5 5
	15	[-]	MOVE     	4 5
	16	[-]	MOVE     	5 4
	17	[-]	TEST     	5 0
	18	[-]	JMP      	0 4	; to 23
	19	[-]	MOVE     	5 4
	20	[-]	MOVE     	6 0
	21	[-]	CALL     	5 2 2
	22	[-]	RETURN   	5 2
	23	[-]	MOVE     	5 2
	24	[-]	GETTABLE 	5 5 -1	; "__proto"
	25	[-]	MOVE     	2 5
	26	[-]	MOVE     	3 2
	27	[-]	TEST     	3 1
	28	[-]	JMP      	0 -24	; to 5
	29	[-]	GETTABUP 	3 0 -3	; _ENV "rawget"
	30	[-]	MOVE     	4 0
	31	[-]	MOVE     	5 1
	32	[-]	CALL     	3 3 2
	33	[-]	TESTSET  	3 3 1
	34	[-]	JMP      	0 5	; to 40
	35	[-]	MOVE     	3 0
	36	[-]	GETTABLE 	3 3 -1	; "__proto"
	37	[-]	MOVE     	4 1
	38	[-]	GETTABLE 	3 3 4
	39	[-]	MOVE     	3 3
	40	[-]	RETURN   	3 2
	41	[-]	RETURN   	0 1
constants (3) for 0000029B16955050:
	1	"__proto"
	2	"__get__"
	3	"rawget"
locals (5) for 0000029B16955050:
	0	t	1	43
	1	k	1	43
	2	proto	2	43
	3	get_	6	27
	4	getmethod	9	27
upvalues (1) for 0000029B16955050:
	0	_ENV	0	0

main <canvas.lua:0,0> (35 instructions at 0000029B1695BCF0)
3 params, 9 slots, 1 upvalue, 6 locals, 3 constants, 0 functions
	1	[-]	MOVE     	4 0
	2	[-]	GETTABLE 	4 4 -1	; "__proto"
	3	[-]	MOVE     	3 4
	4	[-]	JMP      	0 22	; to 27
	5	[-]	MOVE     	5 3
	6	[-]	GETTABLE 	5 5 -2	; "__set__"
	7	[-]	MOVE     	4 5
	8	[-]	MOVE     	6 4
	9	[-]	TESTSET  	6 6 0
	10	[-]	JMP      	0 4	; to 15
	11	[-]	MOVE     	6 4
	12	[-]	MOVE     	7 1
	13	[-]	GETTABLE 	6 6 7
	14	[-]	MOVE     	6 6
	15	[-]	MOVE     	5 6
	16	[-]	MOVE     	6 5
	17	[-]	TEST     	6 0
	18	[-]	JMP      	0 5	; to 24
	19	[-]	MOVE     	6 5
	20	[-]	MOVE     	7 0
	21	[-]	MOVE     	8 2
	22	[-]	CALL     	6 3 1
	23	[-]	RETURN   	0 1
	24	[-]	MOVE     	6 3
	25	[-]	GETTABLE 	6 6 -1	; "__proto"
	26	[-]	MOVE     	3 6
	27	[-]	MOVE     	4 3
	28	[-]	TEST     	4 1
	29	[-]	JMP      	0 -25	; to 5
	30	[-]	GETTABUP 	4 0 -3	; _ENV "rawset"
	31	[-]	MOVE     	5 0
	32	[-]	MOVE     	6 1
	33	[-]	MOVE     	7 2
	34	[-]	CALL     	4 4 1
	35	[-]	RETURN   	0 1
constants (3) for 0000029B1695BCF0:
	1	"__proto"
	2	"__set__"
	3	"rawset"
locals (6) for 0000029B1695BCF0:
	0	t	1	37
	1	k	1	37
	2	v	1	37
	3	proto	2	37
	4	set_	6	28
	5	setmethod	9	28
upvalues (1) for 0000029B1695BCF0:
	0	_ENV	0	0

main <canvas.lua:0,0> (9 instructions at 0000029B1695BEB0)
2 params, 3 slots, 1 upvalue, 2 locals, 0 constants, 1 function
	1	[-]	MOVE     	2 0
	2	[-]	NOT      	2 2
	3	[-]	TEST     	2 0
	4	[-]	JMP      	0 2	; to 7
	5	[-]	MOVE     	2 0
	6	[-]	RETURN   	2 2
	7	[-]	CLOSURE  	2 0	; 0000029B1695BF30
	8	[-]	RETURN   	2 2
	9	[-]	RETURN   	0 1
constants (0) for 0000029B1695BEB0:
locals (2) for 0000029B1695BEB0:
	0	method	1	11
	1	_this	1	11
upvalues (1) for 0000029B1695BEB0:
	0	_ENV	0	0

main <canvas.lua:0,0> (17 instructions at 0000029B1695BF30)
1+ param, 6 slots, 3 upvalues, 1 local, 3 constants, 0 functions
	1	[-]	NEWTABLE 	1 0 0
	2	[-]	VARARG   	2 0
	3	[-]	SETLIST  	1 0 1	; 1
	4	[-]	SETTABLE 	1 -1 0	; 0 -
	5	[-]	MOVE     	0 1
	6	[-]	GETUPVAL 	1 0	; method
	7	[-]	GETUPVAL 	2 1	; _this
	8	[-]	MOVE     	3 0
	9	[-]	LOADK    	4 -1	; 0
	10	[-]	GETTABLE 	3 3 4
	11	[-]	GETTABUP 	4 2 -2	; _ENV "table"
	12	[-]	GETTABLE 	4 4 -3	; "unpack"
	13	[-]	MOVE     	5 0
	14	[-]	CALL     	4 2 0
	15	[-]	CALL     	1 0 2
	16	[-]	RETURN   	1 2
	17	[-]	RETURN   	0 1
constants (3) for 0000029B1695BF30:
	1	0
	2	"table"
	3	"unpack"
locals (1) for 0000029B1695BF30:
	0	params	1	19
upvalues (3) for 0000029B1695BF30:
	0	method	1	0
	1	_this	1	1
	2	_ENV	0	0

main <canvas.lua:0,0> (21 instructions at 0000029B16959DD0)
3+ params, 5 slots, 1 upvalue, 3 locals, 1 constant, 2 functions
	1	[-]	NEWTABLE 	3 0 0
	2	[-]	VARARG   	4 0
	3	[-]	SETLIST  	3 0 1	; 1
	4	[-]	SETTABLE 	3 -1 2	; 0 -
	5	[-]	MOVE     	2 3
	6	[-]	MOVE     	3 0
	7	[-]	NOT      	3 3
	8	[-]	TEST     	3 0
	9	[-]	JMP      	0 2	; to 12
	10	[-]	MOVE     	3 0
	11	[-]	RETURN   	3 2
	12	[-]	MOVE     	3 2
	13	[-]	LOADK    	4 -1	; 0
	14	[-]	GETTABLE 	3 3 4
	15	[-]	TEST     	3 0
	16	[-]	JMP      	0 2	; to 19
	17	[-]	CLOSURE  	3 0	; 0000029B16959E50
	18	[-]	RETURN   	3 2
	19	[-]	CLOSURE  	3 1	; 0000029B16959F40
	20	[-]	RETURN   	3 2
	21	[-]	RETURN   	0 1
constants (1) for 0000029B16959DD0:
	1	0
locals (3) for 0000029B16959DD0:
	0	method	1	23
	1	_this	1	23
	2	prependParams	1	23
upvalues (1) for 0000029B16959DD0:
	0	_ENV	0	0

main <canvas.lua:0,0> (24 instructions at 0000029B16959E50)
1+ param, 7 slots, 4 upvalues, 1 local, 3 constants, 0 functions
	1	[-]	NEWTABLE 	1 0 0
	2	[-]	VARARG   	2 0
	3	[-]	SETLIST  	1 0 1	; 1
	4	[-]	SETTABLE 	1 -1 0	; 0 -
	5	[-]	MOVE     	0 1
	6	[-]	GETUPVAL 	1 0	; method
	7	[-]	GETUPVAL 	2 1	; _this
	8	[-]	GETUPVAL 	3 2	; prependParams
	9	[-]	LOADK    	4 -1	; 0
	10	[-]	GETTABLE 	3 3 4
	11	[-]	GETTABUP 	4 3 -2	; _ENV "table"
	12	[-]	GETTABLE 	4 4 -3	; "unpack"
	13	[-]	GETUPVAL 	5 2	; prependParams
	14	[-]	CALL     	4 2 0
	15	[-]	MOVE     	4 0
	16	[-]	LOADK    	5 -1	; 0
	17	[-]	GETTABLE 	4 4 5
	18	[-]	GETTABUP 	5 3 -2	; _ENV "table"
	19	[-]	GETTABLE 	5 5 -3	; "unpack"
	20	[-]	MOVE     	6 0
	21	[-]	CALL     	5 2 0
	22	[-]	CALL     	1 0 2
	23	[-]	RETURN   	1 2
	24	[-]	RETURN   	0 1
constants (3) for 0000029B16959E50:
	1	0
	2	"table"
	3	"unpack"
locals (1) for 0000029B16959E50:
	0	params	1	26
upvalues (4) for 0000029B16959E50:
	0	method	1	0
	1	_this	1	1
	2	prependParams	1	2
	3	_ENV	0	0

main <canvas.lua:0,0> (21 instructions at 0000029B16959F40)
1+ param, 6 slots, 4 upvalues, 1 local, 3 constants, 0 functions
	1	[-]	NEWTABLE 	1 0 0
	2	[-]	VARARG   	2 0
	3	[-]	SETLIST  	1 0 1	; 1
	4	[-]	SETTABLE 	1 -1 0	; 0 -
	5	[-]	MOVE     	0 1
	6	[-]	GETUPVAL 	1 0	; prependParams
	7	[-]	TESTSET  	1 1 0
	8	[-]	JMP      	0 11	; to 20
	9	[-]	GETUPVAL 	1 1	; method
	10	[-]	GETUPVAL 	2 2	; _this
	11	[-]	MOVE     	3 0
	12	[-]	LOADK    	4 -1	; 0
	13	[-]	GETTABLE 	3 3 4
	14	[-]	GETTABUP 	4 3 -2	; _ENV "table"
	15	[-]	GETTABLE 	4 4 -3	; "unpack"
	16	[-]	MOVE     	5 0
	17	[-]	CALL     	4 2 0
	18	[-]	CALL     	1 0 2
	19	[-]	MOVE     	1 1
	20	[-]	RETURN   	1 2
	21	[-]	RETURN   	0 1
constants (3) for 0000029B16959F40:
	1	0
	2	"table"
	3	"unpack"
locals (1) for 0000029B16959F40:
	0	params	1	23
upvalues (4) for 0000029B16959F40:
	0	prependParams	1	2
	1	method	1	0
	2	_this	1	1
	3	_ENV	0	0

main <canvas.lua:0,0> (4 instructions at 0000029B16959FC0)
1 param, 3 slots, 1 upvalue, 1 local, 2 constants, 0 functions
	1	[2]	GETTABUP 	1 0 -1	; _ENV "gl"
	2	[2]	GETTABLE 	1 1 -2	; "init"
	3	[2]	CALL     	1 1 1
	4	[2]	RETURN   	0 1
constants (2) for 0000029B16959FC0:
	1	"gl"
	2	"init"
locals (1) for 0000029B16959FC0:
	0	this	1	6
upvalues (1) for 0000029B16959FC0:
	0	_ENV	0	0

main <canvas.lua:0,0> (1 instruction at 0000029B1695A040)
4 params, 4 slots, 0 upvalues, 4 locals, 0 constants, 0 functions
	1	[-]	RETURN   	0 1
constants (0) for 0000029B1695A040:
locals (4) for 0000029B1695A040:
	0	this	1	3
	1	eventName	1	3
	2	cb	1	3
	3	flag	1	3
upvalues (0) for 0000029B1695A040:

main <canvas.lua:0,0> (19 instructions at 0000029B1695A0C0)
5 params, 10 slots, 1 upvalue, 5 locals, 7 constants, 0 functions
	1	[3]	GETTABUP 	5 0 -1	; _ENV "error"
	2	[3]	NEWTABLE 	6 2 0
	3	[3]	LOADK    	7 -2	; "__proto"
	4	[3]	GETTABUP 	8 0 -3	; _ENV "Error"
	5	[3]	SETTABLE 	6 7 8
	6	[3]	LOADK    	7 -4	; "__index"
	7	[3]	GETTABUP 	8 0 -3	; _ENV "Error"
	8	[3]	SETTABLE 	6 7 8
	9	[3]	GETTABUP 	7 0 -5	; _ENV "setmetatable"
	10	[3]	MOVE     	8 6
	11	[3]	MOVE     	9 6
	12	[3]	CALL     	7 3 1
	13	[3]	SELF     	7 6 -6	; "constructor"
	14	[3]	TEST     	7 0
	15	[3]	JMP      	0 2	; to 18
	16	[3]	LOADK    	9 -7	; "Method not implemented."
	17	[3]	CALL     	7 3 1
	18	[3]	CALL     	5 2 1
	19	[3]	RETURN   	0 1
constants (7) for 0000029B1695A0C0:
	1	"error"
	2	"__proto"
	3	"Error"
	4	"__index"
	5	"setmetatable"
	6	"constructor"
	7	"Method not implemented."
locals (5) for 0000029B1695A0C0:
	0	this	1	21
	1	mode	1	21
	2	first	1	21
	3	count	1	21
	4	primcount	1	21
upvalues (1) for 0000029B1695A0C0:
	0	_ENV	0	0

main <canvas.lua:0,0> (19 instructions at 0000029B1695A1C0)
6 params, 11 slots, 1 upvalue, 6 locals, 7 constants, 0 functions
	1	[4]	GETTABUP 	6 0 -1	; _ENV "error"
	2	[4]	NEWTABLE 	7 2 0
	3	[4]	LOADK    	8 -2	; "__proto"
	4	[4]	GETTABUP 	9 0 -3	; _ENV "Error"
	5	[4]	SETTABLE 	7 8 9
	6	[4]	LOADK    	8 -4	; "__index"
	7	[4]	GETTABUP 	9 0 -3	; _ENV "Error"
	8	[4]	SETTABLE 	7 8 9
	9	[4]	GETTABUP 	8 0 -5	; _ENV "setmetatable"
	10	[4]	MOVE     	9 7
	11	[4]	MOVE     	10 7
	12	[4]	CALL     	8 3 1
	13	[4]	SELF     	8 7 -6	; "constructor"
	14	[4]	TEST     	8 0
	15	[4]	JMP      	0 2	; to 18
	16	[4]	LOADK    	10 -7	; "Method not implemented."
	17	[4]	CALL     	8 3 1
	18	[4]	CALL     	6 2 1
	19	[4]	RETURN   	0 1
constants (7) for 0000029B1695A1C0:
	1	"error"
	2	"__proto"
	3	"Error"
	4	"__index"
	5	"setmetatable"
	6	"constructor"
	7	"Method not implemented."
locals (6) for 0000029B1695A1C0:
	0	this	1	21
	1	mode	1	21
	2	count	1	21
	3	type	1	21
	4	offset	1	21
	5	primcount	1	21
upvalues (1) for 0000029B1695A1C0:
	0	_ENV	0	0

main <canvas.lua:0,0> (19 instructions at 0000029B1695E1A0)
3 params, 8 slots, 1 upvalue, 3 locals, 7 constants, 0 functions
	1	[5]	GETTABUP 	3 0 -1	; _ENV "error"
	2	[5]	NEWTABLE 	4 2 0
	3	[5]	LOADK    	5 -2	; "__proto"
	4	[5]	GETTABUP 	6 0 -3	; _ENV "Error"
	5	[5]	SETTABLE 	4 5 6
	6	[5]	LOADK    	5 -4	; "__index"
	7	[5]	GETTABUP 	6 0 -3	; _ENV "Error"
	8	[5]	SETTABLE 	4 5 6
	9	[5]	GETTABUP 	5 0 -5	; _ENV "setmetatable"
	10	[5]	MOVE     	6 4
	11	[5]	MOVE     	7 4
	12	[5]	CALL     	5 3 1
	13	[5]	SELF     	5 4 -6	; "constructor"
	14	[5]	TEST     	5 0
	15	[5]	JMP      	0 2	; to 18
	16	[5]	LOADK    	7 -7	; "Method not implemented."
	17	[5]	CALL     	5 3 1
	18	[5]	CALL     	3 2 1
	19	[5]	RETURN   	0 1
constants (7) for 0000029B1695E1A0:
	1	"error"
	2	"__proto"
	3	"Error"
	4	"__index"
	5	"setmetatable"
	6	"constructor"
	7	"Method not implemented."
locals (3) for 0000029B1695E1A0:
	0	this	1	21
	1	index	1	21
	2	divisor	1	21
upvalues (1) for 0000029B1695E1A0:
	0	_ENV	0	0

main <canvas.lua:0,0> (19 instructions at 0000029B1695DEA0)
1 param, 6 slots, 1 upvalue, 1 local, 7 constants, 0 functions
	1	[6]	GETTABUP 	1 0 -1	; _ENV "error"
	2	[6]	NEWTABLE 	2 2 0
	3	[6]	LOADK    	3 -2	; "__proto"
	4	[6]	GETTABUP 	4 0 -3	; _ENV "Error"
	5	[6]	SETTABLE 	2 3 4
	6	[6]	LOADK    	3 -4	; "__index"
	7	[6]	GETTABUP 	4 0 -3	; _ENV "Error"
	8	[6]	SETTABLE 	2 3 4
	9	[6]	GETTABUP 	3 0 -5	; _ENV "setmetatable"
	10	[6]	MOVE     	4 2
	11	[6]	MOVE     	5 2
	12	[6]	CALL     	3 3 1
	13	[6]	SELF     	3 2 -6	; "constructor"
	14	[6]	TEST     	3 0
	15	[6]	JMP      	0 2	; to 18
	16	[6]	LOADK    	5 -7	; "Method not implemented."
	17	[6]	CALL     	3 3 1
	18	[6]	CALL     	1 2 1
	19	[6]	RETURN   	0 1
constants (7) for 0000029B1695DEA0:
	1	"error"
	2	"__proto"
	3	"Error"
	4	"__index"
	5	"setmetatable"
	6	"constructor"
	7	"Method not implemented."
locals (1) for 0000029B1695DEA0:
	0	this	1	21
upvalues (1) for 0000029B1695DEA0:
	0	_ENV	0	0

main <canvas.lua:0,0> (19 instructions at 0000029B1695E220)
2 params, 7 slots, 1 upvalue, 2 locals, 7 constants, 0 functions
	1	[7]	GETTABUP 	2 0 -1	; _ENV "error"
	2	[7]	NEWTABLE 	3 2 0
	3	[7]	LOADK    	4 -2	; "__proto"
	4	[7]	GETTABUP 	5 0 -3	; _ENV "Error"
	5	[7]	SETTABLE 	3 4 5
	6	[7]	LOADK    	4 -4	; "__index"
	7	[7]	GETTABUP 	5 0 -3	; _ENV "Error"
	8	[7]	SETTABLE 	3 4 5
	9	[7]	GETTABUP 	4 0 -5	; _ENV "setmetatable"
	10	[7]	MOVE     	5 3
	11	[7]	MOVE     	6 3
	12	[7]	CALL     	4 3 1
	13	[7]	SELF     	4 3 -6	; "constructor"
	14	[7]	TEST     	4 0
	15	[7]	JMP      	0 2	; to 18
	16	[7]	LOADK    	6 -7	; "Method not implemented."
	17	[7]	CALL     	4 3 1
	18	[7]	CALL     	2 2 1
	19	[7]	RETURN   	0 1
constants (7) for 0000029B1695E220:
	1	"error"
	2	"__proto"
	3	"Error"
	4	"__index"
	5	"setmetatable"
	6	"constructor"
	7	"Method not implemented."
locals (2) for 0000029B1695E220:
	0	this	1	21
	1	vao	1	21
upvalues (1) for 0000029B1695E220:
	0	_ENV	0	0

main <canvas.lua:0,0> (19 instructions at 0000029B1695E2A0)
2 params, 7 slots, 1 upvalue, 2 locals, 7 constants, 0 functions
	1	[8]	GETTABUP 	2 0 -1	; _ENV "error"
	2	[8]	NEWTABLE 	3 2 0
	3	[8]	LOADK    	4 -2	; "__proto"
	4	[8]	GETTABUP 	5 0 -3	; _ENV "Error"
	5	[8]	SETTABLE 	3 4 5
	6	[8]	LOADK    	4 -4	; "__index"
	7	[8]	GETTABUP 	5 0 -3	; _ENV "Error"
	8	[8]	SETTABLE 	3 4 5
	9	[8]	GETTABUP 	4 0 -5	; _ENV "setmetatable"
	10	[8]	MOVE     	5 3
	11	[8]	MOVE     	6 3
	12	[8]	CALL     	4 3 1
	13	[8]	SELF     	4 3 -6	; "constructor"
	14	[8]	TEST     	4 0
	15	[8]	JMP      	0 2	; to 18
	16	[8]	LOADK    	6 -7	; "Method not implemented."
	17	[8]	CALL     	4 3 1
	18	[8]	CALL     	2 2 1
	19	[8]	RETURN   	0 1
constants (7) for 0000029B1695E2A0:
	1	"error"
	2	"__proto"
	3	"Error"
	4	"__index"
	5	"setmetatable"
	6	"constructor"
	7	"Method not implemented."
locals (2) for 0000029B1695E2A0:
	0	this	1	21
	1	vao	1	21
upvalues (1) for 0000029B1695E2A0:
	0	_ENV	0	0

main <canvas.lua:0,0> (19 instructions at 0000029B1695D9A0)
11 params, 16 slots, 1 upvalue, 11 locals, 7 constants, 0 functions
	1	[9]	GETTABUP 	11 0 -1	; _ENV "error"
	2	[9]	NEWTABLE 	12 2 0
	3	[9]	LOADK    	13 -2	; "__proto"
	4	[9]	GETTABUP 	14 0 -3	; _ENV "Error"
	5	[9]	SETTABLE 	12 13 14
	6	[9]	LOADK    	13 -4	; "__index"
	7	[9]	GETTABUP 	14 0 -3	; _ENV "Error"
	8	[9]	SETTABLE 	12 13 14
	9	[9]	GETTABUP 	13 0 -5	; _ENV "setmetatable"
	10	[9]	MOVE     	14 12
	11	[9]	MOVE     	15 12
	12	[9]	CALL     	13 3 1
	13	[9]	SELF     	13 12 -6	; "constructor"
	14	[9]	TEST     	13 0
	15	[9]	JMP      	0 2	; to 18
	16	[9]	LOADK    	15 -7	; "Method not implemented."
	17	[9]	CALL     	13 3 1
	18	[9]	CALL     	11 2 1
	19	[9]	RETURN   	0 1
constants (7) for 0000029B1695D9A0:
	1	"error"
	2	"__proto"
	3	"Error"
	4	"__index"
	5	"setmetatable"
	6	"constructor"
	7	"Method not implemented."
locals (11) for 0000029B1695D9A0:
	0	this	1	21
	1	srcX0	1	21
	2	srcY0	1	21
	3	srcX1	1	21
	4	srcY1	1	21
	5	dstX0	1	21
	6	dstY0	1	21
	7	dstX1	1	21
	8	dstY1	1	21
	9	mask	1	21
	10	filter	1	21
upvalues (1) for 0000029B1695D9A0:
	0	_ENV	0	0

main <canvas.lua:0,0> (19 instructions at 0000029B1695E4A0)
6 params, 11 slots, 1 upvalue, 6 locals, 7 constants, 0 functions
	1	[10]	GETTABUP 	6 0 -1	; _ENV "error"
	2	[10]	NEWTABLE 	7 2 0
	3	[10]	LOADK    	8 -2	; "__proto"
	4	[10]	GETTABUP 	9 0 -3	; _ENV "Error"
	5	[10]	SETTABLE 	7 8 9
	6	[10]	LOADK    	8 -4	; "__index"
	7	[10]	GETTABUP 	9 0 -3	; _ENV "Error"
	8	[10]	SETTABLE 	7 8 9
	9	[10]	GETTABUP 	8 0 -5	; _ENV "setmetatable"
	10	[10]	MOVE     	9 7
	11	[10]	MOVE     	10 7
	12	[10]	CALL     	8 3 1
	13	[10]	SELF     	8 7 -6	; "constructor"
	14	[10]	TEST     	8 0
	15	[10]	JMP      	0 2	; to 18
	16	[10]	LOADK    	10 -7	; "Method not implemented."
	17	[10]	CALL     	8 3 1
	18	[10]	CALL     	6 2 1
	19	[10]	RETURN   	0 1
constants (7) for 0000029B1695E4A0:
	1	"error"
	2	"__proto"
	3	"Error"
	4	"__index"
	5	"setmetatable"
	6	"constructor"
	7	"Method not implemented."
locals (6) for 0000029B1695E4A0:
	0	this	1	21
	1	target	1	21
	2	samples	1	21
	3	internalformat	1	21
	4	width	1	21
	5	height	1	21
upvalues (1) for 0000029B1695E4A0:
	0	_ENV	0	0

main <canvas.lua:0,0> (19 instructions at 0000029B1695E320)
4 params, 9 slots, 1 upvalue, 4 locals, 7 constants, 0 functions
	1	[11]	GETTABUP 	4 0 -1	; _ENV "error"
	2	[11]	NEWTABLE 	5 2 0
	3	[11]	LOADK    	6 -2	; "__proto"
	4	[11]	GETTABUP 	7 0 -3	; _ENV "Error"
	5	[11]	SETTABLE 	5 6 7
	6	[11]	LOADK    	6 -4	; "__index"
	7	[11]	GETTABUP 	7 0 -3	; _ENV "Error"
	8	[11]	SETTABLE 	5 6 7
	9	[11]	GETTABUP 	6 0 -5	; _ENV "setmetatable"
	10	[11]	MOVE     	7 5
	11	[11]	MOVE     	8 5
	12	[11]	CALL     	6 3 1
	13	[11]	SELF     	6 5 -6	; "constructor"
	14	[11]	TEST     	6 0
	15	[11]	JMP      	0 2	; to 18
	16	[11]	LOADK    	8 -7	; "Method not implemented."
	17	[11]	CALL     	6 3 1
	18	[11]	CALL     	4 2 1
	19	[11]	RETURN   	0 1
constants (7) for 0000029B1695E320:
	1	"error"
	2	"__proto"
	3	"Error"
	4	"__index"
	5	"setmetatable"
	6	"constructor"
	7	"Method not implemented."
locals (4) for 0000029B1695E320:
	0	this	1	21
	1	target	1	21
	2	index	1	21
	3	buffer	1	21
upvalues (1) for 0000029B1695E320:
	0	_ENV	0	0

main <canvas.lua:0,0> (19 instructions at 0000029B1695DC20)
3 params, 8 slots, 1 upvalue, 3 locals, 7 constants, 0 functions
	1	[12]	GETTABUP 	3 0 -1	; _ENV "error"
	2	[12]	NEWTABLE 	4 2 0
	3	[12]	LOADK    	5 -2	; "__proto"
	4	[12]	GETTABUP 	6 0 -3	; _ENV "Error"
	5	[12]	SETTABLE 	4 5 6
	6	[12]	LOADK    	5 -4	; "__index"
	7	[12]	GETTABUP 	6 0 -3	; _ENV "Error"
	8	[12]	SETTABLE 	4 5 6
	9	[12]	GETTABUP 	5 0 -5	; _ENV "setmetatable"
	10	[12]	MOVE     	6 4
	11	[12]	MOVE     	7 4
	12	[12]	CALL     	5 3 1
	13	[12]	SELF     	5 4 -6	; "constructor"
	14	[12]	TEST     	5 0
	15	[12]	JMP      	0 2	; to 18
	16	[12]	LOADK    	7 -7	; "Method not implemented."
	17	[12]	CALL     	5 3 1
	18	[12]	CALL     	3 2 1
	19	[12]	RETURN   	0 1
constants (7) for 0000029B1695DC20:
	1	"error"
	2	"__proto"
	3	"Error"
	4	"__index"
	5	"setmetatable"
	6	"constructor"
	7	"Method not implemented."
locals (3) for 0000029B1695DC20:
	0	this	1	21
	1	program	1	21
	2	uniformBlockName	1	21
upvalues (1) for 0000029B1695DC20:
	0	_ENV	0	0

main <canvas.lua:0,0> (19 instructions at 0000029B1695DA20)
4 params, 9 slots, 1 upvalue, 4 locals, 7 constants, 0 functions
	1	[13]	GETTABUP 	4 0 -1	; _ENV "error"
	2	[13]	NEWTABLE 	5 2 0
	3	[13]	LOADK    	6 -2	; "__proto"
	4	[13]	GETTABUP 	7 0 -3	; _ENV "Error"
	5	[13]	SETTABLE 	5 6 7
	6	[13]	LOADK    	6 -4	; "__index"
	7	[13]	GETTABUP 	7 0 -3	; _ENV "Error"
	8	[13]	SETTABLE 	5 6 7
	9	[13]	GETTABUP 	6 0 -5	; _ENV "setmetatable"
	10	[13]	MOVE     	7 5
	11	[13]	MOVE     	8 5
	12	[13]	CALL     	6 3 1
	13	[13]	SELF     	6 5 -6	; "constructor"
	14	[13]	TEST     	6 0
	15	[13]	JMP      	0 2	; to 18
	16	[13]	LOADK    	8 -7	; "Method not implemented."
	17	[13]	CALL     	6 3 1
	18	[13]	CALL     	4 2 1
	19	[13]	RETURN   	0 1
constants (7) for 0000029B1695DA20:
	1	"error"
	2	"__proto"
	3	"Error"
	4	"__index"
	5	"setmetatable"
	6	"constructor"
	7	"Method not implemented."
locals (4) for 0000029B1695DA20:
	0	this	1	21
	1	program	1	21
	2	uniformBlockIndex	1	21
	3	uniformBlockBinding	1	21
upvalues (1) for 0000029B1695DA20:
	0	_ENV	0	0

main <canvas.lua:0,0> (19 instructions at 0000029B1695E420)
1 param, 6 slots, 1 upvalue, 1 local, 7 constants, 0 functions
	1	[14]	GETTABUP 	1 0 -1	; _ENV "error"
	2	[14]	NEWTABLE 	2 2 0
	3	[14]	LOADK    	3 -2	; "__proto"
	4	[14]	GETTABUP 	4 0 -3	; _ENV "Error"
	5	[14]	SETTABLE 	2 3 4
	6	[14]	LOADK    	3 -4	; "__index"
	7	[14]	GETTABUP 	4 0 -3	; _ENV "Error"
	8	[14]	SETTABLE 	2 3 4
	9	[14]	GETTABUP 	3 0 -5	; _ENV "setmetatable"
	10	[14]	MOVE     	4 2
	11	[14]	MOVE     	5 2
	12	[14]	CALL     	3 3 1
	13	[14]	SELF     	3 2 -6	; "constructor"
	14	[14]	TEST     	3 0
	15	[14]	JMP      	0 2	; to 18
	16	[14]	LOADK    	5 -7	; "Method not implemented."
	17	[14]	CALL     	3 3 1
	18	[14]	CALL     	1 2 1
	19	[14]	RETURN   	0 1
constants (7) for 0000029B1695E420:
	1	"error"
	2	"__proto"
	3	"Error"
	4	"__index"
	5	"setmetatable"
	6	"constructor"
	7	"Method not implemented."
locals (1) for 0000029B1695E420:
	0	this	1	21
upvalues (1) for 0000029B1695E420:
	0	_ENV	0	0

main <canvas.lua:0,0> (19 instructions at 0000029B1695E520)
2 params, 7 slots, 1 upvalue, 2 locals, 7 constants, 0 functions
	1	[15]	GETTABUP 	2 0 -1	; _ENV "error"
	2	[15]	NEWTABLE 	3 2 0
	3	[15]	LOADK    	4 -2	; "__proto"
	4	[15]	GETTABUP 	5 0 -3	; _ENV "Error"
	5	[15]	SETTABLE 	3 4 5
	6	[15]	LOADK    	4 -4	; "__index"
	7	[15]	GETTABUP 	5 0 -3	; _ENV "Error"
	8	[15]	SETTABLE 	3 4 5
	9	[15]	GETTABUP 	4 0 -5	; _ENV "setmetatable"
	10	[15]	MOVE     	5 3
	11	[15]	MOVE     	6 3
	12	[15]	CALL     	4 3 1
	13	[15]	SELF     	4 3 -6	; "constructor"
	14	[15]	TEST     	4 0
	15	[15]	JMP      	0 2	; to 18
	16	[15]	LOADK    	6 -7	; "Method not implemented."
	17	[15]	CALL     	4 3 1
	18	[15]	CALL     	2 2 1
	19	[15]	RETURN   	0 1
constants (7) for 0000029B1695E520:
	1	"error"
	2	"__proto"
	3	"Error"
	4	"__index"
	5	"setmetatable"
	6	"constructor"
	7	"Method not implemented."
locals (2) for 0000029B1695E520:
	0	this	1	21
	1	query	1	21
upvalues (1) for 0000029B1695E520:
	0	_ENV	0	0

main <canvas.lua:0,0> (19 instructions at 0000029B1695DD20)
3 params, 8 slots, 1 upvalue, 3 locals, 7 constants, 0 functions
	1	[16]	GETTABUP 	3 0 -1	; _ENV "error"
	2	[16]	NEWTABLE 	4 2 0
	3	[16]	LOADK    	5 -2	; "__proto"
	4	[16]	GETTABUP 	6 0 -3	; _ENV "Error"
	5	[16]	SETTABLE 	4 5 6
	6	[16]	LOADK    	5 -4	; "__index"
	7	[16]	GETTABUP 	6 0 -3	; _ENV "Error"
	8	[16]	SETTABLE 	4 5 6
	9	[16]	GETTABUP 	5 0 -5	; _ENV "setmetatable"
	10	[16]	MOVE     	6 4
	11	[16]	MOVE     	7 4
	12	[16]	CALL     	5 3 1
	13	[16]	SELF     	5 4 -6	; "constructor"
	14	[16]	TEST     	5 0
	15	[16]	JMP      	0 2	; to 18
	16	[16]	LOADK    	7 -7	; "Method not implemented."
	17	[16]	CALL     	5 3 1
	18	[16]	CALL     	3 2 1
	19	[16]	RETURN   	0 1
constants (7) for 0000029B1695DD20:
	1	"error"
	2	"__proto"
	3	"Error"
	4	"__index"
	5	"setmetatable"
	6	"constructor"
	7	"Method not implemented."
locals (3) for 0000029B1695DD20:
	0	this	1	21
	1	target	1	21
	2	query	1	21
upvalues (1) for 0000029B1695DD20:
	0	_ENV	0	0

main <canvas.lua:0,0> (19 instructions at 0000029B1695D820)
2 params, 7 slots, 1 upvalue, 2 locals, 7 constants, 0 functions
	1	[17]	GETTABUP 	2 0 -1	; _ENV "error"
	2	[17]	NEWTABLE 	3 2 0
	3	[17]	LOADK    	4 -2	; "__proto"
	4	[17]	GETTABUP 	5 0 -3	; _ENV "Error"
	5	[17]	SETTABLE 	3 4 5
	6	[17]	LOADK    	4 -4	; "__index"
	7	[17]	GETTABUP 	5 0 -3	; _ENV "Error"
	8	[17]	SETTABLE 	3 4 5
	9	[17]	GETTABUP 	4 0 -5	; _ENV "setmetatable"
	10	[17]	MOVE     	5 3
	11	[17]	MOVE     	6 3
	12	[17]	CALL     	4 3 1
	13	[17]	SELF     	4 3 -6	; "constructor"
	14	[17]	TEST     	4 0
	15	[17]	JMP      	0 2	; to 18
	16	[17]	LOADK    	6 -7	; "Method not implemented."
	17	[17]	CALL     	4 3 1
	18	[17]	CALL     	2 2 1
	19	[17]	RETURN   	0 1
constants (7) for 0000029B1695D820:
	1	"error"
	2	"__proto"
	3	"Error"
	4	"__index"
	5	"setmetatable"
	6	"constructor"
	7	"Method not implemented."
locals (2) for 0000029B1695D820:
	0	this	1	21
	1	target	1	21
upvalues (1) for 0000029B1695D820:
	0	_ENV	0	0

main <canvas.lua:0,0> (19 instructions at 0000029B1695D8A0)
3 params, 8 slots, 1 upvalue, 3 locals, 7 constants, 0 functions
	1	[18]	GETTABUP 	3 0 -1	; _ENV "error"
	2	[18]	NEWTABLE 	4 2 0
	3	[18]	LOADK    	5 -2	; "__proto"
	4	[18]	GETTABUP 	6 0 -3	; _ENV "Error"
	5	[18]	SETTABLE 	4 5 6
	6	[18]	LOADK    	5 -4	; "__index"
	7	[18]	GETTABUP 	6 0 -3	; _ENV "Error"
	8	[18]	SETTABLE 	4 5 6
	9	[18]	GETTABUP 	5 0 -5	; _ENV "setmetatable"
	10	[18]	MOVE     	6 4
	11	[18]	MOVE     	7 4
	12	[18]	CALL     	5 3 1
	13	[18]	SELF     	5 4 -6	; "constructor"
	14	[18]	TEST     	5 0
	15	[18]	JMP      	0 2	; to 18
	16	[18]	LOADK    	7 -7	; "Method not implemented."
	17	[18]	CALL     	5 3 1
	18	[18]	CALL     	3 2 1
	19	[18]	RETURN   	0 1
constants (7) for 0000029B1695D8A0:
	1	"error"
	2	"__proto"
	3	"Error"
	4	"__index"
	5	"setmetatable"
	6	"constructor"
	7	"Method not implemented."
locals (3) for 0000029B1695D8A0:
	0	this	1	21
	1	query	1	21
	2	pname	1	21
upvalues (1) for 0000029B1695D8A0:
	0	_ENV	0	0

main <canvas.lua:0,0> (19 instructions at 0000029B1695DFA0)
3 params, 8 slots, 1 upvalue, 3 locals, 7 constants, 0 functions
	1	[19]	GETTABUP 	3 0 -1	; _ENV "error"
	2	[19]	NEWTABLE 	4 2 0
	3	[19]	LOADK    	5 -2	; "__proto"
	4	[19]	GETTABUP 	6 0 -3	; _ENV "Error"
	5	[19]	SETTABLE 	4 5 6
	6	[19]	LOADK    	5 -4	; "__index"
	7	[19]	GETTABUP 	6 0 -3	; _ENV "Error"
	8	[19]	SETTABLE 	4 5 6
	9	[19]	GETTABUP 	5 0 -5	; _ENV "setmetatable"
	10	[19]	MOVE     	6 4
	11	[19]	MOVE     	7 4
	12	[19]	CALL     	5 3 1
	13	[19]	SELF     	5 4 -6	; "constructor"
	14	[19]	TEST     	5 0
	15	[19]	JMP      	0 2	; to 18
	16	[19]	LOADK    	7 -7	; "Method not implemented."
	17	[19]	CALL     	5 3 1
	18	[19]	CALL     	3 2 1
	19	[19]	RETURN   	0 1
constants (7) for 0000029B1695DFA0:
	1	"error"
	2	"__proto"
	3	"Error"
	4	"__index"
	5	"setmetatable"
	6	"constructor"
	7	"Method not implemented."
locals (3) for 0000029B1695DFA0:
	0	this	1	21
	1	target	1	21
	2	pname	1	21
upvalues (1) for 0000029B1695DFA0:
	0	_ENV	0	0

main <canvas.lua:0,0> (19 instructions at 0000029B1695DE20)
2 params, 7 slots, 1 upvalue, 2 locals, 7 constants, 0 functions
	1	[20]	GETTABUP 	2 0 -1	; _ENV "error"
	2	[20]	NEWTABLE 	3 2 0
	3	[20]	LOADK    	4 -2	; "__proto"
	4	[20]	GETTABUP 	5 0 -3	; _ENV "Error"
	5	[20]	SETTABLE 	3 4 5
	6	[20]	LOADK    	4 -4	; "__index"
	7	[20]	GETTABUP 	5 0 -3	; _ENV "Error"
	8	[20]	SETTABLE 	3 4 5
	9	[20]	GETTABUP 	4 0 -5	; _ENV "setmetatable"
	10	[20]	MOVE     	5 3
	11	[20]	MOVE     	6 3
	12	[20]	CALL     	4 3 1
	13	[20]	SELF     	4 3 -6	; "constructor"
	14	[20]	TEST     	4 0
	15	[20]	JMP      	0 2	; to 18
	16	[20]	LOADK    	6 -7	; "Method not implemented."
	17	[20]	CALL     	4 3 1
	18	[20]	CALL     	2 2 1
	19	[20]	RETURN   	0 1
constants (7) for 0000029B1695DE20:
	1	"error"
	2	"__proto"
	3	"Error"
	4	"__index"
	5	"setmetatable"
	6	"constructor"
	7	"Method not implemented."
locals (2) for 0000029B1695DE20:
	0	this	1	21
	1	buffers	1	21
upvalues (1) for 0000029B1695DE20:
	0	_ENV	0	0

main <canvas.lua:0,0> (19 instructions at 0000029B16960150)
2 params, 7 slots, 1 upvalue, 2 locals, 7 constants, 0 functions
	1	[21]	GETTABUP 	2 0 -1	; _ENV "error"
	2	[21]	NEWTABLE 	3 2 0
	3	[21]	LOADK    	4 -2	; "__proto"
	4	[21]	GETTABUP 	5 0 -3	; _ENV "Error"
	5	[21]	SETTABLE 	3 4 5
	6	[21]	LOADK    	4 -4	; "__index"
	7	[21]	GETTABUP 	5 0 -3	; _ENV "Error"
	8	[21]	SETTABLE 	3 4 5
	9	[21]	GETTABUP 	4 0 -5	; _ENV "setmetatable"
	10	[21]	MOVE     	5 3
	11	[21]	MOVE     	6 3
	12	[21]	CALL     	4 3 1
	13	[21]	SELF     	4 3 -6	; "constructor"
	14	[21]	TEST     	4 0
	15	[21]	JMP      	0 2	; to 18
	16	[21]	LOADK    	6 -7	; "Method not implemented."
	17	[21]	CALL     	4 3 1
	18	[21]	CALL     	2 2 1
	19	[21]	RETURN   	0 1
constants (7) for 0000029B16960150:
	1	"error"
	2	"__proto"
	3	"Error"
	4	"__index"
	5	"setmetatable"
	6	"constructor"
	7	"Method not implemented."
locals (2) for 0000029B16960150:
	0	this	1	21
	1	src	1	21
upvalues (1) for 0000029B16960150:
	0	_ENV	0	0

main <canvas.lua:0,0> (19 instructions at 0000029B16961CD0)
12 params, 17 slots, 1 upvalue, 12 locals, 7 constants, 0 functions
	1	[22]	GETTABUP 	12 0 -1	; _ENV "error"
	2	[22]	NEWTABLE 	13 2 0
	3	[22]	LOADK    	14 -2	; "__proto"
	4	[22]	GETTABUP 	15 0 -3	; _ENV "Error"
	5	[22]	SETTABLE 	13 14 15
	6	[22]	LOADK    	14 -4	; "__index"
	7	[22]	GETTABUP 	15 0 -3	; _ENV "Error"
	8	[22]	SETTABLE 	13 14 15
	9	[22]	GETTABUP 	14 0 -5	; _ENV "setmetatable"
	10	[22]	MOVE     	15 13
	11	[22]	MOVE     	16 13
	12	[22]	CALL     	14 3 1
	13	[22]	SELF     	14 13 -6	; "constructor"
	14	[22]	TEST     	14 0
	15	[22]	JMP      	0 2	; to 18
	16	[22]	LOADK    	16 -7	; "Method not implemented."
	17	[22]	CALL     	14 3 1
	18	[22]	CALL     	12 2 1
	19	[22]	RETURN   	0 1
constants (7) for 0000029B16961CD0:
	1	"error"
	2	"__proto"
	3	"Error"
	4	"__index"
	5	"setmetatable"
	6	"constructor"
	7	"Method not implemented."
locals (12) for 0000029B16961CD0:
	0	this	1	21
	1	target	1	21
	2	level	1	21
	3	internalformat	1	21
	4	width	1	21
	5	height	1	21
	6	depth	1	21
	7	border	1	21
	8	format	1	21
	9	type	1	21
	10	pixels	1	21
	11	offset	1	21
upvalues (1) for 0000029B16961CD0:
	0	_ENV	0	0

main <canvas.lua:0,0> (19 instructions at 0000029B16961750)
11 params, 16 slots, 1 upvalue, 11 locals, 7 constants, 0 functions
	1	[23]	GETTABUP 	11 0 -1	; _ENV "error"
	2	[23]	NEWTABLE 	12 2 0
	3	[23]	LOADK    	13 -2	; "__proto"
	4	[23]	GETTABUP 	14 0 -3	; _ENV "Error"
	5	[23]	SETTABLE 	12 13 14
	6	[23]	LOADK    	13 -4	; "__index"
	7	[23]	GETTABUP 	14 0 -3	; _ENV "Error"
	8	[23]	SETTABLE 	12 13 14
	9	[23]	GETTABUP 	13 0 -5	; _ENV "setmetatable"
	10	[23]	MOVE     	14 12
	11	[23]	MOVE     	15 12
	12	[23]	CALL     	13 3 1
	13	[23]	SELF     	13 12 -6	; "constructor"
	14	[23]	TEST     	13 0
	15	[23]	JMP      	0 2	; to 18
	16	[23]	LOADK    	15 -7	; "Method not implemented."
	17	[23]	CALL     	13 3 1
	18	[23]	CALL     	11 2 1
	19	[23]	RETURN   	0 1
constants (7) for 0000029B16961750:
	1	"error"
	2	"__proto"
	3	"Error"
	4	"__index"
	5	"setmetatable"
	6	"constructor"
	7	"Method not implemented."
locals (11) for 0000029B16961750:
	0	this	1	21
	1	target	1	21
	2	level	1	21
	3	internalformat	1	21
	4	width	1	21
	5	height	1	21
	6	depth	1	21
	7	border	1	21
	8	data	1	21
	9	offset	1	21
	10	length	1	21
upvalues (1) for 0000029B16961750:
	0	_ENV	0	0

main <canvas.lua:0,0> (19 instructions at 0000029B16960550)
1 param, 6 slots, 1 upvalue, 1 local, 7 constants, 0 functions
	1	[24]	GETTABUP 	1 0 -1	; _ENV "error"
	2	[24]	NEWTABLE 	2 2 0
	3	[24]	LOADK    	3 -2	; "__proto"
	4	[24]	GETTABUP 	4 0 -3	; _ENV "Error"
	5	[24]	SETTABLE 	2 3 4
	6	[24]	LOADK    	3 -4	; "__index"
	7	[24]	GETTABUP 	4 0 -3	; _ENV "Error"
	8	[24]	SETTABLE 	2 3 4
	9	[24]	GETTABUP 	3 0 -5	; _ENV "setmetatable"
	10	[24]	MOVE     	4 2
	11	[24]	MOVE     	5 2
	12	[24]	CALL     	3 3 1
	13	[24]	SELF     	3 2 -6	; "constructor"
	14	[24]	TEST     	3 0
	15	[24]	JMP      	0 2	; to 18
	16	[24]	LOADK    	5 -7	; "Method not implemented."
	17	[24]	CALL     	3 3 1
	18	[24]	CALL     	1 2 1
	19	[24]	RETURN   	0 1
constants (7) for 0000029B16960550:
	1	"error"
	2	"__proto"
	3	"Error"
	4	"__index"
	5	"setmetatable"
	6	"constructor"
	7	"Method not implemented."
locals (1) for 0000029B16960550:
	0	this	1	21
upvalues (1) for 0000029B16960550:
	0	_ENV	0	0

main <canvas.lua:0,0> (19 instructions at 0000029B16961150)
2 params, 7 slots, 1 upvalue, 2 locals, 7 constants, 0 functions
	1	[25]	GETTABUP 	2 0 -1	; _ENV "error"
	2	[25]	NEWTABLE 	3 2 0
	3	[25]	LOADK    	4 -2	; "__proto"
	4	[25]	GETTABUP 	5 0 -3	; _ENV "Error"
	5	[25]	SETTABLE 	3 4 5
	6	[25]	LOADK    	4 -4	; "__index"
	7	[25]	GETTABUP 	5 0 -3	; _ENV "Error"
	8	[25]	SETTABLE 	3 4 5
	9	[25]	GETTABUP 	4 0 -5	; _ENV "setmetatable"
	10	[25]	MOVE     	5 3
	11	[25]	MOVE     	6 3
	12	[25]	CALL     	4 3 1
	13	[25]	SELF     	4 3 -6	; "constructor"
	14	[25]	TEST     	4 0
	15	[25]	JMP      	0 2	; to 18
	16	[25]	LOADK    	6 -7	; "Method not implemented."
	17	[25]	CALL     	4 3 1
	18	[25]	CALL     	2 2 1
	19	[25]	RETURN   	0 1
constants (7) for 0000029B16961150:
	1	"error"
	2	"__proto"
	3	"Error"
	4	"__index"
	5	"setmetatable"
	6	"constructor"
	7	"Method not implemented."
locals (2) for 0000029B16961150:
	0	this	1	21
	1	transformFeedbac	1	21
upvalues (1) for 0000029B16961150:
	0	_ENV	0	0

main <canvas.lua:0,0> (19 instructions at 0000029B16960350)
3 params, 8 slots, 1 upvalue, 3 locals, 7 constants, 0 functions
	1	[26]	GETTABUP 	3 0 -1	; _ENV "error"
	2	[26]	NEWTABLE 	4 2 0
	3	[26]	LOADK    	5 -2	; "__proto"
	4	[26]	GETTABUP 	6 0 -3	; _ENV "Error"
	5	[26]	SETTABLE 	4 5 6
	6	[26]	LOADK    	5 -4	; "__index"
	7	[26]	GETTABUP 	6 0 -3	; _ENV "Error"
	8	[26]	SETTABLE 	4 5 6
	9	[26]	GETTABUP 	5 0 -5	; _ENV "setmetatable"
	10	[26]	MOVE     	6 4
	11	[26]	MOVE     	7 4
	12	[26]	CALL     	5 3 1
	13	[26]	SELF     	5 4 -6	; "constructor"
	14	[26]	TEST     	5 0
	15	[26]	JMP      	0 2	; to 18
	16	[26]	LOADK    	7 -7	; "Method not implemented."
	17	[26]	CALL     	5 3 1
	18	[26]	CALL     	3 2 1
	19	[26]	RETURN   	0 1
constants (7) for 0000029B16960350:
	1	"error"
	2	"__proto"
	3	"Error"
	4	"__index"
	5	"setmetatable"
	6	"constructor"
	7	"Method not implemented."
locals (3) for 0000029B16960350:
	0	this	1	21
	1	target	1	21
	2	transformFeedback	1	21
upvalues (1) for 0000029B16960350:
	0	_ENV	0	0

main <canvas.lua:0,0> (19 instructions at 0000029B16961350)
2 params, 7 slots, 1 upvalue, 2 locals, 7 constants, 0 functions
	1	[27]	GETTABUP 	2 0 -1	; _ENV "error"
	2	[27]	NEWTABLE 	3 2 0
	3	[27]	LOADK    	4 -2	; "__proto"
	4	[27]	GETTABUP 	5 0 -3	; _ENV "Error"
	5	[27]	SETTABLE 	3 4 5
	6	[27]	LOADK    	4 -4	; "__index"
	7	[27]	GETTABUP 	5 0 -3	; _ENV "Error"
	8	[27]	SETTABLE 	3 4 5
	9	[27]	GETTABUP 	4 0 -5	; _ENV "setmetatable"
	10	[27]	MOVE     	5 3
	11	[27]	MOVE     	6 3
	12	[27]	CALL     	4 3 1
	13	[27]	SELF     	4 3 -6	; "constructor"
	14	[27]	TEST     	4 0
	15	[27]	JMP      	0 2	; to 18
	16	[27]	LOADK    	6 -7	; "Method not implemented."
	17	[27]	CALL     	4 3 1
	18	[27]	CALL     	2 2 1
	19	[27]	RETURN   	0 1
constants (7) for 0000029B16961350:
	1	"error"
	2	"__proto"
	3	"Error"
	4	"__index"
	5	"setmetatable"
	6	"constructor"
	7	"Method not implemented."
locals (2) for 0000029B16961350:
	0	this	1	21
	1	primitiveMode	1	21
upvalues (1) for 0000029B16961350:
	0	_ENV	0	0

main <canvas.lua:0,0> (19 instructions at 0000029B169610D0)
1 param, 6 slots, 1 upvalue, 1 local, 7 constants, 0 functions
	1	[28]	GETTABUP 	1 0 -1	; _ENV "error"
	2	[28]	NEWTABLE 	2 2 0
	3	[28]	LOADK    	3 -2	; "__proto"
	4	[28]	GETTABUP 	4 0 -3	; _ENV "Error"
	5	[28]	SETTABLE 	2 3 4
	6	[28]	LOADK    	3 -4	; "__index"
	7	[28]	GETTABUP 	4 0 -3	; _ENV "Error"
	8	[28]	SETTABLE 	2 3 4
	9	[28]	GETTABUP 	3 0 -5	; _ENV "setmetatable"
	10	[28]	MOVE     	4 2
	11	[28]	MOVE     	5 2
	12	[28]	CALL     	3 3 1
	13	[28]	SELF     	3 2 -6	; "constructor"
	14	[28]	TEST     	3 0
	15	[28]	JMP      	0 2	; to 18
	16	[28]	LOADK    	5 -7	; "Method not implemented."
	17	[28]	CALL     	3 3 1
	18	[28]	CALL     	1 2 1
	19	[28]	RETURN   	0 1
constants (7) for 0000029B169610D0:
	1	"error"
	2	"__proto"
	3	"Error"
	4	"__index"
	5	"setmetatable"
	6	"constructor"
	7	"Method not implemented."
locals (1) for 0000029B169610D0:
	0	this	1	21
upvalues (1) for 0000029B169610D0:
	0	_ENV	0	0

main <canvas.lua:0,0> (19 instructions at 0000029B169601D0)
4 params, 9 slots, 1 upvalue, 4 locals, 7 constants, 0 functions
	1	[29]	GETTABUP 	4 0 -1	; _ENV "error"
	2	[29]	NEWTABLE 	5 2 0
	3	[29]	LOADK    	6 -2	; "__proto"
	4	[29]	GETTABUP 	7 0 -3	; _ENV "Error"
	5	[29]	SETTABLE 	5 6 7
	6	[29]	LOADK    	6 -4	; "__index"
	7	[29]	GETTABUP 	7 0 -3	; _ENV "Error"
	8	[29]	SETTABLE 	5 6 7
	9	[29]	GETTABUP 	6 0 -5	; _ENV "setmetatable"
	10	[29]	MOVE     	7 5
	11	[29]	MOVE     	8 5
	12	[29]	CALL     	6 3 1
	13	[29]	SELF     	6 5 -6	; "constructor"
	14	[29]	TEST     	6 0
	15	[29]	JMP      	0 2	; to 18
	16	[29]	LOADK    	8 -7	; "Method not implemented."
	17	[29]	CALL     	6 3 1
	18	[29]	CALL     	4 2 1
	19	[29]	RETURN   	0 1
constants (7) for 0000029B169601D0:
	1	"error"
	2	"__proto"
	3	"Error"
	4	"__index"
	5	"setmetatable"
	6	"constructor"
	7	"Method not implemented."
locals (4) for 0000029B169601D0:
	0	this	1	21
	1	program	1	21
	2	varyings	1	21
	3	bufferMode	1	21
upvalues (1) for 0000029B169601D0:
	0	_ENV	0	0

main <canvas.lua:0,0> (19 instructions at 0000029B16960250)
5 params, 10 slots, 1 upvalue, 5 locals, 7 constants, 0 functions
	1	[30]	GETTABUP 	5 0 -1	; _ENV "error"
	2	[30]	NEWTABLE 	6 2 0
	3	[30]	LOADK    	7 -2	; "__proto"
	4	[30]	GETTABUP 	8 0 -3	; _ENV "Error"
	5	[30]	SETTABLE 	6 7 8
	6	[30]	LOADK    	7 -4	; "__index"
	7	[30]	GETTABUP 	8 0 -3	; _ENV "Error"
	8	[30]	SETTABLE 	6 7 8
	9	[30]	GETTABUP 	7 0 -5	; _ENV "setmetatable"
	10	[30]	MOVE     	8 6
	11	[30]	MOVE     	9 6
	12	[30]	CALL     	7 3 1
	13	[30]	SELF     	7 6 -6	; "constructor"
	14	[30]	TEST     	7 0
	15	[30]	JMP      	0 2	; to 18
	16	[30]	LOADK    	9 -7	; "Method not implemented."
	17	[30]	CALL     	7 3 1
	18	[30]	CALL     	5 2 1
	19	[30]	RETURN   	0 1
constants (7) for 0000029B16960250:
	1	"error"
	2	"__proto"
	3	"Error"
	4	"__index"
	5	"setmetatable"
	6	"constructor"
	7	"Method not implemented."
locals (5) for 0000029B16960250:
	0	this	1	21
	1	buffer	1	21
	2	drawbuffer	1	21
	3	values	1	21
	4	srcOffset	1	21
upvalues (1) for 0000029B16960250:
	0	_ENV	0	0

main <canvas.lua:0,0> (19 instructions at 0000029B16960950)
5 params, 10 slots, 1 upvalue, 5 locals, 7 constants, 0 functions
	1	[31]	GETTABUP 	5 0 -1	; _ENV "error"
	2	[31]	NEWTABLE 	6 2 0
	3	[31]	LOADK    	7 -2	; "__proto"
	4	[31]	GETTABUP 	8 0 -3	; _ENV "Error"
	5	[31]	SETTABLE 	6 7 8
	6	[31]	LOADK    	7 -4	; "__index"
	7	[31]	GETTABUP 	8 0 -3	; _ENV "Error"
	8	[31]	SETTABLE 	6 7 8
	9	[31]	GETTABUP 	7 0 -5	; _ENV "setmetatable"
	10	[31]	MOVE     	8 6
	11	[31]	MOVE     	9 6
	12	[31]	CALL     	7 3 1
	13	[31]	SELF     	7 6 -6	; "constructor"
	14	[31]	TEST     	7 0
	15	[31]	JMP      	0 2	; to 18
	16	[31]	LOADK    	9 -7	; "Method not implemented."
	17	[31]	CALL     	7 3 1
	18	[31]	CALL     	5 2 1
	19	[31]	RETURN   	0 1
constants (7) for 0000029B16960950:
	1	"error"
	2	"__proto"
	3	"Error"
	4	"__index"
	5	"setmetatable"
	6	"constructor"
	7	"Method not implemented."
locals (5) for 0000029B16960950:
	0	this	1	21
	1	buffer	1	21
	2	drawbuffer	1	21
	3	values	1	21
	4	srcOffset	1	21
upvalues (1) for 0000029B16960950:
	0	_ENV	0	0

main <canvas.lua:0,0> (19 instructions at 0000029B16960D50)
5 params, 10 slots, 1 upvalue, 5 locals, 7 constants, 0 functions
	1	[32]	GETTABUP 	5 0 -1	; _ENV "error"
	2	[32]	NEWTABLE 	6 2 0
	3	[32]	LOADK    	7 -2	; "__proto"
	4	[32]	GETTABUP 	8 0 -3	; _ENV "Error"
	5	[32]	SETTABLE 	6 7 8
	6	[32]	LOADK    	7 -4	; "__index"
	7	[32]	GETTABUP 	8 0 -3	; _ENV "Error"
	8	[32]	SETTABLE 	6 7 8
	9	[32]	GETTABUP 	7 0 -5	; _ENV "setmetatable"
	10	[32]	MOVE     	8 6
	11	[32]	MOVE     	9 6
	12	[32]	CALL     	7 3 1
	13	[32]	SELF     	7 6 -6	; "constructor"
	14	[32]	TEST     	7 0
	15	[32]	JMP      	0 2	; to 18
	16	[32]	LOADK    	9 -7	; "Method not implemented."
	17	[32]	CALL     	7 3 1
	18	[32]	CALL     	5 2 1
	19	[32]	RETURN   	0 1
constants (7) for 0000029B16960D50:
	1	"error"
	2	"__proto"
	3	"Error"
	4	"__index"
	5	"setmetatable"
	6	"constructor"
	7	"Method not implemented."
locals (5) for 0000029B16960D50:
	0	this	1	21
	1	buffer	1	21
	2	drawbuffer	1	21
	3	values	1	21
	4	srcOffset	1	21
upvalues (1) for 0000029B16960D50:
	0	_ENV	0	0

main <canvas.lua:0,0> (19 instructions at 0000029B169600D0)
5 params, 10 slots, 1 upvalue, 5 locals, 7 constants, 0 functions
	1	[33]	GETTABUP 	5 0 -1	; _ENV "error"
	2	[33]	NEWTABLE 	6 2 0
	3	[33]	LOADK    	7 -2	; "__proto"
	4	[33]	GETTABUP 	8 0 -3	; _ENV "Error"
	5	[33]	SETTABLE 	6 7 8
	6	[33]	LOADK    	7 -4	; "__index"
	7	[33]	GETTABUP 	8 0 -3	; _ENV "Error"
	8	[33]	SETTABLE 	6 7 8
	9	[33]	GETTABUP 	7 0 -5	; _ENV "setmetatable"
	10	[33]	MOVE     	8 6
	11	[33]	MOVE     	9 6
	12	[33]	CALL     	7 3 1
	13	[33]	SELF     	7 6 -6	; "constructor"
	14	[33]	TEST     	7 0
	15	[33]	JMP      	0 2	; to 18
	16	[33]	LOADK    	9 -7	; "Method not implemented."
	17	[33]	CALL     	7 3 1
	18	[33]	CALL     	5 2 1
	19	[33]	RETURN   	0 1
constants (7) for 0000029B169600D0:
	1	"error"
	2	"__proto"
	3	"Error"
	4	"__index"
	5	"setmetatable"
	6	"constructor"
	7	"Method not implemented."
locals (5) for 0000029B169600D0:
	0	this	1	21
	1	buffer	1	21
	2	drawbuffer	1	21
	3	depth	1	21
	4	stencil	1	21
upvalues (1) for 0000029B169600D0:
	0	_ENV	0	0

main <canvas.lua:0,0> (19 instructions at 0000029B169602D0)
2 params, 7 slots, 1 upvalue, 2 locals, 7 constants, 0 functions
	1	[34]	GETTABUP 	2 0 -1	; _ENV "error"
	2	[34]	NEWTABLE 	3 2 0
	3	[34]	LOADK    	4 -2	; "__proto"
	4	[34]	GETTABUP 	5 0 -3	; _ENV "Error"
	5	[34]	SETTABLE 	3 4 5
	6	[34]	LOADK    	4 -4	; "__index"
	7	[34]	GETTABUP 	5 0 -3	; _ENV "Error"
	8	[34]	SETTABLE 	3 4 5
	9	[34]	GETTABUP 	4 0 -5	; _ENV "setmetatable"
	10	[34]	MOVE     	5 3
	11	[34]	MOVE     	6 3
	12	[34]	CALL     	4 3 1
	13	[34]	SELF     	4 3 -6	; "constructor"
	14	[34]	TEST     	4 0
	15	[34]	JMP      	0 2	; to 18
	16	[34]	LOADK    	6 -7	; "Method not implemented."
	17	[34]	CALL     	4 3 1
	18	[34]	CALL     	2 2 1
	19	[34]	RETURN   	0 1
constants (7) for 0000029B169602D0:
	1	"error"
	2	"__proto"
	3	"Error"
	4	"__index"
	5	"setmetatable"
	6	"constructor"
	7	"Method not implemented."
locals (2) for 0000029B169602D0:
	0	this	1	21
	1	texture	1	21
upvalues (1) for 0000029B169602D0:
	0	_ENV	0	0

main <canvas.lua:0,0> (19 instructions at 0000029B16960850)
3 params, 8 slots, 1 upvalue, 3 locals, 7 constants, 0 functions
	1	[35]	GETTABUP 	3 0 -1	; _ENV "error"
	2	[35]	NEWTABLE 	4 2 0
	3	[35]	LOADK    	5 -2	; "__proto"
	4	[35]	GETTABUP 	6 0 -3	; _ENV "Error"
	5	[35]	SETTABLE 	4 5 6
	6	[35]	LOADK    	5 -4	; "__index"
	7	[35]	GETTABUP 	6 0 -3	; _ENV "Error"
	8	[35]	SETTABLE 	4 5 6
	9	[35]	GETTABUP 	5 0 -5	; _ENV "setmetatable"
	10	[35]	MOVE     	6 4
	11	[35]	MOVE     	7 4
	12	[35]	CALL     	5 3 1
	13	[35]	SELF     	5 4 -6	; "constructor"
	14	[35]	TEST     	5 0
	15	[35]	JMP      	0 2	; to 18
	16	[35]	LOADK    	7 -7	; "Method not implemented."
	17	[35]	CALL     	5 3 1
	18	[35]	CALL     	3 2 1
	19	[35]	RETURN   	0 1
constants (7) for 0000029B16960850:
	1	"error"
	2	"__proto"
	3	"Error"
	4	"__index"
	5	"setmetatable"
	6	"constructor"
	7	"Method not implemented."
locals (3) for 0000029B16960850:
	0	this	1	21
	1	program	1	21
	2	shader	1	21
upvalues (1) for 0000029B16960850:
	0	_ENV	0	0

main <canvas.lua:0,0> (19 instructions at 0000029B16960AD0)
4 params, 9 slots, 1 upvalue, 4 locals, 7 constants, 0 functions
	1	[36]	GETTABUP 	4 0 -1	; _ENV "error"
	2	[36]	NEWTABLE 	5 2 0
	3	[36]	LOADK    	6 -2	; "__proto"
	4	[36]	GETTABUP 	7 0 -3	; _ENV "Error"
	5	[36]	SETTABLE 	5 6 7
	6	[36]	LOADK    	6 -4	; "__index"
	7	[36]	GETTABUP 	7 0 -3	; _ENV "Error"
	8	[36]	SETTABLE 	5 6 7
	9	[36]	GETTABUP 	6 0 -5	; _ENV "setmetatable"
	10	[36]	MOVE     	7 5
	11	[36]	MOVE     	8 5
	12	[36]	CALL     	6 3 1
	13	[36]	SELF     	6 5 -6	; "constructor"
	14	[36]	TEST     	6 0
	15	[36]	JMP      	0 2	; to 18
	16	[36]	LOADK    	8 -7	; "Method not implemented."
	17	[36]	CALL     	6 3 1
	18	[36]	CALL     	4 2 1
	19	[36]	RETURN   	0 1
constants (7) for 0000029B16960AD0:
	1	"error"
	2	"__proto"
	3	"Error"
	4	"__index"
	5	"setmetatable"
	6	"constructor"
	7	"Method not implemented."
locals (4) for 0000029B16960AD0:
	0	this	1	21
	1	program	1	21
	2	index	1	21
	3	name	1	21
upvalues (1) for 0000029B16960AD0:
	0	_ENV	0	0

main <canvas.lua:0,0> (19 instructions at 0000029B16960450)
3 params, 8 slots, 1 upvalue, 3 locals, 7 constants, 0 functions
	1	[37]	GETTABUP 	3 0 -1	; _ENV "error"
	2	[37]	NEWTABLE 	4 2 0
	3	[37]	LOADK    	5 -2	; "__proto"
	4	[37]	GETTABUP 	6 0 -3	; _ENV "Error"
	5	[37]	SETTABLE 	4 5 6
	6	[37]	LOADK    	5 -4	; "__index"
	7	[37]	GETTABUP 	6 0 -3	; _ENV "Error"
	8	[37]	SETTABLE 	4 5 6
	9	[37]	GETTABUP 	5 0 -5	; _ENV "setmetatable"
	10	[37]	MOVE     	6 4
	11	[37]	MOVE     	7 4
	12	[37]	CALL     	5 3 1
	13	[37]	SELF     	5 4 -6	; "constructor"
	14	[37]	TEST     	5 0
	15	[37]	JMP      	0 2	; to 18
	16	[37]	LOADK    	7 -7	; "Method not implemented."
	17	[37]	CALL     	5 3 1
	18	[37]	CALL     	3 2 1
	19	[37]	RETURN   	0 1
constants (7) for 0000029B16960450:
	1	"error"
	2	"__proto"
	3	"Error"
	4	"__index"
	5	"setmetatable"
	6	"constructor"
	7	"Method not implemented."
locals (3) for 0000029B16960450:
	0	this	1	21
	1	target	1	21
	2	buffer	1	21
upvalues (1) for 0000029B16960450:
	0	_ENV	0	0

main <canvas.lua:0,0> (19 instructions at 0000029B16961DD0)
3 params, 8 slots, 1 upvalue, 3 locals, 7 constants, 0 functions
	1	[38]	GETTABUP 	3 0 -1	; _ENV "error"
	2	[38]	NEWTABLE 	4 2 0
	3	[38]	LOADK    	5 -2	; "__proto"
	4	[38]	GETTABUP 	6 0 -3	; _ENV "Error"
	5	[38]	SETTABLE 	4 5 6
	6	[38]	LOADK    	5 -4	; "__index"
	7	[38]	GETTABUP 	6 0 -3	; _ENV "Error"
	8	[38]	SETTABLE 	4 5 6
	9	[38]	GETTABUP 	5 0 -5	; _ENV "setmetatable"
	10	[38]	MOVE     	6 4
	11	[38]	MOVE     	7 4
	12	[38]	CALL     	5 3 1
	13	[38]	SELF     	5 4 -6	; "constructor"
	14	[38]	TEST     	5 0
	15	[38]	JMP      	0 2	; to 18
	16	[38]	LOADK    	7 -7	; "Method not implemented."
	17	[38]	CALL     	5 3 1
	18	[38]	CALL     	3 2 1
	19	[38]	RETURN   	0 1
constants (7) for 0000029B16961DD0:
	1	"error"
	2	"__proto"
	3	"Error"
	4	"__index"
	5	"setmetatable"
	6	"constructor"
	7	"Method not implemented."
locals (3) for 0000029B16961DD0:
	0	this	1	21
	1	target	1	21
	2	framebuffer	1	21
upvalues (1) for 0000029B16961DD0:
	0	_ENV	0	0

main <canvas.lua:0,0> (19 instructions at 0000029B16961850)
3 params, 8 slots, 1 upvalue, 3 locals, 7 constants, 0 functions
	1	[39]	GETTABUP 	3 0 -1	; _ENV "error"
	2	[39]	NEWTABLE 	4 2 0
	3	[39]	LOADK    	5 -2	; "__proto"
	4	[39]	GETTABUP 	6 0 -3	; _ENV "Error"
	5	[39]	SETTABLE 	4 5 6
	6	[39]	LOADK    	5 -4	; "__index"
	7	[39]	GETTABUP 	6 0 -3	; _ENV "Error"
	8	[39]	SETTABLE 	4 5 6
	9	[39]	GETTABUP 	5 0 -5	; _ENV "setmetatable"
	10	[39]	MOVE     	6 4
	11	[39]	MOVE     	7 4
	12	[39]	CALL     	5 3 1
	13	[39]	SELF     	5 4 -6	; "constructor"
	14	[39]	TEST     	5 0
	15	[39]	JMP      	0 2	; to 18
	16	[39]	LOADK    	7 -7	; "Method not implemented."
	17	[39]	CALL     	5 3 1
	18	[39]	CALL     	3 2 1
	19	[39]	RETURN   	0 1
constants (7) for 0000029B16961850:
	1	"error"
	2	"__proto"
	3	"Error"
	4	"__index"
	5	"setmetatable"
	6	"constructor"
	7	"Method not implemented."
locals (3) for 0000029B16961850:
	0	this	1	21
	1	target	1	21
	2	renderbuffer	1	21
upvalues (1) for 0000029B16961850:
	0	_ENV	0	0

main <canvas.lua:0,0> (19 instructions at 0000029B16961950)
3 params, 8 slots, 1 upvalue, 3 locals, 7 constants, 0 functions
	1	[40]	GETTABUP 	3 0 -1	; _ENV "error"
	2	[40]	NEWTABLE 	4 2 0
	3	[40]	LOADK    	5 -2	; "__proto"
	4	[40]	GETTABUP 	6 0 -3	; _ENV "Error"
	5	[40]	SETTABLE 	4 5 6
	6	[40]	LOADK    	5 -4	; "__index"
	7	[40]	GETTABUP 	6 0 -3	; _ENV "Error"
	8	[40]	SETTABLE 	4 5 6
	9	[40]	GETTABUP 	5 0 -5	; _ENV "setmetatable"
	10	[40]	MOVE     	6 4
	11	[40]	MOVE     	7 4
	12	[40]	CALL     	5 3 1
	13	[40]	SELF     	5 4 -6	; "constructor"
	14	[40]	TEST     	5 0
	15	[40]	JMP      	0 2	; to 18
	16	[40]	LOADK    	7 -7	; "Method not implemented."
	17	[40]	CALL     	5 3 1
	18	[40]	CALL     	3 2 1
	19	[40]	RETURN   	0 1
constants (7) for 0000029B16961950:
	1	"error"
	2	"__proto"
	3	"Error"
	4	"__index"
	5	"setmetatable"
	6	"constructor"
	7	"Method not implemented."
locals (3) for 0000029B16961950:
	0	this	1	21
	1	target	1	21
	2	texture	1	21
upvalues (1) for 0000029B16961950:
	0	_ENV	0	0

main <canvas.lua:0,0> (19 instructions at 0000029B16961C50)
5 params, 10 slots, 1 upvalue, 5 locals, 7 constants, 0 functions
	1	[41]	GETTABUP 	5 0 -1	; _ENV "error"
	2	[41]	NEWTABLE 	6 2 0
	3	[41]	LOADK    	7 -2	; "__proto"
	4	[41]	GETTABUP 	8 0 -3	; _ENV "Error"
	5	[41]	SETTABLE 	6 7 8
	6	[41]	LOADK    	7 -4	; "__index"
	7	[41]	GETTABUP 	8 0 -3	; _ENV "Error"
	8	[41]	SETTABLE 	6 7 8
	9	[41]	GETTABUP 	7 0 -5	; _ENV "setmetatable"
	10	[41]	MOVE     	8 6
	11	[41]	MOVE     	9 6
	12	[41]	CALL     	7 3 1
	13	[41]	SELF     	7 6 -6	; "constructor"
	14	[41]	TEST     	7 0
	15	[41]	JMP      	0 2	; to 18
	16	[41]	LOADK    	9 -7	; "Method not implemented."
	17	[41]	CALL     	7 3 1
	18	[41]	CALL     	5 2 1
	19	[41]	RETURN   	0 1
constants (7) for 0000029B16961C50:
	1	"error"
	2	"__proto"
	3	"Error"
	4	"__index"
	5	"setmetatable"
	6	"constructor"
	7	"Method not implemented."
locals (5) for 0000029B16961C50:
	0	this	1	21
	1	red	1	21
	2	green	1	21
	3	blue	1	21
	4	alpha	1	21
upvalues (1) for 0000029B16961C50:
	0	_ENV	0	0

main <canvas.lua:0,0> (19 instructions at 0000029B16960B50)
2 params, 7 slots, 1 upvalue, 2 locals, 7 constants, 0 functions
	1	[42]	GETTABUP 	2 0 -1	; _ENV "error"
	2	[42]	NEWTABLE 	3 2 0
	3	[42]	LOADK    	4 -2	; "__proto"
	4	[42]	GETTABUP 	5 0 -3	; _ENV "Error"
	5	[42]	SETTABLE 	3 4 5
	6	[42]	LOADK    	4 -4	; "__index"
	7	[42]	GETTABUP 	5 0 -3	; _ENV "Error"
	8	[42]	SETTABLE 	3 4 5
	9	[42]	GETTABUP 	4 0 -5	; _ENV "setmetatable"
	10	[42]	MOVE     	5 3
	11	[42]	MOVE     	6 3
	12	[42]	CALL     	4 3 1
	13	[42]	SELF     	4 3 -6	; "constructor"
	14	[42]	TEST     	4 0
	15	[42]	JMP      	0 2	; to 18
	16	[42]	LOADK    	6 -7	; "Method not implemented."
	17	[42]	CALL     	4 3 1
	18	[42]	CALL     	2 2 1
	19	[42]	RETURN   	0 1
constants (7) for 0000029B16960B50:
	1	"error"
	2	"__proto"
	3	"Error"
	4	"__index"
	5	"setmetatable"
	6	"constructor"
	7	"Method not implemented."
locals (2) for 0000029B16960B50:
	0	this	1	21
	1	mode	1	21
upvalues (1) for 0000029B16960B50:
	0	_ENV	0	0

main <canvas.lua:0,0> (19 instructions at 0000029B169608D0)
3 params, 8 slots, 1 upvalue, 3 locals, 7 constants, 0 functions
	1	[43]	GETTABUP 	3 0 -1	; _ENV "error"
	2	[43]	NEWTABLE 	4 2 0
	3	[43]	LOADK    	5 -2	; "__proto"
	4	[43]	GETTABUP 	6 0 -3	; _ENV "Error"
	5	[43]	SETTABLE 	4 5 6
	6	[43]	LOADK    	5 -4	; "__index"
	7	[43]	GETTABUP 	6 0 -3	; _ENV "Error"
	8	[43]	SETTABLE 	4 5 6
	9	[43]	GETTABUP 	5 0 -5	; _ENV "setmetatable"
	10	[43]	MOVE     	6 4
	11	[43]	MOVE     	7 4
	12	[43]	CALL     	5 3 1
	13	[43]	SELF     	5 4 -6	; "constructor"
	14	[43]	TEST     	5 0
	15	[43]	JMP      	0 2	; to 18
	16	[43]	LOADK    	7 -7	; "Method not implemented."
	17	[43]	CALL     	5 3 1
	18	[43]	CALL     	3 2 1
	19	[43]	RETURN   	0 1
constants (7) for 0000029B169608D0:
	1	"error"
	2	"__proto"
	3	"Error"
	4	"__index"
	5	"setmetatable"
	6	"constructor"
	7	"Method not implemented."
locals (3) for 0000029B169608D0:
	0	this	1	21
	1	modeRGB	1	21
	2	modeAlpha	1	21
upvalues (1) for 0000029B169608D0:
	0	_ENV	0	0

main <canvas.lua:0,0> (19 instructions at 0000029B16960E50)
3 params, 8 slots, 1 upvalue, 3 locals, 7 constants, 0 functions
	1	[44]	GETTABUP 	3 0 -1	; _ENV "error"
	2	[44]	NEWTABLE 	4 2 0
	3	[44]	LOADK    	5 -2	; "__proto"
	4	[44]	GETTABUP 	6 0 -3	; _ENV "Error"
	5	[44]	SETTABLE 	4 5 6
	6	[44]	LOADK    	5 -4	; "__index"
	7	[44]	GETTABUP 	6 0 -3	; _ENV "Error"
	8	[44]	SETTABLE 	4 5 6
	9	[44]	GETTABUP 	5 0 -5	; _ENV "setmetatable"
	10	[44]	MOVE     	6 4
	11	[44]	MOVE     	7 4
	12	[44]	CALL     	5 3 1
	13	[44]	SELF     	5 4 -6	; "constructor"
	14	[44]	TEST     	5 0
	15	[44]	JMP      	0 2	; to 18
	16	[44]	LOADK    	7 -7	; "Method not implemented."
	17	[44]	CALL     	5 3 1
	18	[44]	CALL     	3 2 1
	19	[44]	RETURN   	0 1
constants (7) for 0000029B16960E50:
	1	"error"
	2	"__proto"
	3	"Error"
	4	"__index"
	5	"setmetatable"
	6	"constructor"
	7	"Method not implemented."
locals (3) for 0000029B16960E50:
	0	this	1	21
	1	sfactor	1	21
	2	dfactor	1	21
upvalues (1) for 0000029B16960E50:
	0	_ENV	0	0

main <canvas.lua:0,0> (19 instructions at 0000029B16961ED0)
5 params, 10 slots, 1 upvalue, 5 locals, 7 constants, 0 functions
	1	[45]	GETTABUP 	5 0 -1	; _ENV "error"
	2	[45]	NEWTABLE 	6 2 0
	3	[45]	LOADK    	7 -2	; "__proto"
	4	[45]	GETTABUP 	8 0 -3	; _ENV "Error"
	5	[45]	SETTABLE 	6 7 8
	6	[45]	LOADK    	7 -4	; "__index"
	7	[45]	GETTABUP 	8 0 -3	; _ENV "Error"
	8	[45]	SETTABLE 	6 7 8
	9	[45]	GETTABUP 	7 0 -5	; _ENV "setmetatable"
	10	[45]	MOVE     	8 6
	11	[45]	MOVE     	9 6
	12	[45]	CALL     	7 3 1
	13	[45]	SELF     	7 6 -6	; "constructor"
	14	[45]	TEST     	7 0
	15	[45]	JMP      	0 2	; to 18
	16	[45]	LOADK    	9 -7	; "Method not implemented."
	17	[45]	CALL     	7 3 1
	18	[45]	CALL     	5 2 1
	19	[45]	RETURN   	0 1
constants (7) for 0000029B16961ED0:
	1	"error"
	2	"__proto"
	3	"Error"
	4	"__index"
	5	"setmetatable"
	6	"constructor"
	7	"Method not implemented."
locals (5) for 0000029B16961ED0:
	0	this	1	21
	1	srcRGB	1	21
	2	dstRGB	1	21
	3	srcAlpha	1	21
	4	dstAlpha	1	21
upvalues (1) for 0000029B16961ED0:
	0	_ENV	0	0

main <canvas.lua:0,0> (19 instructions at 0000029B169619D0)
4 params, 9 slots, 1 upvalue, 4 locals, 7 constants, 0 functions
	1	[46]	GETTABUP 	4 0 -1	; _ENV "error"
	2	[46]	NEWTABLE 	5 2 0
	3	[46]	LOADK    	6 -2	; "__proto"
	4	[46]	GETTABUP 	7 0 -3	; _ENV "Error"
	5	[46]	SETTABLE 	5 6 7
	6	[46]	LOADK    	6 -4	; "__index"
	7	[46]	GETTABUP 	7 0 -3	; _ENV "Error"
	8	[46]	SETTABLE 	5 6 7
	9	[46]	GETTABUP 	6 0 -5	; _ENV "setmetatable"
	10	[46]	MOVE     	7 5
	11	[46]	MOVE     	8 5
	12	[46]	CALL     	6 3 1
	13	[46]	SELF     	6 5 -6	; "constructor"
	14	[46]	TEST     	6 0
	15	[46]	JMP      	0 2	; to 18
	16	[46]	LOADK    	8 -7	; "Method not implemented."
	17	[46]	CALL     	6 3 1
	18	[46]	CALL     	4 2 1
	19	[46]	RETURN   	0 1
constants (7) for 0000029B169619D0:
	1	"error"
	2	"__proto"
	3	"Error"
	4	"__index"
	5	"setmetatable"
	6	"constructor"
	7	"Method not implemented."
locals (4) for 0000029B169619D0:
	0	this	1	21
	1	target	1	21
	2	data	1	21
	3	usage	1	21
upvalues (1) for 0000029B169619D0:
	0	_ENV	0	0

main <canvas.lua:0,0> (19 instructions at 0000029B16961A50)
4 params, 9 slots, 1 upvalue, 4 locals, 7 constants, 0 functions
	1	[47]	GETTABUP 	4 0 -1	; _ENV "error"
	2	[47]	NEWTABLE 	5 2 0
	3	[47]	LOADK    	6 -2	; "__proto"
	4	[47]	GETTABUP 	7 0 -3	; _ENV "Error"
	5	[47]	SETTABLE 	5 6 7
	6	[47]	LOADK    	6 -4	; "__index"
	7	[47]	GETTABUP 	7 0 -3	; _ENV "Error"
	8	[47]	SETTABLE 	5 6 7
	9	[47]	GETTABUP 	6 0 -5	; _ENV "setmetatable"
	10	[47]	MOVE     	7 5
	11	[47]	MOVE     	8 5
	12	[47]	CALL     	6 3 1
	13	[47]	SELF     	6 5 -6	; "constructor"
	14	[47]	TEST     	6 0
	15	[47]	JMP      	0 2	; to 18
	16	[47]	LOADK    	8 -7	; "Method not implemented."
	17	[47]	CALL     	6 3 1
	18	[47]	CALL     	4 2 1
	19	[47]	RETURN   	0 1
constants (7) for 0000029B16961A50:
	1	"error"
	2	"__proto"
	3	"Error"
	4	"__index"
	5	"setmetatable"
	6	"constructor"
	7	"Method not implemented."
locals (4) for 0000029B16961A50:
	0	this	1	21
	1	target	1	21
	2	offset	1	21
	3	data	1	21
upvalues (1) for 0000029B16961A50:
	0	_ENV	0	0

main <canvas.lua:0,0> (19 instructions at 0000029B169604D0)
2 params, 7 slots, 1 upvalue, 2 locals, 7 constants, 0 functions
	1	[48]	GETTABUP 	2 0 -1	; _ENV "error"
	2	[48]	NEWTABLE 	3 2 0
	3	[48]	LOADK    	4 -2	; "__proto"
	4	[48]	GETTABUP 	5 0 -3	; _ENV "Error"
	5	[48]	SETTABLE 	3 4 5
	6	[48]	LOADK    	4 -4	; "__index"
	7	[48]	GETTABUP 	5 0 -3	; _ENV "Error"
	8	[48]	SETTABLE 	3 4 5
	9	[48]	GETTABUP 	4 0 -5	; _ENV "setmetatable"
	10	[48]	MOVE     	5 3
	11	[48]	MOVE     	6 3
	12	[48]	CALL     	4 3 1
	13	[48]	SELF     	4 3 -6	; "constructor"
	14	[48]	TEST     	4 0
	15	[48]	JMP      	0 2	; to 18
	16	[48]	LOADK    	6 -7	; "Method not implemented."
	17	[48]	CALL     	4 3 1
	18	[48]	CALL     	2 2 1
	19	[48]	RETURN   	0 1
constants (7) for 0000029B169604D0:
	1	"error"
	2	"__proto"
	3	"Error"
	4	"__index"
	5	"setmetatable"
	6	"constructor"
	7	"Method not implemented."
locals (2) for 0000029B169604D0:
	0	this	1	21
	1	target	1	21
upvalues (1) for 0000029B169604D0:
	0	_ENV	0	0

main <canvas.lua:0,0> (19 instructions at 0000029B169607D0)
2 params, 7 slots, 1 upvalue, 2 locals, 7 constants, 0 functions
	1	[49]	GETTABUP 	2 0 -1	; _ENV "error"
	2	[49]	NEWTABLE 	3 2 0
	3	[49]	LOADK    	4 -2	; "__proto"
	4	[49]	GETTABUP 	5 0 -3	; _ENV "Error"
	5	[49]	SETTABLE 	3 4 5
	6	[49]	LOADK    	4 -4	; "__index"
	7	[49]	GETTABUP 	5 0 -3	; _ENV "Error"
	8	[49]	SETTABLE 	3 4 5
	9	[49]	GETTABUP 	4 0 -5	; _ENV "setmetatable"
	10	[49]	MOVE     	5 3
	11	[49]	MOVE     	6 3
	12	[49]	CALL     	4 3 1
	13	[49]	SELF     	4 3 -6	; "constructor"
	14	[49]	TEST     	4 0
	15	[49]	JMP      	0 2	; to 18
	16	[49]	LOADK    	6 -7	; "Method not implemented."
	17	[49]	CALL     	4 3 1
	18	[49]	CALL     	2 2 1
	19	[49]	RETURN   	0 1
constants (7) for 0000029B169607D0:
	1	"error"
	2	"__proto"
	3	"Error"
	4	"__index"
	5	"setmetatable"
	6	"constructor"
	7	"Method not implemented."
locals (2) for 0000029B169607D0:
	0	this	1	21
	1	mask	1	21
upvalues (1) for 0000029B169607D0:
	0	_ENV	0	0

main <canvas.lua:0,0> (19 instructions at 0000029B16960ED0)
5 params, 10 slots, 1 upvalue, 5 locals, 7 constants, 0 functions
	1	[50]	GETTABUP 	5 0 -1	; _ENV "error"
	2	[50]	NEWTABLE 	6 2 0
	3	[50]	LOADK    	7 -2	; "__proto"
	4	[50]	GETTABUP 	8 0 -3	; _ENV "Error"
	5	[50]	SETTABLE 	6 7 8
	6	[50]	LOADK    	7 -4	; "__index"
	7	[50]	GETTABUP 	8 0 -3	; _ENV "Error"
	8	[50]	SETTABLE 	6 7 8
	9	[50]	GETTABUP 	7 0 -5	; _ENV "setmetatable"
	10	[50]	MOVE     	8 6
	11	[50]	MOVE     	9 6
	12	[50]	CALL     	7 3 1
	13	[50]	SELF     	7 6 -6	; "constructor"
	14	[50]	TEST     	7 0
	15	[50]	JMP      	0 2	; to 18
	16	[50]	LOADK    	9 -7	; "Method not implemented."
	17	[50]	CALL     	7 3 1
	18	[50]	CALL     	5 2 1
	19	[50]	RETURN   	0 1
constants (7) for 0000029B16960ED0:
	1	"error"
	2	"__proto"
	3	"Error"
	4	"__index"
	5	"setmetatable"
	6	"constructor"
	7	"Method not implemented."
locals (5) for 0000029B16960ED0:
	0	this	1	21
	1	red	1	21
	2	green	1	21
	3	blue	1	21
	4	alpha	1	21
upvalues (1) for 0000029B16960ED0:
	0	_ENV	0	0

main <canvas.lua:0,0> (19 instructions at 0000029B16961050)
2 params, 7 slots, 1 upvalue, 2 locals, 7 constants, 0 functions
	1	[51]	GETTABUP 	2 0 -1	; _ENV "error"
	2	[51]	NEWTABLE 	3 2 0
	3	[51]	LOADK    	4 -2	; "__proto"
	4	[51]	GETTABUP 	5 0 -3	; _ENV "Error"
	5	[51]	SETTABLE 	3 4 5
	6	[51]	LOADK    	4 -4	; "__index"
	7	[51]	GETTABUP 	5 0 -3	; _ENV "Error"
	8	[51]	SETTABLE 	3 4 5
	9	[51]	GETTABUP 	4 0 -5	; _ENV "setmetatable"
	10	[51]	MOVE     	5 3
	11	[51]	MOVE     	6 3
	12	[51]	CALL     	4 3 1
	13	[51]	SELF     	4 3 -6	; "constructor"
	14	[51]	TEST     	4 0
	15	[51]	JMP      	0 2	; to 18
	16	[51]	LOADK    	6 -7	; "Method not implemented."
	17	[51]	CALL     	4 3 1
	18	[51]	CALL     	2 2 1
	19	[51]	RETURN   	0 1
constants (7) for 0000029B16961050:
	1	"error"
	2	"__proto"
	3	"Error"
	4	"__index"
	5	"setmetatable"
	6	"constructor"
	7	"Method not implemented."
locals (2) for 0000029B16961050:
	0	this	1	21
	1	depth	1	21
upvalues (1) for 0000029B16961050:
	0	_ENV	0	0

main <canvas.lua:0,0> (19 instructions at 0000029B16966C60)
2 params, 7 slots, 1 upvalue, 2 locals, 7 constants, 0 functions
	1	[52]	GETTABUP 	2 0 -1	; _ENV "error"
	2	[52]	NEWTABLE 	3 2 0
	3	[52]	LOADK    	4 -2	; "__proto"
	4	[52]	GETTABUP 	5 0 -3	; _ENV "Error"
	5	[52]	SETTABLE 	3 4 5
	6	[52]	LOADK    	4 -4	; "__index"
	7	[52]	GETTABUP 	5 0 -3	; _ENV "Error"
	8	[52]	SETTABLE 	3 4 5
	9	[52]	GETTABUP 	4 0 -5	; _ENV "setmetatable"
	10	[52]	MOVE     	5 3
	11	[52]	MOVE     	6 3
	12	[52]	CALL     	4 3 1
	13	[52]	SELF     	4 3 -6	; "constructor"
	14	[52]	TEST     	4 0
	15	[52]	JMP      	0 2	; to 18
	16	[52]	LOADK    	6 -7	; "Method not implemented."
	17	[52]	CALL     	4 3 1
	18	[52]	CALL     	2 2 1
	19	[52]	RETURN   	0 1
constants (7) for 0000029B16966C60:
	1	"error"
	2	"__proto"
	3	"Error"
	4	"__index"
	5	"setmetatable"
	6	"constructor"
	7	"Method not implemented."
locals (2) for 0000029B16966C60:
	0	this	1	21
	1	s	1	21
upvalues (1) for 0000029B16966C60:
	0	_ENV	0	0

main <canvas.lua:0,0> (19 instructions at 0000029B16967C60)
5 params, 10 slots, 1 upvalue, 5 locals, 7 constants, 0 functions
	1	[53]	GETTABUP 	5 0 -1	; _ENV "error"
	2	[53]	NEWTABLE 	6 2 0
	3	[53]	LOADK    	7 -2	; "__proto"
	4	[53]	GETTABUP 	8 0 -3	; _ENV "Error"
	5	[53]	SETTABLE 	6 7 8
	6	[53]	LOADK    	7 -4	; "__index"
	7	[53]	GETTABUP 	8 0 -3	; _ENV "Error"
	8	[53]	SETTABLE 	6 7 8
	9	[53]	GETTABUP 	7 0 -5	; _ENV "setmetatable"
	10	[53]	MOVE     	8 6
	11	[53]	MOVE     	9 6
	12	[53]	CALL     	7 3 1
	13	[53]	SELF     	7 6 -6	; "constructor"
	14	[53]	TEST     	7 0
	15	[53]	JMP      	0 2	; to 18
	16	[53]	LOADK    	9 -7	; "Method not implemented."
	17	[53]	CALL     	7 3 1
	18	[53]	CALL     	5 2 1
	19	[53]	RETURN   	0 1
constants (7) for 0000029B16967C60:
	1	"error"
	2	"__proto"
	3	"Error"
	4	"__index"
	5	"setmetatable"
	6	"constructor"
	7	"Method not implemented."
locals (5) for 0000029B16967C60:
	0	this	1	21
	1	red	1	21
	2	green	1	21
	3	blue	1	21
	4	alpha	1	21
upvalues (1) for 0000029B16967C60:
	0	_ENV	0	0

main <canvas.lua:0,0> (19 instructions at 0000029B16967AE0)
2 params, 7 slots, 1 upvalue, 2 locals, 7 constants, 0 functions
	1	[54]	GETTABUP 	2 0 -1	; _ENV "error"
	2	[54]	NEWTABLE 	3 2 0
	3	[54]	LOADK    	4 -2	; "__proto"
	4	[54]	GETTABUP 	5 0 -3	; _ENV "Error"
	5	[54]	SETTABLE 	3 4 5
	6	[54]	LOADK    	4 -4	; "__index"
	7	[54]	GETTABUP 	5 0 -3	; _ENV "Error"
	8	[54]	SETTABLE 	3 4 5
	9	[54]	GETTABUP 	4 0 -5	; _ENV "setmetatable"
	10	[54]	MOVE     	5 3
	11	[54]	MOVE     	6 3
	12	[54]	CALL     	4 3 1
	13	[54]	SELF     	4 3 -6	; "constructor"
	14	[54]	TEST     	4 0
	15	[54]	JMP      	0 2	; to 18
	16	[54]	LOADK    	6 -7	; "Method not implemented."
	17	[54]	CALL     	4 3 1
	18	[54]	CALL     	2 2 1
	19	[54]	RETURN   	0 1
constants (7) for 0000029B16967AE0:
	1	"error"
	2	"__proto"
	3	"Error"
	4	"__index"
	5	"setmetatable"
	6	"constructor"
	7	"Method not implemented."
locals (2) for 0000029B16967AE0:
	0	this	1	21
	1	shader	1	21
upvalues (1) for 0000029B16967AE0:
	0	_ENV	0	0

main <canvas.lua:0,0> (19 instructions at 0000029B169672E0)
8 params, 13 slots, 1 upvalue, 8 locals, 7 constants, 0 functions
	1	[55]	GETTABUP 	8 0 -1	; _ENV "error"
	2	[55]	NEWTABLE 	9 2 0
	3	[55]	LOADK    	10 -2	; "__proto"
	4	[55]	GETTABUP 	11 0 -3	; _ENV "Error"
	5	[55]	SETTABLE 	9 10 11
	6	[55]	LOADK    	10 -4	; "__index"
	7	[55]	GETTABUP 	11 0 -3	; _ENV "Error"
	8	[55]	SETTABLE 	9 10 11
	9	[55]	GETTABUP 	10 0 -5	; _ENV "setmetatable"
	10	[55]	MOVE     	11 9
	11	[55]	MOVE     	12 9
	12	[55]	CALL     	10 3 1
	13	[55]	SELF     	10 9 -6	; "constructor"
	14	[55]	TEST     	10 0
	15	[55]	JMP      	0 2	; to 18
	16	[55]	LOADK    	12 -7	; "Method not implemented."
	17	[55]	CALL     	10 3 1
	18	[55]	CALL     	8 2 1
	19	[55]	RETURN   	0 1
constants (7) for 0000029B169672E0:
	1	"error"
	2	"__proto"
	3	"Error"
	4	"__index"
	5	"setmetatable"
	6	"constructor"
	7	"Method not implemented."
locals (8) for 0000029B169672E0:
	0	this	1	21
	1	target	1	21
	2	level	1	21
	3	internalformat	1	21
	4	width	1	21
	5	height	1	21
	6	border	1	21
	7	data	1	21
upvalues (1) for 0000029B169672E0:
	0	_ENV	0	0

main <canvas.lua:0,0> (19 instructions at 0000029B169674E0)
9 params, 14 slots, 1 upvalue, 9 locals, 7 constants, 0 functions
	1	[56]	GETTABUP 	9 0 -1	; _ENV "error"
	2	[56]	NEWTABLE 	10 2 0
	3	[56]	LOADK    	11 -2	; "__proto"
	4	[56]	GETTABUP 	12 0 -3	; _ENV "Error"
	5	[56]	SETTABLE 	10 11 12
	6	[56]	LOADK    	11 -4	; "__index"
	7	[56]	GETTABUP 	12 0 -3	; _ENV "Error"
	8	[56]	SETTABLE 	10 11 12
	9	[56]	GETTABUP 	11 0 -5	; _ENV "setmetatable"
	10	[56]	MOVE     	12 10
	11	[56]	MOVE     	13 10
	12	[56]	CALL     	11 3 1
	13	[56]	SELF     	11 10 -6	; "constructor"
	14	[56]	TEST     	11 0
	15	[56]	JMP      	0 2	; to 18
	16	[56]	LOADK    	13 -7	; "Method not implemented."
	17	[56]	CALL     	11 3 1
	18	[56]	CALL     	9 2 1
	19	[56]	RETURN   	0 1
constants (7) for 0000029B169674E0:
	1	"error"
	2	"__proto"
	3	"Error"
	4	"__index"
	5	"setmetatable"
	6	"constructor"
	7	"Method not implemented."
locals (9) for 0000029B169674E0:
	0	this	1	21
	1	target	1	21
	2	level	1	21
	3	xoffset	1	21
	4	yoffset	1	21
	5	width	1	21
	6	height	1	21
	7	format	1	21
	8	data	1	21
upvalues (1) for 0000029B169674E0:
	0	_ENV	0	0

main <canvas.lua:0,0> (19 instructions at 0000029B16965F60)
9 params, 14 slots, 1 upvalue, 9 locals, 7 constants, 0 functions
	1	[57]	GETTABUP 	9 0 -1	; _ENV "error"
	2	[57]	NEWTABLE 	10 2 0
	3	[57]	LOADK    	11 -2	; "__proto"
	4	[57]	GETTABUP 	12 0 -3	; _ENV "Error"
	5	[57]	SETTABLE 	10 11 12
	6	[57]	LOADK    	11 -4	; "__index"
	7	[57]	GETTABUP 	12 0 -3	; _ENV "Error"
	8	[57]	SETTABLE 	10 11 12
	9	[57]	GETTABUP 	11 0 -5	; _ENV "setmetatable"
	10	[57]	MOVE     	12 10
	11	[57]	MOVE     	13 10
	12	[57]	CALL     	11 3 1
	13	[57]	SELF     	11 10 -6	; "constructor"
	14	[57]	TEST     	11 0
	15	[57]	JMP      	0 2	; to 18
	16	[57]	LOADK    	13 -7	; "Method not implemented."
	17	[57]	CALL     	11 3 1
	18	[57]	CALL     	9 2 1
	19	[57]	RETURN   	0 1
constants (7) for 0000029B16965F60:
	1	"error"
	2	"__proto"
	3	"Error"
	4	"__index"
	5	"setmetatable"
	6	"constructor"
	7	"Method not implemented."
locals (9) for 0000029B16965F60:
	0	this	1	21
	1	target	1	21
	2	level	1	21
	3	internalformat	1	21
	4	x	1	21
	5	y	1	21
	6	width	1	21
	7	height	1	21
	8	border	1	21
upvalues (1) for 0000029B16965F60:
	0	_ENV	0	0

main <canvas.lua:0,0> (19 instructions at 0000029B16967160)
9 params, 14 slots, 1 upvalue, 9 locals, 7 constants, 0 functions
	1	[58]	GETTABUP 	9 0 -1	; _ENV "error"
	2	[58]	NEWTABLE 	10 2 0
	3	[58]	LOADK    	11 -2	; "__proto"
	4	[58]	GETTABUP 	12 0 -3	; _ENV "Error"
	5	[58]	SETTABLE 	10 11 12
	6	[58]	LOADK    	11 -4	; "__index"
	7	[58]	GETTABUP 	12 0 -3	; _ENV "Error"
	8	[58]	SETTABLE 	10 11 12
	9	[58]	GETTABUP 	11 0 -5	; _ENV "setmetatable"
	10	[58]	MOVE     	12 10
	11	[58]	MOVE     	13 10
	12	[58]	CALL     	11 3 1
	13	[58]	SELF     	11 10 -6	; "constructor"
	14	[58]	TEST     	11 0
	15	[58]	JMP      	0 2	; to 18
	16	[58]	LOADK    	13 -7	; "Method not implemented."
	17	[58]	CALL     	11 3 1
	18	[58]	CALL     	9 2 1
	19	[58]	RETURN   	0 1
constants (7) for 0000029B16967160:
	1	"error"
	2	"__proto"
	3	"Error"
	4	"__index"
	5	"setmetatable"
	6	"constructor"
	7	"Method not implemented."
locals (9) for 0000029B16967160:
	0	this	1	21
	1	target	1	21
	2	level	1	21
	3	xoffset	1	21
	4	yoffset	1	21
	5	x	1	21
	6	y	1	21
	7	width	1	21
	8	height	1	21
upvalues (1) for 0000029B16967160:
	0	_ENV	0	0

main <canvas.lua:0,0> (10 instructions at 0000029B16967460)
1 param, 5 slots, 1 upvalue, 2 locals, 3 constants, 0 functions
	1	[59]	GETTABUP 	2 0 -1	; _ENV "gl"
	2	[59]	GETTABLE 	2 2 -2	; "createBuffer"
	3	[59]	CALL     	2 1 2
	4	[59]	MOVE     	1 2
	5	[60]	NEWTABLE 	2 1 0
	6	[60]	LOADK    	3 -3	; "references"
	7	[60]	MOVE     	4 1
	8	[60]	SETTABLE 	2 3 4
	9	[60]	RETURN   	2 2
	10	[60]	RETURN   	0 1
constants (3) for 0000029B16967460:
	1	"gl"
	2	"createBuffer"
	3	"references"
locals (2) for 0000029B16967460:
	0	this	1	12
	1	val	2	12
upvalues (1) for 0000029B16967460:
	0	_ENV	0	0

main <canvas.lua:0,0> (19 instructions at 0000029B169661E0)
1 param, 6 slots, 1 upvalue, 1 local, 7 constants, 0 functions
	1	[61]	GETTABUP 	1 0 -1	; _ENV "error"
	2	[61]	NEWTABLE 	2 2 0
	3	[61]	LOADK    	3 -2	; "__proto"
	4	[61]	GETTABUP 	4 0 -3	; _ENV "Error"
	5	[61]	SETTABLE 	2 3 4
	6	[61]	LOADK    	3 -4	; "__index"
	7	[61]	GETTABUP 	4 0 -3	; _ENV "Error"
	8	[61]	SETTABLE 	2 3 4
	9	[61]	GETTABUP 	3 0 -5	; _ENV "setmetatable"
	10	[61]	MOVE     	4 2
	11	[61]	MOVE     	5 2
	12	[61]	CALL     	3 3 1
	13	[61]	SELF     	3 2 -6	; "constructor"
	14	[61]	TEST     	3 0
	15	[61]	JMP      	0 2	; to 18
	16	[61]	LOADK    	5 -7	; "Method not implemented."
	17	[61]	CALL     	3 3 1
	18	[61]	CALL     	1 2 1
	19	[61]	RETURN   	0 1
constants (7) for 0000029B169661E0:
	1	"error"
	2	"__proto"
	3	"Error"
	4	"__index"
	5	"setmetatable"
	6	"constructor"
	7	"Method not implemented."
locals (1) for 0000029B169661E0:
	0	this	1	21
upvalues (1) for 0000029B169661E0:
	0	_ENV	0	0

main <canvas.lua:0,0> (19 instructions at 0000029B16966DE0)
1 param, 6 slots, 1 upvalue, 1 local, 7 constants, 0 functions
	1	[62]	GETTABUP 	1 0 -1	; _ENV "error"
	2	[62]	NEWTABLE 	2 2 0
	3	[62]	LOADK    	3 -2	; "__proto"
	4	[62]	GETTABUP 	4 0 -3	; _ENV "Error"
	5	[62]	SETTABLE 	2 3 4
	6	[62]	LOADK    	3 -4	; "__index"
	7	[62]	GETTABUP 	4 0 -3	; _ENV "Error"
	8	[62]	SETTABLE 	2 3 4
	9	[62]	GETTABUP 	3 0 -5	; _ENV "setmetatable"
	10	[62]	MOVE     	4 2
	11	[62]	MOVE     	5 2
	12	[62]	CALL     	3 3 1
	13	[62]	SELF     	3 2 -6	; "constructor"
	14	[62]	TEST     	3 0
	15	[62]	JMP      	0 2	; to 18
	16	[62]	LOADK    	5 -7	; "Method not implemented."
	17	[62]	CALL     	3 3 1
	18	[62]	CALL     	1 2 1
	19	[62]	RETURN   	0 1
constants (7) for 0000029B16966DE0:
	1	"error"
	2	"__proto"
	3	"Error"
	4	"__index"
	5	"setmetatable"
	6	"constructor"
	7	"Method not implemented."
locals (1) for 0000029B16966DE0:
	0	this	1	21
upvalues (1) for 0000029B16966DE0:
	0	_ENV	0	0

main <canvas.lua:0,0> (19 instructions at 0000029B16966960)
1 param, 6 slots, 1 upvalue, 1 local, 7 constants, 0 functions
	1	[63]	GETTABUP 	1 0 -1	; _ENV "error"
	2	[63]	NEWTABLE 	2 2 0
	3	[63]	LOADK    	3 -2	; "__proto"
	4	[63]	GETTABUP 	4 0 -3	; _ENV "Error"
	5	[63]	SETTABLE 	2 3 4
	6	[63]	LOADK    	3 -4	; "__index"
	7	[63]	GETTABUP 	4 0 -3	; _ENV "Error"
	8	[63]	SETTABLE 	2 3 4
	9	[63]	GETTABUP 	3 0 -5	; _ENV "setmetatable"
	10	[63]	MOVE     	4 2
	11	[63]	MOVE     	5 2
	12	[63]	CALL     	3 3 1
	13	[63]	SELF     	3 2 -6	; "constructor"
	14	[63]	TEST     	3 0
	15	[63]	JMP      	0 2	; to 18
	16	[63]	LOADK    	5 -7	; "Method not implemented."
	17	[63]	CALL     	3 3 1
	18	[63]	CALL     	1 2 1
	19	[63]	RETURN   	0 1
constants (7) for 0000029B16966960:
	1	"error"
	2	"__proto"
	3	"Error"
	4	"__index"
	5	"setmetatable"
	6	"constructor"
	7	"Method not implemented."
locals (1) for 0000029B16966960:
	0	this	1	21
upvalues (1) for 0000029B16966960:
	0	_ENV	0	0

main <canvas.lua:0,0> (19 instructions at 0000029B16965FE0)
2 params, 7 slots, 1 upvalue, 2 locals, 7 constants, 0 functions
	1	[64]	GETTABUP 	2 0 -1	; _ENV "error"
	2	[64]	NEWTABLE 	3 2 0
	3	[64]	LOADK    	4 -2	; "__proto"
	4	[64]	GETTABUP 	5 0 -3	; _ENV "Error"
	5	[64]	SETTABLE 	3 4 5
	6	[64]	LOADK    	4 -4	; "__index"
	7	[64]	GETTABUP 	5 0 -3	; _ENV "Error"
	8	[64]	SETTABLE 	3 4 5
	9	[64]	GETTABUP 	4 0 -5	; _ENV "setmetatable"
	10	[64]	MOVE     	5 3
	11	[64]	MOVE     	6 3
	12	[64]	CALL     	4 3 1
	13	[64]	SELF     	4 3 -6	; "constructor"
	14	[64]	TEST     	4 0
	15	[64]	JMP      	0 2	; to 18
	16	[64]	LOADK    	6 -7	; "Method not implemented."
	17	[64]	CALL     	4 3 1
	18	[64]	CALL     	2 2 1
	19	[64]	RETURN   	0 1
constants (7) for 0000029B16965FE0:
	1	"error"
	2	"__proto"
	3	"Error"
	4	"__index"
	5	"setmetatable"
	6	"constructor"
	7	"Method not implemented."
locals (2) for 0000029B16965FE0:
	0	this	1	21
	1	type	1	21
upvalues (1) for 0000029B16965FE0:
	0	_ENV	0	0

main <canvas.lua:0,0> (19 instructions at 0000029B16966060)
1 param, 6 slots, 1 upvalue, 1 local, 7 constants, 0 functions
	1	[65]	GETTABUP 	1 0 -1	; _ENV "error"
	2	[65]	NEWTABLE 	2 2 0
	3	[65]	LOADK    	3 -2	; "__proto"
	4	[65]	GETTABUP 	4 0 -3	; _ENV "Error"
	5	[65]	SETTABLE 	2 3 4
	6	[65]	LOADK    	3 -4	; "__index"
	7	[65]	GETTABUP 	4 0 -3	; _ENV "Error"
	8	[65]	SETTABLE 	2 3 4
	9	[65]	GETTABUP 	3 0 -5	; _ENV "setmetatable"
	10	[65]	MOVE     	4 2
	11	[65]	MOVE     	5 2
	12	[65]	CALL     	3 3 1
	13	[65]	SELF     	3 2 -6	; "constructor"
	14	[65]	TEST     	3 0
	15	[65]	JMP      	0 2	; to 18
	16	[65]	LOADK    	5 -7	; "Method not implemented."
	17	[65]	CALL     	3 3 1
	18	[65]	CALL     	1 2 1
	19	[65]	RETURN   	0 1
constants (7) for 0000029B16966060:
	1	"error"
	2	"__proto"
	3	"Error"
	4	"__index"
	5	"setmetatable"
	6	"constructor"
	7	"Method not implemented."
locals (1) for 0000029B16966060:
	0	this	1	21
upvalues (1) for 0000029B16966060:
	0	_ENV	0	0

main <canvas.lua:0,0> (19 instructions at 0000029B16966260)
2 params, 7 slots, 1 upvalue, 2 locals, 7 constants, 0 functions
	1	[66]	GETTABUP 	2 0 -1	; _ENV "error"
	2	[66]	NEWTABLE 	3 2 0
	3	[66]	LOADK    	4 -2	; "__proto"
	4	[66]	GETTABUP 	5 0 -3	; _ENV "Error"
	5	[66]	SETTABLE 	3 4 5
	6	[66]	LOADK    	4 -4	; "__index"
	7	[66]	GETTABUP 	5 0 -3	; _ENV "Error"
	8	[66]	SETTABLE 	3 4 5
	9	[66]	GETTABUP 	4 0 -5	; _ENV "setmetatable"
	10	[66]	MOVE     	5 3
	11	[66]	MOVE     	6 3
	12	[66]	CALL     	4 3 1
	13	[66]	SELF     	4 3 -6	; "constructor"
	14	[66]	TEST     	4 0
	15	[66]	JMP      	0 2	; to 18
	16	[66]	LOADK    	6 -7	; "Method not implemented."
	17	[66]	CALL     	4 3 1
	18	[66]	CALL     	2 2 1
	19	[66]	RETURN   	0 1
constants (7) for 0000029B16966260:
	1	"error"
	2	"__proto"
	3	"Error"
	4	"__index"
	5	"setmetatable"
	6	"constructor"
	7	"Method not implemented."
locals (2) for 0000029B16966260:
	0	this	1	21
	1	mode	1	21
upvalues (1) for 0000029B16966260:
	0	_ENV	0	0

main <canvas.lua:0,0> (19 instructions at 0000029B169669E0)
2 params, 7 slots, 1 upvalue, 2 locals, 7 constants, 0 functions
	1	[67]	GETTABUP 	2 0 -1	; _ENV "error"
	2	[67]	NEWTABLE 	3 2 0
	3	[67]	LOADK    	4 -2	; "__proto"
	4	[67]	GETTABUP 	5 0 -3	; _ENV "Error"
	5	[67]	SETTABLE 	3 4 5
	6	[67]	LOADK    	4 -4	; "__index"
	7	[67]	GETTABUP 	5 0 -3	; _ENV "Error"
	8	[67]	SETTABLE 	3 4 5
	9	[67]	GETTABUP 	4 0 -5	; _ENV "setmetatable"
	10	[67]	MOVE     	5 3
	11	[67]	MOVE     	6 3
	12	[67]	CALL     	4 3 1
	13	[67]	SELF     	4 3 -6	; "constructor"
	14	[67]	TEST     	4 0
	15	[67]	JMP      	0 2	; to 18
	16	[67]	LOADK    	6 -7	; "Method not implemented."
	17	[67]	CALL     	4 3 1
	18	[67]	CALL     	2 2 1
	19	[67]	RETURN   	0 1
constants (7) for 0000029B169669E0:
	1	"error"
	2	"__proto"
	3	"Error"
	4	"__index"
	5	"setmetatable"
	6	"constructor"
	7	"Method not implemented."
locals (2) for 0000029B169669E0:
	0	this	1	21
	1	buffer	1	21
upvalues (1) for 0000029B169669E0:
	0	_ENV	0	0

main <canvas.lua:0,0> (19 instructions at 0000029B16967B60)
2 params, 7 slots, 1 upvalue, 2 locals, 7 constants, 0 functions
	1	[68]	GETTABUP 	2 0 -1	; _ENV "error"
	2	[68]	NEWTABLE 	3 2 0
	3	[68]	LOADK    	4 -2	; "__proto"
	4	[68]	GETTABUP 	5 0 -3	; _ENV "Error"
	5	[68]	SETTABLE 	3 4 5
	6	[68]	LOADK    	4 -4	; "__index"
	7	[68]	GETTABUP 	5 0 -3	; _ENV "Error"
	8	[68]	SETTABLE 	3 4 5
	9	[68]	GETTABUP 	4 0 -5	; _ENV "setmetatable"
	10	[68]	MOVE     	5 3
	11	[68]	MOVE     	6 3
	12	[68]	CALL     	4 3 1
	13	[68]	SELF     	4 3 -6	; "constructor"
	14	[68]	TEST     	4 0
	15	[68]	JMP      	0 2	; to 18
	16	[68]	LOADK    	6 -7	; "Method not implemented."
	17	[68]	CALL     	4 3 1
	18	[68]	CALL     	2 2 1
	19	[68]	RETURN   	0 1
constants (7) for 0000029B16967B60:
	1	"error"
	2	"__proto"
	3	"Error"
	4	"__index"
	5	"setmetatable"
	6	"constructor"
	7	"Method not implemented."
locals (2) for 0000029B16967B60:
	0	this	1	21
	1	framebuffer	1	21
upvalues (1) for 0000029B16967B60:
	0	_ENV	0	0

main <canvas.lua:0,0> (19 instructions at 0000029B169665E0)
2 params, 7 slots, 1 upvalue, 2 locals, 7 constants, 0 functions
	1	[69]	GETTABUP 	2 0 -1	; _ENV "error"
	2	[69]	NEWTABLE 	3 2 0
	3	[69]	LOADK    	4 -2	; "__proto"
	4	[69]	GETTABUP 	5 0 -3	; _ENV "Error"
	5	[69]	SETTABLE 	3 4 5
	6	[69]	LOADK    	4 -4	; "__index"
	7	[69]	GETTABUP 	5 0 -3	; _ENV "Error"
	8	[69]	SETTABLE 	3 4 5
	9	[69]	GETTABUP 	4 0 -5	; _ENV "setmetatable"
	10	[69]	MOVE     	5 3
	11	[69]	MOVE     	6 3
	12	[69]	CALL     	4 3 1
	13	[69]	SELF     	4 3 -6	; "constructor"
	14	[69]	TEST     	4 0
	15	[69]	JMP      	0 2	; to 18
	16	[69]	LOADK    	6 -7	; "Method not implemented."
	17	[69]	CALL     	4 3 1
	18	[69]	CALL     	2 2 1
	19	[69]	RETURN   	0 1
constants (7) for 0000029B169665E0:
	1	"error"
	2	"__proto"
	3	"Error"
	4	"__index"
	5	"setmetatable"
	6	"constructor"
	7	"Method not implemented."
locals (2) for 0000029B169665E0:
	0	this	1	21
	1	program	1	21
upvalues (1) for 0000029B169665E0:
	0	_ENV	0	0

main <canvas.lua:0,0> (19 instructions at 0000029B16966B60)
2 params, 7 slots, 1 upvalue, 2 locals, 7 constants, 0 functions
	1	[70]	GETTABUP 	2 0 -1	; _ENV "error"
	2	[70]	NEWTABLE 	3 2 0
	3	[70]	LOADK    	4 -2	; "__proto"
	4	[70]	GETTABUP 	5 0 -3	; _ENV "Error"
	5	[70]	SETTABLE 	3 4 5
	6	[70]	LOADK    	4 -4	; "__index"
	7	[70]	GETTABUP 	5 0 -3	; _ENV "Error"
	8	[70]	SETTABLE 	3 4 5
	9	[70]	GETTABUP 	4 0 -5	; _ENV "setmetatable"
	10	[70]	MOVE     	5 3
	11	[70]	MOVE     	6 3
	12	[70]	CALL     	4 3 1
	13	[70]	SELF     	4 3 -6	; "constructor"
	14	[70]	TEST     	4 0
	15	[70]	JMP      	0 2	; to 18
	16	[70]	LOADK    	6 -7	; "Method not implemented."
	17	[70]	CALL     	4 3 1
	18	[70]	CALL     	2 2 1
	19	[70]	RETURN   	0 1
constants (7) for 0000029B16966B60:
	1	"error"
	2	"__proto"
	3	"Error"
	4	"__index"
	5	"setmetatable"
	6	"constructor"
	7	"Method not implemented."
locals (2) for 0000029B16966B60:
	0	this	1	21
	1	renderbuffer	1	21
upvalues (1) for 0000029B16966B60:
	0	_ENV	0	0

main <canvas.lua:0,0> (19 instructions at 0000029B16967BE0)
2 params, 7 slots, 1 upvalue, 2 locals, 7 constants, 0 functions
	1	[71]	GETTABUP 	2 0 -1	; _ENV "error"
	2	[71]	NEWTABLE 	3 2 0
	3	[71]	LOADK    	4 -2	; "__proto"
	4	[71]	GETTABUP 	5 0 -3	; _ENV "Error"
	5	[71]	SETTABLE 	3 4 5
	6	[71]	LOADK    	4 -4	; "__index"
	7	[71]	GETTABUP 	5 0 -3	; _ENV "Error"
	8	[71]	SETTABLE 	3 4 5
	9	[71]	GETTABUP 	4 0 -5	; _ENV "setmetatable"
	10	[71]	MOVE     	5 3
	11	[71]	MOVE     	6 3
	12	[71]	CALL     	4 3 1
	13	[71]	SELF     	4 3 -6	; "constructor"
	14	[71]	TEST     	4 0
	15	[71]	JMP      	0 2	; to 18
	16	[71]	LOADK    	6 -7	; "Method not implemented."
	17	[71]	CALL     	4 3 1
	18	[71]	CALL     	2 2 1
	19	[71]	RETURN   	0 1
constants (7) for 0000029B16967BE0:
	1	"error"
	2	"__proto"
	3	"Error"
	4	"__index"
	5	"setmetatable"
	6	"constructor"
	7	"Method not implemented."
locals (2) for 0000029B16967BE0:
	0	this	1	21
	1	shader	1	21
upvalues (1) for 0000029B16967BE0:
	0	_ENV	0	0

main <canvas.lua:0,0> (19 instructions at 0000029B169675E0)
2 params, 7 slots, 1 upvalue, 2 locals, 7 constants, 0 functions
	1	[72]	GETTABUP 	2 0 -1	; _ENV "error"
	2	[72]	NEWTABLE 	3 2 0
	3	[72]	LOADK    	4 -2	; "__proto"
	4	[72]	GETTABUP 	5 0 -3	; _ENV "Error"
	5	[72]	SETTABLE 	3 4 5
	6	[72]	LOADK    	4 -4	; "__index"
	7	[72]	GETTABUP 	5 0 -3	; _ENV "Error"
	8	[72]	SETTABLE 	3 4 5
	9	[72]	GETTABUP 	4 0 -5	; _ENV "setmetatable"
	10	[72]	MOVE     	5 3
	11	[72]	MOVE     	6 3
	12	[72]	CALL     	4 3 1
	13	[72]	SELF     	4 3 -6	; "constructor"
	14	[72]	TEST     	4 0
	15	[72]	JMP      	0 2	; to 18
	16	[72]	LOADK    	6 -7	; "Method not implemented."
	17	[72]	CALL     	4 3 1
	18	[72]	CALL     	2 2 1
	19	[72]	RETURN   	0 1
constants (7) for 0000029B169675E0:
	1	"error"
	2	"__proto"
	3	"Error"
	4	"__index"
	5	"setmetatable"
	6	"constructor"
	7	"Method not implemented."
locals (2) for 0000029B169675E0:
	0	this	1	21
	1	texture	1	21
upvalues (1) for 0000029B169675E0:
	0	_ENV	0	0

main <canvas.lua:0,0> (19 instructions at 0000029B16966660)
2 params, 7 slots, 1 upvalue, 2 locals, 7 constants, 0 functions
	1	[73]	GETTABUP 	2 0 -1	; _ENV "error"
	2	[73]	NEWTABLE 	3 2 0
	3	[73]	LOADK    	4 -2	; "__proto"
	4	[73]	GETTABUP 	5 0 -3	; _ENV "Error"
	5	[73]	SETTABLE 	3 4 5
	6	[73]	LOADK    	4 -4	; "__index"
	7	[73]	GETTABUP 	5 0 -3	; _ENV "Error"
	8	[73]	SETTABLE 	3 4 5
	9	[73]	GETTABUP 	4 0 -5	; _ENV "setmetatable"
	10	[73]	MOVE     	5 3
	11	[73]	MOVE     	6 3
	12	[73]	CALL     	4 3 1
	13	[73]	SELF     	4 3 -6	; "constructor"
	14	[73]	TEST     	4 0
	15	[73]	JMP      	0 2	; to 18
	16	[73]	LOADK    	6 -7	; "Method not implemented."
	17	[73]	CALL     	4 3 1
	18	[73]	CALL     	2 2 1
	19	[73]	RETURN   	0 1
constants (7) for 0000029B16966660:
	1	"error"
	2	"__proto"
	3	"Error"
	4	"__index"
	5	"setmetatable"
	6	"constructor"
	7	"Method not implemented."
locals (2) for 0000029B16966660:
	0	this	1	21
	1	func	1	21
upvalues (1) for 0000029B16966660:
	0	_ENV	0	0

main <canvas.lua:0,0> (19 instructions at 0000029B16966560)
2 params, 7 slots, 1 upvalue, 2 locals, 7 constants, 0 functions
	1	[74]	GETTABUP 	2 0 -1	; _ENV "error"
	2	[74]	NEWTABLE 	3 2 0
	3	[74]	LOADK    	4 -2	; "__proto"
	4	[74]	GETTABUP 	5 0 -3	; _ENV "Error"
	5	[74]	SETTABLE 	3 4 5
	6	[74]	LOADK    	4 -4	; "__index"
	7	[74]	GETTABUP 	5 0 -3	; _ENV "Error"
	8	[74]	SETTABLE 	3 4 5
	9	[74]	GETTABUP 	4 0 -5	; _ENV "setmetatable"
	10	[74]	MOVE     	5 3
	11	[74]	MOVE     	6 3
	12	[74]	CALL     	4 3 1
	13	[74]	SELF     	4 3 -6	; "constructor"
	14	[74]	TEST     	4 0
	15	[74]	JMP      	0 2	; to 18
	16	[74]	LOADK    	6 -7	; "Method not implemented."
	17	[74]	CALL     	4 3 1
	18	[74]	CALL     	2 2 1
	19	[74]	RETURN   	0 1
constants (7) for 0000029B16966560:
	1	"error"
	2	"__proto"
	3	"Error"
	4	"__index"
	5	"setmetatable"
	6	"constructor"
	7	"Method not implemented."
locals (2) for 0000029B16966560:
	0	this	1	21
	1	flag	1	21
upvalues (1) for 0000029B16966560:
	0	_ENV	0	0

main <canvas.lua:0,0> (19 instructions at 0000029B169663E0)
3 params, 8 slots, 1 upvalue, 3 locals, 7 constants, 0 functions
	1	[75]	GETTABUP 	3 0 -1	; _ENV "error"
	2	[75]	NEWTABLE 	4 2 0
	3	[75]	LOADK    	5 -2	; "__proto"
	4	[75]	GETTABUP 	6 0 -3	; _ENV "Error"
	5	[75]	SETTABLE 	4 5 6
	6	[75]	LOADK    	5 -4	; "__index"
	7	[75]	GETTABUP 	6 0 -3	; _ENV "Error"
	8	[75]	SETTABLE 	4 5 6
	9	[75]	GETTABUP 	5 0 -5	; _ENV "setmetatable"
	10	[75]	MOVE     	6 4
	11	[75]	MOVE     	7 4
	12	[75]	CALL     	5 3 1
	13	[75]	SELF     	5 4 -6	; "constructor"
	14	[75]	TEST     	5 0
	15	[75]	JMP      	0 2	; to 18
	16	[75]	LOADK    	7 -7	; "Method not implemented."
	17	[75]	CALL     	5 3 1
	18	[75]	CALL     	3 2 1
	19	[75]	RETURN   	0 1
constants (7) for 0000029B169663E0:
	1	"error"
	2	"__proto"
	3	"Error"
	4	"__index"
	5	"setmetatable"
	6	"constructor"
	7	"Method not implemented."
locals (3) for 0000029B169663E0:
	0	this	1	21
	1	zNear	1	21
	2	zFar	1	21
upvalues (1) for 0000029B169663E0:
	0	_ENV	0	0

main <canvas.lua:0,0> (19 instructions at 0000029B16967660)
3 params, 8 slots, 1 upvalue, 3 locals, 7 constants, 0 functions
	1	[76]	GETTABUP 	3 0 -1	; _ENV "error"
	2	[76]	NEWTABLE 	4 2 0
	3	[76]	LOADK    	5 -2	; "__proto"
	4	[76]	GETTABUP 	6 0 -3	; _ENV "Error"
	5	[76]	SETTABLE 	4 5 6
	6	[76]	LOADK    	5 -4	; "__index"
	7	[76]	GETTABUP 	6 0 -3	; _ENV "Error"
	8	[76]	SETTABLE 	4 5 6
	9	[76]	GETTABUP 	5 0 -5	; _ENV "setmetatable"
	10	[76]	MOVE     	6 4
	11	[76]	MOVE     	7 4
	12	[76]	CALL     	5 3 1
	13	[76]	SELF     	5 4 -6	; "constructor"
	14	[76]	TEST     	5 0
	15	[76]	JMP      	0 2	; to 18
	16	[76]	LOADK    	7 -7	; "Method not implemented."
	17	[76]	CALL     	5 3 1
	18	[76]	CALL     	3 2 1
	19	[76]	RETURN   	0 1
constants (7) for 0000029B16967660:
	1	"error"
	2	"__proto"
	3	"Error"
	4	"__index"
	5	"setmetatable"
	6	"constructor"
	7	"Method not implemented."
locals (3) for 0000029B16967660:
	0	this	1	21
	1	program	1	21
	2	shader	1	21
upvalues (1) for 0000029B16967660:
	0	_ENV	0	0

main <canvas.lua:0,0> (19 instructions at 0000029B16967860)
2 params, 7 slots, 1 upvalue, 2 locals, 7 constants, 0 functions
	1	[77]	GETTABUP 	2 0 -1	; _ENV "error"
	2	[77]	NEWTABLE 	3 2 0
	3	[77]	LOADK    	4 -2	; "__proto"
	4	[77]	GETTABUP 	5 0 -3	; _ENV "Error"
	5	[77]	SETTABLE 	3 4 5
	6	[77]	LOADK    	4 -4	; "__index"
	7	[77]	GETTABUP 	5 0 -3	; _ENV "Error"
	8	[77]	SETTABLE 	3 4 5
	9	[77]	GETTABUP 	4 0 -5	; _ENV "setmetatable"
	10	[77]	MOVE     	5 3
	11	[77]	MOVE     	6 3
	12	[77]	CALL     	4 3 1
	13	[77]	SELF     	4 3 -6	; "constructor"
	14	[77]	TEST     	4 0
	15	[77]	JMP      	0 2	; to 18
	16	[77]	LOADK    	6 -7	; "Method not implemented."
	17	[77]	CALL     	4 3 1
	18	[77]	CALL     	2 2 1
	19	[77]	RETURN   	0 1
constants (7) for 0000029B16967860:
	1	"error"
	2	"__proto"
	3	"Error"
	4	"__index"
	5	"setmetatable"
	6	"constructor"
	7	"Method not implemented."
locals (2) for 0000029B16967860:
	0	this	1	21
	1	cap	1	21
upvalues (1) for 0000029B16967860:
	0	_ENV	0	0

main <canvas.lua:0,0> (19 instructions at 0000029B169679E0)
2 params, 7 slots, 1 upvalue, 2 locals, 7 constants, 0 functions
	1	[78]	GETTABUP 	2 0 -1	; _ENV "error"
	2	[78]	NEWTABLE 	3 2 0
	3	[78]	LOADK    	4 -2	; "__proto"
	4	[78]	GETTABUP 	5 0 -3	; _ENV "Error"
	5	[78]	SETTABLE 	3 4 5
	6	[78]	LOADK    	4 -4	; "__index"
	7	[78]	GETTABUP 	5 0 -3	; _ENV "Error"
	8	[78]	SETTABLE 	3 4 5
	9	[78]	GETTABUP 	4 0 -5	; _ENV "setmetatable"
	10	[78]	MOVE     	5 3
	11	[78]	MOVE     	6 3
	12	[78]	CALL     	4 3 1
	13	[78]	SELF     	4 3 -6	; "constructor"
	14	[78]	TEST     	4 0
	15	[78]	JMP      	0 2	; to 18
	16	[78]	LOADK    	6 -7	; "Method not implemented."
	17	[78]	CALL     	4 3 1
	18	[78]	CALL     	2 2 1
	19	[78]	RETURN   	0 1
constants (7) for 0000029B169679E0:
	1	"error"
	2	"__proto"
	3	"Error"
	4	"__index"
	5	"setmetatable"
	6	"constructor"
	7	"Method not implemented."
locals (2) for 0000029B169679E0:
	0	this	1	21
	1	index	1	21
upvalues (1) for 0000029B169679E0:
	0	_ENV	0	0

main <canvas.lua:0,0> (19 instructions at 0000029B16966D60)
4 params, 9 slots, 1 upvalue, 4 locals, 7 constants, 0 functions
	1	[79]	GETTABUP 	4 0 -1	; _ENV "error"
	2	[79]	NEWTABLE 	5 2 0
	3	[79]	LOADK    	6 -2	; "__proto"
	4	[79]	GETTABUP 	7 0 -3	; _ENV "Error"
	5	[79]	SETTABLE 	5 6 7
	6	[79]	LOADK    	6 -4	; "__index"
	7	[79]	GETTABUP 	7 0 -3	; _ENV "Error"
	8	[79]	SETTABLE 	5 6 7
	9	[79]	GETTABUP 	6 0 -5	; _ENV "setmetatable"
	10	[79]	MOVE     	7 5
	11	[79]	MOVE     	8 5
	12	[79]	CALL     	6 3 1
	13	[79]	SELF     	6 5 -6	; "constructor"
	14	[79]	TEST     	6 0
	15	[79]	JMP      	0 2	; to 18
	16	[79]	LOADK    	8 -7	; "Method not implemented."
	17	[79]	CALL     	6 3 1
	18	[79]	CALL     	4 2 1
	19	[79]	RETURN   	0 1
constants (7) for 0000029B16966D60:
	1	"error"
	2	"__proto"
	3	"Error"
	4	"__index"
	5	"setmetatable"
	6	"constructor"
	7	"Method not implemented."
locals (4) for 0000029B16966D60:
	0	this	1	21
	1	mode	1	21
	2	first	1	21
	3	count	1	21
upvalues (1) for 0000029B16966D60:
	0	_ENV	0	0

main <canvas.lua:0,0> (19 instructions at 0000029B16966E60)
5 params, 10 slots, 1 upvalue, 5 locals, 7 constants, 0 functions
	1	[80]	GETTABUP 	5 0 -1	; _ENV "error"
	2	[80]	NEWTABLE 	6 2 0
	3	[80]	LOADK    	7 -2	; "__proto"
	4	[80]	GETTABUP 	8 0 -3	; _ENV "Error"
	5	[80]	SETTABLE 	6 7 8
	6	[80]	LOADK    	7 -4	; "__index"
	7	[80]	GETTABUP 	8 0 -3	; _ENV "Error"
	8	[80]	SETTABLE 	6 7 8
	9	[80]	GETTABUP 	7 0 -5	; _ENV "setmetatable"
	10	[80]	MOVE     	8 6
	11	[80]	MOVE     	9 6
	12	[80]	CALL     	7 3 1
	13	[80]	SELF     	7 6 -6	; "constructor"
	14	[80]	TEST     	7 0
	15	[80]	JMP      	0 2	; to 18
	16	[80]	LOADK    	9 -7	; "Method not implemented."
	17	[80]	CALL     	7 3 1
	18	[80]	CALL     	5 2 1
	19	[80]	RETURN   	0 1
constants (7) for 0000029B16966E60:
	1	"error"
	2	"__proto"
	3	"Error"
	4	"__index"
	5	"setmetatable"
	6	"constructor"
	7	"Method not implemented."
locals (5) for 0000029B16966E60:
	0	this	1	21
	1	mode	1	21
	2	count	1	21
	3	type	1	21
	4	offset	1	21
upvalues (1) for 0000029B16966E60:
	0	_ENV	0	0

main <canvas.lua:0,0> (19 instructions at 0000029B16966EE0)
2 params, 7 slots, 1 upvalue, 2 locals, 7 constants, 0 functions
	1	[81]	GETTABUP 	2 0 -1	; _ENV "error"
	2	[81]	NEWTABLE 	3 2 0
	3	[81]	LOADK    	4 -2	; "__proto"
	4	[81]	GETTABUP 	5 0 -3	; _ENV "Error"
	5	[81]	SETTABLE 	3 4 5
	6	[81]	LOADK    	4 -4	; "__index"
	7	[81]	GETTABUP 	5 0 -3	; _ENV "Error"
	8	[81]	SETTABLE 	3 4 5
	9	[81]	GETTABUP 	4 0 -5	; _ENV "setmetatable"
	10	[81]	MOVE     	5 3
	11	[81]	MOVE     	6 3
	12	[81]	CALL     	4 3 1
	13	[81]	SELF     	4 3 -6	; "constructor"
	14	[81]	TEST     	4 0
	15	[81]	JMP      	0 2	; to 18
	16	[81]	LOADK    	6 -7	; "Method not implemented."
	17	[81]	CALL     	4 3 1
	18	[81]	CALL     	2 2 1
	19	[81]	RETURN   	0 1
constants (7) for 0000029B16966EE0:
	1	"error"
	2	"__proto"
	3	"Error"
	4	"__index"
	5	"setmetatable"
	6	"constructor"
	7	"Method not implemented."
locals (2) for 0000029B16966EE0:
	0	this	1	21
	1	cap	1	21
upvalues (1) for 0000029B16966EE0:
	0	_ENV	0	0

main <canvas.lua:0,0> (19 instructions at 0000029B16966F60)
2 params, 7 slots, 1 upvalue, 2 locals, 7 constants, 0 functions
	1	[82]	GETTABUP 	2 0 -1	; _ENV "error"
	2	[82]	NEWTABLE 	3 2 0
	3	[82]	LOADK    	4 -2	; "__proto"
	4	[82]	GETTABUP 	5 0 -3	; _ENV "Error"
	5	[82]	SETTABLE 	3 4 5
	6	[82]	LOADK    	4 -4	; "__index"
	7	[82]	GETTABUP 	5 0 -3	; _ENV "Error"
	8	[82]	SETTABLE 	3 4 5
	9	[82]	GETTABUP 	4 0 -5	; _ENV "setmetatable"
	10	[82]	MOVE     	5 3
	11	[82]	MOVE     	6 3
	12	[82]	CALL     	4 3 1
	13	[82]	SELF     	4 3 -6	; "constructor"
	14	[82]	TEST     	4 0
	15	[82]	JMP      	0 2	; to 18
	16	[82]	LOADK    	6 -7	; "Method not implemented."
	17	[82]	CALL     	4 3 1
	18	[82]	CALL     	2 2 1
	19	[82]	RETURN   	0 1
constants (7) for 0000029B16966F60:
	1	"error"
	2	"__proto"
	3	"Error"
	4	"__index"
	5	"setmetatable"
	6	"constructor"
	7	"Method not implemented."
locals (2) for 0000029B16966F60:
	0	this	1	21
	1	index	1	21
upvalues (1) for 0000029B16966F60:
	0	_ENV	0	0

main <canvas.lua:0,0> (19 instructions at 0000029B169677E0)
1 param, 6 slots, 1 upvalue, 1 local, 7 constants, 0 functions
	1	[83]	GETTABUP 	1 0 -1	; _ENV "error"
	2	[83]	NEWTABLE 	2 2 0
	3	[83]	LOADK    	3 -2	; "__proto"
	4	[83]	GETTABUP 	4 0 -3	; _ENV "Error"
	5	[83]	SETTABLE 	2 3 4
	6	[83]	LOADK    	3 -4	; "__index"
	7	[83]	GETTABUP 	4 0 -3	; _ENV "Error"
	8	[83]	SETTABLE 	2 3 4
	9	[83]	GETTABUP 	3 0 -5	; _ENV "setmetatable"
	10	[83]	MOVE     	4 2
	11	[83]	MOVE     	5 2
	12	[83]	CALL     	3 3 1
	13	[83]	SELF     	3 2 -6	; "constructor"
	14	[83]	TEST     	3 0
	15	[83]	JMP      	0 2	; to 18
	16	[83]	LOADK    	5 -7	; "Method not implemented."
	17	[83]	CALL     	3 3 1
	18	[83]	CALL     	1 2 1
	19	[83]	RETURN   	0 1
constants (7) for 0000029B169677E0:
	1	"error"
	2	"__proto"
	3	"Error"
	4	"__index"
	5	"setmetatable"
	6	"constructor"
	7	"Method not implemented."
locals (1) for 0000029B169677E0:
	0	this	1	21
upvalues (1) for 0000029B169677E0:
	0	_ENV	0	0

main <canvas.lua:0,0> (19 instructions at 0000029B16965E60)
1 param, 6 slots, 1 upvalue, 1 local, 7 constants, 0 functions
	1	[84]	GETTABUP 	1 0 -1	; _ENV "error"
	2	[84]	NEWTABLE 	2 2 0
	3	[84]	LOADK    	3 -2	; "__proto"
	4	[84]	GETTABUP 	4 0 -3	; _ENV "Error"
	5	[84]	SETTABLE 	2 3 4
	6	[84]	LOADK    	3 -4	; "__index"
	7	[84]	GETTABUP 	4 0 -3	; _ENV "Error"
	8	[84]	SETTABLE 	2 3 4
	9	[84]	GETTABUP 	3 0 -5	; _ENV "setmetatable"
	10	[84]	MOVE     	4 2
	11	[84]	MOVE     	5 2
	12	[84]	CALL     	3 3 1
	13	[84]	SELF     	3 2 -6	; "constructor"
	14	[84]	TEST     	3 0
	15	[84]	JMP      	0 2	; to 18
	16	[84]	LOADK    	5 -7	; "Method not implemented."
	17	[84]	CALL     	3 3 1
	18	[84]	CALL     	1 2 1
	19	[84]	RETURN   	0 1
constants (7) for 0000029B16965E60:
	1	"error"
	2	"__proto"
	3	"Error"
	4	"__index"
	5	"setmetatable"
	6	"constructor"
	7	"Method not implemented."
locals (1) for 0000029B16965E60:
	0	this	1	21
upvalues (1) for 0000029B16965E60:
	0	_ENV	0	0

main <canvas.lua:0,0> (19 instructions at 0000029B1696C590)
5 params, 10 slots, 1 upvalue, 5 locals, 7 constants, 0 functions
	1	[85]	GETTABUP 	5 0 -1	; _ENV "error"
	2	[85]	NEWTABLE 	6 2 0
	3	[85]	LOADK    	7 -2	; "__proto"
	4	[85]	GETTABUP 	8 0 -3	; _ENV "Error"
	5	[85]	SETTABLE 	6 7 8
	6	[85]	LOADK    	7 -4	; "__index"
	7	[85]	GETTABUP 	8 0 -3	; _ENV "Error"
	8	[85]	SETTABLE 	6 7 8
	9	[85]	GETTABUP 	7 0 -5	; _ENV "setmetatable"
	10	[85]	MOVE     	8 6
	11	[85]	MOVE     	9 6
	12	[85]	CALL     	7 3 1
	13	[85]	SELF     	7 6 -6	; "constructor"
	14	[85]	TEST     	7 0
	15	[85]	JMP      	0 2	; to 18
	16	[85]	LOADK    	9 -7	; "Method not implemented."
	17	[85]	CALL     	7 3 1
	18	[85]	CALL     	5 2 1
	19	[85]	RETURN   	0 1
constants (7) for 0000029B1696C590:
	1	"error"
	2	"__proto"
	3	"Error"
	4	"__index"
	5	"setmetatable"
	6	"constructor"
	7	"Method not implemented."
locals (5) for 0000029B1696C590:
	0	this	1	21
	1	target	1	21
	2	attachment	1	21
	3	renderbuffertarget	1	21
	4	renderbuffer	1	21
upvalues (1) for 0000029B1696C590:
	0	_ENV	0	0

main <canvas.lua:0,0> (19 instructions at 0000029B1696C910)
6 params, 11 slots, 1 upvalue, 6 locals, 7 constants, 0 functions
	1	[86]	GETTABUP 	6 0 -1	; _ENV "error"
	2	[86]	NEWTABLE 	7 2 0
	3	[86]	LOADK    	8 -2	; "__proto"
	4	[86]	GETTABUP 	9 0 -3	; _ENV "Error"
	5	[86]	SETTABLE 	7 8 9
	6	[86]	LOADK    	8 -4	; "__index"
	7	[86]	GETTABUP 	9 0 -3	; _ENV "Error"
	8	[86]	SETTABLE 	7 8 9
	9	[86]	GETTABUP 	8 0 -5	; _ENV "setmetatable"
	10	[86]	MOVE     	9 7
	11	[86]	MOVE     	10 7
	12	[86]	CALL     	8 3 1
	13	[86]	SELF     	8 7 -6	; "constructor"
	14	[86]	TEST     	8 0
	15	[86]	JMP      	0 2	; to 18
	16	[86]	LOADK    	10 -7	; "Method not implemented."
	17	[86]	CALL     	8 3 1
	18	[86]	CALL     	6 2 1
	19	[86]	RETURN   	0 1
constants (7) for 0000029B1696C910:
	1	"error"
	2	"__proto"
	3	"Error"
	4	"__index"
	5	"setmetatable"
	6	"constructor"
	7	"Method not implemented."
locals (6) for 0000029B1696C910:
	0	this	1	21
	1	target	1	21
	2	attachment	1	21
	3	textarget	1	21
	4	texture	1	21
	5	level	1	21
upvalues (1) for 0000029B1696C910:
	0	_ENV	0	0

main <canvas.lua:0,0> (19 instructions at 0000029B1696C090)
2 params, 7 slots, 1 upvalue, 2 locals, 7 constants, 0 functions
	1	[87]	GETTABUP 	2 0 -1	; _ENV "error"
	2	[87]	NEWTABLE 	3 2 0
	3	[87]	LOADK    	4 -2	; "__proto"
	4	[87]	GETTABUP 	5 0 -3	; _ENV "Error"
	5	[87]	SETTABLE 	3 4 5
	6	[87]	LOADK    	4 -4	; "__index"
	7	[87]	GETTABUP 	5 0 -3	; _ENV "Error"
	8	[87]	SETTABLE 	3 4 5
	9	[87]	GETTABUP 	4 0 -5	; _ENV "setmetatable"
	10	[87]	MOVE     	5 3
	11	[87]	MOVE     	6 3
	12	[87]	CALL     	4 3 1
	13	[87]	SELF     	4 3 -6	; "constructor"
	14	[87]	TEST     	4 0
	15	[87]	JMP      	0 2	; to 18
	16	[87]	LOADK    	6 -7	; "Method not implemented."
	17	[87]	CALL     	4 3 1
	18	[87]	CALL     	2 2 1
	19	[87]	RETURN   	0 1
constants (7) for 0000029B1696C090:
	1	"error"
	2	"__proto"
	3	"Error"
	4	"__index"
	5	"setmetatable"
	6	"constructor"
	7	"Method not implemented."
locals (2) for 0000029B1696C090:
	0	this	1	21
	1	mode	1	21
upvalues (1) for 0000029B1696C090:
	0	_ENV	0	0

main <canvas.lua:0,0> (19 instructions at 0000029B1696BD90)
2 params, 7 slots, 1 upvalue, 2 locals, 7 constants, 0 functions
	1	[88]	GETTABUP 	2 0 -1	; _ENV "error"
	2	[88]	NEWTABLE 	3 2 0
	3	[88]	LOADK    	4 -2	; "__proto"
	4	[88]	GETTABUP 	5 0 -3	; _ENV "Error"
	5	[88]	SETTABLE 	3 4 5
	6	[88]	LOADK    	4 -4	; "__index"
	7	[88]	GETTABUP 	5 0 -3	; _ENV "Error"
	8	[88]	SETTABLE 	3 4 5
	9	[88]	GETTABUP 	4 0 -5	; _ENV "setmetatable"
	10	[88]	MOVE     	5 3
	11	[88]	MOVE     	6 3
	12	[88]	CALL     	4 3 1
	13	[88]	SELF     	4 3 -6	; "constructor"
	14	[88]	TEST     	4 0
	15	[88]	JMP      	0 2	; to 18
	16	[88]	LOADK    	6 -7	; "Method not implemented."
	17	[88]	CALL     	4 3 1
	18	[88]	CALL     	2 2 1
	19	[88]	RETURN   	0 1
constants (7) for 0000029B1696BD90:
	1	"error"
	2	"__proto"
	3	"Error"
	4	"__index"
	5	"setmetatable"
	6	"constructor"
	7	"Method not implemented."
locals (2) for 0000029B1696BD90:
	0	this	1	21
	1	target	1	21
upvalues (1) for 0000029B1696BD90:
	0	_ENV	0	0

main <canvas.lua:0,0> (19 instructions at 0000029B1696B010)
3 params, 8 slots, 1 upvalue, 3 locals, 7 constants, 0 functions
	1	[89]	GETTABUP 	3 0 -1	; _ENV "error"
	2	[89]	NEWTABLE 	4 2 0
	3	[89]	LOADK    	5 -2	; "__proto"
	4	[89]	GETTABUP 	6 0 -3	; _ENV "Error"
	5	[89]	SETTABLE 	4 5 6
	6	[89]	LOADK    	5 -4	; "__index"
	7	[89]	GETTABUP 	6 0 -3	; _ENV "Error"
	8	[89]	SETTABLE 	4 5 6
	9	[89]	GETTABUP 	5 0 -5	; _ENV "setmetatable"
	10	[89]	MOVE     	6 4
	11	[89]	MOVE     	7 4
	12	[89]	CALL     	5 3 1
	13	[89]	SELF     	5 4 -6	; "constructor"
	14	[89]	TEST     	5 0
	15	[89]	JMP      	0 2	; to 18
	16	[89]	LOADK    	7 -7	; "Method not implemented."
	17	[89]	CALL     	5 3 1
	18	[89]	CALL     	3 2 1
	19	[89]	RETURN   	0 1
constants (7) for 0000029B1696B010:
	1	"error"
	2	"__proto"
	3	"Error"
	4	"__index"
	5	"setmetatable"
	6	"constructor"
	7	"Method not implemented."
locals (3) for 0000029B1696B010:
	0	this	1	21
	1	program	1	21
	2	index	1	21
upvalues (1) for 0000029B1696B010:
	0	_ENV	0	0

main <canvas.lua:0,0> (19 instructions at 0000029B1696B910)
3 params, 8 slots, 1 upvalue, 3 locals, 7 constants, 0 functions
	1	[90]	GETTABUP 	3 0 -1	; _ENV "error"
	2	[90]	NEWTABLE 	4 2 0
	3	[90]	LOADK    	5 -2	; "__proto"
	4	[90]	GETTABUP 	6 0 -3	; _ENV "Error"
	5	[90]	SETTABLE 	4 5 6
	6	[90]	LOADK    	5 -4	; "__index"
	7	[90]	GETTABUP 	6 0 -3	; _ENV "Error"
	8	[90]	SETTABLE 	4 5 6
	9	[90]	GETTABUP 	5 0 -5	; _ENV "setmetatable"
	10	[90]	MOVE     	6 4
	11	[90]	MOVE     	7 4
	12	[90]	CALL     	5 3 1
	13	[90]	SELF     	5 4 -6	; "constructor"
	14	[90]	TEST     	5 0
	15	[90]	JMP      	0 2	; to 18
	16	[90]	LOADK    	7 -7	; "Method not implemented."
	17	[90]	CALL     	5 3 1
	18	[90]	CALL     	3 2 1
	19	[90]	RETURN   	0 1
constants (7) for 0000029B1696B910:
	1	"error"
	2	"__proto"
	3	"Error"
	4	"__index"
	5	"setmetatable"
	6	"constructor"
	7	"Method not implemented."
locals (3) for 0000029B1696B910:
	0	this	1	21
	1	program	1	21
	2	index	1	21
upvalues (1) for 0000029B1696B910:
	0	_ENV	0	0

main <canvas.lua:0,0> (19 instructions at 0000029B1696B990)
2 params, 7 slots, 1 upvalue, 2 locals, 7 constants, 0 functions
	1	[91]	GETTABUP 	2 0 -1	; _ENV "error"
	2	[91]	NEWTABLE 	3 2 0
	3	[91]	LOADK    	4 -2	; "__proto"
	4	[91]	GETTABUP 	5 0 -3	; _ENV "Error"
	5	[91]	SETTABLE 	3 4 5
	6	[91]	LOADK    	4 -4	; "__index"
	7	[91]	GETTABUP 	5 0 -3	; _ENV "Error"
	8	[91]	SETTABLE 	3 4 5
	9	[91]	GETTABUP 	4 0 -5	; _ENV "setmetatable"
	10	[91]	MOVE     	5 3
	11	[91]	MOVE     	6 3
	12	[91]	CALL     	4 3 1
	13	[91]	SELF     	4 3 -6	; "constructor"
	14	[91]	TEST     	4 0
	15	[91]	JMP      	0 2	; to 18
	16	[91]	LOADK    	6 -7	; "Method not implemented."
	17	[91]	CALL     	4 3 1
	18	[91]	CALL     	2 2 1
	19	[91]	RETURN   	0 1
constants (7) for 0000029B1696B990:
	1	"error"
	2	"__proto"
	3	"Error"
	4	"__index"
	5	"setmetatable"
	6	"constructor"
	7	"Method not implemented."
locals (2) for 0000029B1696B990:
	0	this	1	21
	1	program	1	21
upvalues (1) for 0000029B1696B990:
	0	_ENV	0	0

main <canvas.lua:0,0> (19 instructions at 0000029B1696B890)
3 params, 8 slots, 1 upvalue, 3 locals, 7 constants, 0 functions
	1	[92]	GETTABUP 	3 0 -1	; _ENV "error"
	2	[92]	NEWTABLE 	4 2 0
	3	[92]	LOADK    	5 -2	; "__proto"
	4	[92]	GETTABUP 	6 0 -3	; _ENV "Error"
	5	[92]	SETTABLE 	4 5 6
	6	[92]	LOADK    	5 -4	; "__index"
	7	[92]	GETTABUP 	6 0 -3	; _ENV "Error"
	8	[92]	SETTABLE 	4 5 6
	9	[92]	GETTABUP 	5 0 -5	; _ENV "setmetatable"
	10	[92]	MOVE     	6 4
	11	[92]	MOVE     	7 4
	12	[92]	CALL     	5 3 1
	13	[92]	SELF     	5 4 -6	; "constructor"
	14	[92]	TEST     	5 0
	15	[92]	JMP      	0 2	; to 18
	16	[92]	LOADK    	7 -7	; "Method not implemented."
	17	[92]	CALL     	5 3 1
	18	[92]	CALL     	3 2 1
	19	[92]	RETURN   	0 1
constants (7) for 0000029B1696B890:
	1	"error"
	2	"__proto"
	3	"Error"
	4	"__index"
	5	"setmetatable"
	6	"constructor"
	7	"Method not implemented."
locals (3) for 0000029B1696B890:
	0	this	1	21
	1	program	1	21
	2	name	1	21
upvalues (1) for 0000029B1696B890:
	0	_ENV	0	0

main <canvas.lua:0,0> (19 instructions at 0000029B1696C490)
3 params, 8 slots, 1 upvalue, 3 locals, 7 constants, 0 functions
	1	[93]	GETTABUP 	3 0 -1	; _ENV "error"
	2	[93]	NEWTABLE 	4 2 0
	3	[93]	LOADK    	5 -2	; "__proto"
	4	[93]	GETTABUP 	6 0 -3	; _ENV "Error"
	5	[93]	SETTABLE 	4 5 6
	6	[93]	LOADK    	5 -4	; "__index"
	7	[93]	GETTABUP 	6 0 -3	; _ENV "Error"
	8	[93]	SETTABLE 	4 5 6
	9	[93]	GETTABUP 	5 0 -5	; _ENV "setmetatable"
	10	[93]	MOVE     	6 4
	11	[93]	MOVE     	7 4
	12	[93]	CALL     	5 3 1
	13	[93]	SELF     	5 4 -6	; "constructor"
	14	[93]	TEST     	5 0
	15	[93]	JMP      	0 2	; to 18
	16	[93]	LOADK    	7 -7	; "Method not implemented."
	17	[93]	CALL     	5 3 1
	18	[93]	CALL     	3 2 1
	19	[93]	RETURN   	0 1
constants (7) for 0000029B1696C490:
	1	"error"
	2	"__proto"
	3	"Error"
	4	"__index"
	5	"setmetatable"
	6	"constructor"
	7	"Method not implemented."
locals (3) for 0000029B1696C490:
	0	this	1	21
	1	target	1	21
	2	pname	1	21
upvalues (1) for 0000029B1696C490:
	0	_ENV	0	0

main <canvas.lua:0,0> (3 instructions at 0000029B1696B810)
1 param, 2 slots, 0 upvalues, 1 local, 1 constant, 0 functions
	1	[94]	LOADNIL  	1 1
	2	[94]	RETURN   	1 2
	3	[94]	RETURN   	0 1
constants (1) for 0000029B1696B810:
	1	nil
locals (1) for 0000029B1696B810:
	0	this	1	5
upvalues (0) for 0000029B1696B810:

main <canvas.lua:0,0> (19 instructions at 0000029B1696CC90)
1 param, 6 slots, 1 upvalue, 1 local, 7 constants, 0 functions
	1	[95]	GETTABUP 	1 0 -1	; _ENV "error"
	2	[95]	NEWTABLE 	2 2 0
	3	[95]	LOADK    	3 -2	; "__proto"
	4	[95]	GETTABUP 	4 0 -3	; _ENV "Error"
	5	[95]	SETTABLE 	2 3 4
	6	[95]	LOADK    	3 -4	; "__index"
	7	[95]	GETTABUP 	4 0 -3	; _ENV "Error"
	8	[95]	SETTABLE 	2 3 4
	9	[95]	GETTABUP 	3 0 -5	; _ENV "setmetatable"
	10	[95]	MOVE     	4 2
	11	[95]	MOVE     	5 2
	12	[95]	CALL     	3 3 1
	13	[95]	SELF     	3 2 -6	; "constructor"
	14	[95]	TEST     	3 0
	15	[95]	JMP      	0 2	; to 18
	16	[95]	LOADK    	5 -7	; "Method not implemented."
	17	[95]	CALL     	3 3 1
	18	[95]	CALL     	1 2 1
	19	[95]	RETURN   	0 1
constants (7) for 0000029B1696CC90:
	1	"error"
	2	"__proto"
	3	"Error"
	4	"__index"
	5	"setmetatable"
	6	"constructor"
	7	"Method not implemented."
locals (1) for 0000029B1696CC90:
	0	this	1	21
upvalues (1) for 0000029B1696CC90:
	0	_ENV	0	0

main <canvas.lua:0,0> (3 instructions at 0000029B1696CD10)
2 params, 3 slots, 0 upvalues, 2 locals, 1 constant, 0 functions
	1	[96]	LOADNIL  	2 1
	2	[96]	RETURN   	2 2
	3	[96]	RETURN   	0 1
constants (1) for 0000029B1696CD10:
	1	nil
locals (2) for 0000029B1696CD10:
	0	this	1	5
	1	extensionName	1	5
upvalues (0) for 0000029B1696CD10:

main <canvas.lua:0,0> (19 instructions at 0000029B1696BB90)
4 params, 9 slots, 1 upvalue, 4 locals, 7 constants, 0 functions
	1	[97]	GETTABUP 	4 0 -1	; _ENV "error"
	2	[97]	NEWTABLE 	5 2 0
	3	[97]	LOADK    	6 -2	; "__proto"
	4	[97]	GETTABUP 	7 0 -3	; _ENV "Error"
	5	[97]	SETTABLE 	5 6 7
	6	[97]	LOADK    	6 -4	; "__index"
	7	[97]	GETTABUP 	7 0 -3	; _ENV "Error"
	8	[97]	SETTABLE 	5 6 7
	9	[97]	GETTABUP 	6 0 -5	; _ENV "setmetatable"
	10	[97]	MOVE     	7 5
	11	[97]	MOVE     	8 5
	12	[97]	CALL     	6 3 1
	13	[97]	SELF     	6 5 -6	; "constructor"
	14	[97]	TEST     	6 0
	15	[97]	JMP      	0 2	; to 18
	16	[97]	LOADK    	8 -7	; "Method not implemented."
	17	[97]	CALL     	6 3 1
	18	[97]	CALL     	4 2 1
	19	[97]	RETURN   	0 1
constants (7) for 0000029B1696BB90:
	1	"error"
	2	"__proto"
	3	"Error"
	4	"__index"
	5	"setmetatable"
	6	"constructor"
	7	"Method not implemented."
locals (4) for 0000029B1696BB90:
	0	this	1	21
	1	target	1	21
	2	attachment	1	21
	3	pname	1	21
upvalues (1) for 0000029B1696BB90:
	0	_ENV	0	0

main <canvas.lua:0,0> (3 instructions at 0000029B1696CB10)
2 params, 3 slots, 0 upvalues, 2 locals, 1 constant, 0 functions
	1	[98]	LOADK    	2 -1	; 0
	2	[98]	RETURN   	2 2
	3	[98]	RETURN   	0 1
constants (1) for 0000029B1696CB10:
	1	0
locals (2) for 0000029B1696CB10:
	0	this	1	5
	1	pname	1	5
upvalues (0) for 0000029B1696CB10:

main <canvas.lua:0,0> (19 instructions at 0000029B1696C890)
2 params, 7 slots, 1 upvalue, 2 locals, 7 constants, 0 functions
	1	[99]	GETTABUP 	2 0 -1	; _ENV "error"
	2	[99]	NEWTABLE 	3 2 0
	3	[99]	LOADK    	4 -2	; "__proto"
	4	[99]	GETTABUP 	5 0 -3	; _ENV "Error"
	5	[99]	SETTABLE 	3 4 5
	6	[99]	LOADK    	4 -4	; "__index"
	7	[99]	GETTABUP 	5 0 -3	; _ENV "Error"
	8	[99]	SETTABLE 	3 4 5
	9	[99]	GETTABUP 	4 0 -5	; _ENV "setmetatable"
	10	[99]	MOVE     	5 3
	11	[99]	MOVE     	6 3
	12	[99]	CALL     	4 3 1
	13	[99]	SELF     	4 3 -6	; "constructor"
	14	[99]	TEST     	4 0
	15	[99]	JMP      	0 2	; to 18
	16	[99]	LOADK    	6 -7	; "Method not implemented."
	17	[99]	CALL     	4 3 1
	18	[99]	CALL     	2 2 1
	19	[99]	RETURN   	0 1
constants (7) for 0000029B1696C890:
	1	"error"
	2	"__proto"
	3	"Error"
	4	"__index"
	5	"setmetatable"
	6	"constructor"
	7	"Method not implemented."
locals (2) for 0000029B1696C890:
	0	this	1	21
	1	program	1	21
upvalues (1) for 0000029B1696C890:
	0	_ENV	0	0

main <canvas.lua:0,0> (19 instructions at 0000029B1696C790)
3 params, 8 slots, 1 upvalue, 3 locals, 7 constants, 0 functions
	1	[100]	GETTABUP 	3 0 -1	; _ENV "error"
	2	[100]	NEWTABLE 	4 2 0
	3	[100]	LOADK    	5 -2	; "__proto"
	4	[100]	GETTABUP 	6 0 -3	; _ENV "Error"
	5	[100]	SETTABLE 	4 5 6
	6	[100]	LOADK    	5 -4	; "__index"
	7	[100]	GETTABUP 	6 0 -3	; _ENV "Error"
	8	[100]	SETTABLE 	4 5 6
	9	[100]	GETTABUP 	5 0 -5	; _ENV "setmetatable"
	10	[100]	MOVE     	6 4
	11	[100]	MOVE     	7 4
	12	[100]	CALL     	5 3 1
	13	[100]	SELF     	5 4 -6	; "constructor"
	14	[100]	TEST     	5 0
	15	[100]	JMP      	0 2	; to 18
	16	[100]	LOADK    	7 -7	; "Method not implemented."
	17	[100]	CALL     	5 3 1
	18	[100]	CALL     	3 2 1
	19	[100]	RETURN   	0 1
constants (7) for 0000029B1696C790:
	1	"error"
	2	"__proto"
	3	"Error"
	4	"__index"
	5	"setmetatable"
	6	"constructor"
	7	"Method not implemented."
locals (3) for 0000029B1696C790:
	0	this	1	21
	1	program	1	21
	2	pname	1	21
upvalues (1) for 0000029B1696C790:
	0	_ENV	0	0

main <canvas.lua:0,0> (19 instructions at 0000029B1696C210)
3 params, 8 slots, 1 upvalue, 3 locals, 7 constants, 0 functions
	1	[101]	GETTABUP 	3 0 -1	; _ENV "error"
	2	[101]	NEWTABLE 	4 2 0
	3	[101]	LOADK    	5 -2	; "__proto"
	4	[101]	GETTABUP 	6 0 -3	; _ENV "Error"
	5	[101]	SETTABLE 	4 5 6
	6	[101]	LOADK    	5 -4	; "__index"
	7	[101]	GETTABUP 	6 0 -3	; _ENV "Error"
	8	[101]	SETTABLE 	4 5 6
	9	[101]	GETTABUP 	5 0 -5	; _ENV "setmetatable"
	10	[101]	MOVE     	6 4
	11	[101]	MOVE     	7 4
	12	[101]	CALL     	5 3 1
	13	[101]	SELF     	5 4 -6	; "constructor"
	14	[101]	TEST     	5 0
	15	[101]	JMP      	0 2	; to 18
	16	[101]	LOADK    	7 -7	; "Method not implemented."
	17	[101]	CALL     	5 3 1
	18	[101]	CALL     	3 2 1
	19	[101]	RETURN   	0 1
constants (7) for 0000029B1696C210:
	1	"error"
	2	"__proto"
	3	"Error"
	4	"__index"
	5	"setmetatable"
	6	"constructor"
	7	"Method not implemented."
locals (3) for 0000029B1696C210:
	0	this	1	21
	1	target	1	21
	2	pname	1	21
upvalues (1) for 0000029B1696C210:
	0	_ENV	0	0

main <canvas.lua:0,0> (19 instructions at 0000029B1696B490)
2 params, 7 slots, 1 upvalue, 2 locals, 7 constants, 0 functions
	1	[102]	GETTABUP 	2 0 -1	; _ENV "error"
	2	[102]	NEWTABLE 	3 2 0
	3	[102]	LOADK    	4 -2	; "__proto"
	4	[102]	GETTABUP 	5 0 -3	; _ENV "Error"
	5	[102]	SETTABLE 	3 4 5
	6	[102]	LOADK    	4 -4	; "__index"
	7	[102]	GETTABUP 	5 0 -3	; _ENV "Error"
	8	[102]	SETTABLE 	3 4 5
	9	[102]	GETTABUP 	4 0 -5	; _ENV "setmetatable"
	10	[102]	MOVE     	5 3
	11	[102]	MOVE     	6 3
	12	[102]	CALL     	4 3 1
	13	[102]	SELF     	4 3 -6	; "constructor"
	14	[102]	TEST     	4 0
	15	[102]	JMP      	0 2	; to 18
	16	[102]	LOADK    	6 -7	; "Method not implemented."
	17	[102]	CALL     	4 3 1
	18	[102]	CALL     	2 2 1
	19	[102]	RETURN   	0 1
constants (7) for 0000029B1696B490:
	1	"error"
	2	"__proto"
	3	"Error"
	4	"__index"
	5	"setmetatable"
	6	"constructor"
	7	"Method not implemented."
locals (2) for 0000029B1696B490:
	0	this	1	21
	1	shader	1	21
upvalues (1) for 0000029B1696B490:
	0	_ENV	0	0

main <canvas.lua:0,0> (19 instructions at 0000029B1696C810)
3 params, 8 slots, 1 upvalue, 3 locals, 7 constants, 0 functions
	1	[103]	GETTABUP 	3 0 -1	; _ENV "error"
	2	[103]	NEWTABLE 	4 2 0
	3	[103]	LOADK    	5 -2	; "__proto"
	4	[103]	GETTABUP 	6 0 -3	; _ENV "Error"
	5	[103]	SETTABLE 	4 5 6
	6	[103]	LOADK    	5 -4	; "__index"
	7	[103]	GETTABUP 	6 0 -3	; _ENV "Error"
	8	[103]	SETTABLE 	4 5 6
	9	[103]	GETTABUP 	5 0 -5	; _ENV "setmetatable"
	10	[103]	MOVE     	6 4
	11	[103]	MOVE     	7 4
	12	[103]	CALL     	5 3 1
	13	[103]	SELF     	5 4 -6	; "constructor"
	14	[103]	TEST     	5 0
	15	[103]	JMP      	0 2	; to 18
	16	[103]	LOADK    	7 -7	; "Method not implemented."
	17	[103]	CALL     	5 3 1
	18	[103]	CALL     	3 2 1
	19	[103]	RETURN   	0 1
constants (7) for 0000029B1696C810:
	1	"error"
	2	"__proto"
	3	"Error"
	4	"__index"
	5	"setmetatable"
	6	"constructor"
	7	"Method not implemented."
locals (3) for 0000029B1696C810:
	0	this	1	21
	1	shader	1	21
	2	pname	1	21
upvalues (1) for 0000029B1696C810:
	0	_ENV	0	0

main <canvas.lua:0,0> (3 instructions at 0000029B1696CD90)
3 params, 4 slots, 0 upvalues, 3 locals, 1 constant, 0 functions
	1	[104]	LOADNIL  	3 1
	2	[104]	RETURN   	3 2
	3	[104]	RETURN   	0 1
constants (1) for 0000029B1696CD90:
	1	nil
locals (3) for 0000029B1696CD90:
	0	this	1	5
	1	shadertype	1	5
	2	precisiontype	1	5
upvalues (0) for 0000029B1696CD90:

main <canvas.lua:0,0> (19 instructions at 0000029B1696BB10)
2 params, 7 slots, 1 upvalue, 2 locals, 7 constants, 0 functions
	1	[105]	GETTABUP 	2 0 -1	; _ENV "error"
	2	[105]	NEWTABLE 	3 2 0
	3	[105]	LOADK    	4 -2	; "__proto"
	4	[105]	GETTABUP 	5 0 -3	; _ENV "Error"
	5	[105]	SETTABLE 	3 4 5
	6	[105]	LOADK    	4 -4	; "__index"
	7	[105]	GETTABUP 	5 0 -3	; _ENV "Error"
	8	[105]	SETTABLE 	3 4 5
	9	[105]	GETTABUP 	4 0 -5	; _ENV "setmetatable"
	10	[105]	MOVE     	5 3
	11	[105]	MOVE     	6 3
	12	[105]	CALL     	4 3 1
	13	[105]	SELF     	4 3 -6	; "constructor"
	14	[105]	TEST     	4 0
	15	[105]	JMP      	0 2	; to 18
	16	[105]	LOADK    	6 -7	; "Method not implemented."
	17	[105]	CALL     	4 3 1
	18	[105]	CALL     	2 2 1
	19	[105]	RETURN   	0 1
constants (7) for 0000029B1696BB10:
	1	"error"
	2	"__proto"
	3	"Error"
	4	"__index"
	5	"setmetatable"
	6	"constructor"
	7	"Method not implemented."
locals (2) for 0000029B1696BB10:
	0	this	1	21
	1	shader	1	21
upvalues (1) for 0000029B1696BB10:
	0	_ENV	0	0

main <canvas.lua:0,0> (19 instructions at 0000029B1696CE10)
1 param, 6 slots, 1 upvalue, 1 local, 7 constants, 0 functions
	1	[106]	GETTABUP 	1 0 -1	; _ENV "error"
	2	[106]	NEWTABLE 	2 2 0
	3	[106]	LOADK    	3 -2	; "__proto"
	4	[106]	GETTABUP 	4 0 -3	; _ENV "Error"
	5	[106]	SETTABLE 	2 3 4
	6	[106]	LOADK    	3 -4	; "__index"
	7	[106]	GETTABUP 	4 0 -3	; _ENV "Error"
	8	[106]	SETTABLE 	2 3 4
	9	[106]	GETTABUP 	3 0 -5	; _ENV "setmetatable"
	10	[106]	MOVE     	4 2
	11	[106]	MOVE     	5 2
	12	[106]	CALL     	3 3 1
	13	[106]	SELF     	3 2 -6	; "constructor"
	14	[106]	TEST     	3 0
	15	[106]	JMP      	0 2	; to 18
	16	[106]	LOADK    	5 -7	; "Method not implemented."
	17	[106]	CALL     	3 3 1
	18	[106]	CALL     	1 2 1
	19	[106]	RETURN   	0 1
constants (7) for 0000029B1696CE10:
	1	"error"
	2	"__proto"
	3	"Error"
	4	"__index"
	5	"setmetatable"
	6	"constructor"
	7	"Method not implemented."
locals (1) for 0000029B1696CE10:
	0	this	1	21
upvalues (1) for 0000029B1696CE10:
	0	_ENV	0	0

main <canvas.lua:0,0> (19 instructions at 0000029B1696B090)
3 params, 8 slots, 1 upvalue, 3 locals, 7 constants, 0 functions
	1	[107]	GETTABUP 	3 0 -1	; _ENV "error"
	2	[107]	NEWTABLE 	4 2 0
	3	[107]	LOADK    	5 -2	; "__proto"
	4	[107]	GETTABUP 	6 0 -3	; _ENV "Error"
	5	[107]	SETTABLE 	4 5 6
	6	[107]	LOADK    	5 -4	; "__index"
	7	[107]	GETTABUP 	6 0 -3	; _ENV "Error"
	8	[107]	SETTABLE 	4 5 6
	9	[107]	GETTABUP 	5 0 -5	; _ENV "setmetatable"
	10	[107]	MOVE     	6 4
	11	[107]	MOVE     	7 4
	12	[107]	CALL     	5 3 1
	13	[107]	SELF     	5 4 -6	; "constructor"
	14	[107]	TEST     	5 0
	15	[107]	JMP      	0 2	; to 18
	16	[107]	LOADK    	7 -7	; "Method not implemented."
	17	[107]	CALL     	5 3 1
	18	[107]	CALL     	3 2 1
	19	[107]	RETURN   	0 1
constants (7) for 0000029B1696B090:
	1	"error"
	2	"__proto"
	3	"Error"
	4	"__index"
	5	"setmetatable"
	6	"constructor"
	7	"Method not implemented."
locals (3) for 0000029B1696B090:
	0	this	1	21
	1	target	1	21
	2	pname	1	21
upvalues (1) for 0000029B1696B090:
	0	_ENV	0	0

main <canvas.lua:0,0> (19 instructions at 0000029B1696B790)
3 params, 8 slots, 1 upvalue, 3 locals, 7 constants, 0 functions
	1	[108]	GETTABUP 	3 0 -1	; _ENV "error"
	2	[108]	NEWTABLE 	4 2 0
	3	[108]	LOADK    	5 -2	; "__proto"
	4	[108]	GETTABUP 	6 0 -3	; _ENV "Error"
	5	[108]	SETTABLE 	4 5 6
	6	[108]	LOADK    	5 -4	; "__index"
	7	[108]	GETTABUP 	6 0 -3	; _ENV "Error"
	8	[108]	SETTABLE 	4 5 6
	9	[108]	GETTABUP 	5 0 -5	; _ENV "setmetatable"
	10	[108]	MOVE     	6 4
	11	[108]	MOVE     	7 4
	12	[108]	CALL     	5 3 1
	13	[108]	SELF     	5 4 -6	; "constructor"
	14	[108]	TEST     	5 0
	15	[108]	JMP      	0 2	; to 18
	16	[108]	LOADK    	7 -7	; "Method not implemented."
	17	[108]	CALL     	5 3 1
	18	[108]	CALL     	3 2 1
	19	[108]	RETURN   	0 1
constants (7) for 0000029B1696B790:
	1	"error"
	2	"__proto"
	3	"Error"
	4	"__index"
	5	"setmetatable"
	6	"constructor"
	7	"Method not implemented."
locals (3) for 0000029B1696B790:
	0	this	1	21
	1	program	1	21
	2	location	1	21
upvalues (1) for 0000029B1696B790:
	0	_ENV	0	0

main <canvas.lua:0,0> (19 instructions at 0000029B1696BF10)
3 params, 8 slots, 1 upvalue, 3 locals, 7 constants, 0 functions
	1	[109]	GETTABUP 	3 0 -1	; _ENV "error"
	2	[109]	NEWTABLE 	4 2 0
	3	[109]	LOADK    	5 -2	; "__proto"
	4	[109]	GETTABUP 	6 0 -3	; _ENV "Error"
	5	[109]	SETTABLE 	4 5 6
	6	[109]	LOADK    	5 -4	; "__index"
	7	[109]	GETTABUP 	6 0 -3	; _ENV "Error"
	8	[109]	SETTABLE 	4 5 6
	9	[109]	GETTABUP 	5 0 -5	; _ENV "setmetatable"
	10	[109]	MOVE     	6 4
	11	[109]	MOVE     	7 4
	12	[109]	CALL     	5 3 1
	13	[109]	SELF     	5 4 -6	; "constructor"
	14	[109]	TEST     	5 0
	15	[109]	JMP      	0 2	; to 18
	16	[109]	LOADK    	7 -7	; "Method not implemented."
	17	[109]	CALL     	5 3 1
	18	[109]	CALL     	3 2 1
	19	[109]	RETURN   	0 1
constants (7) for 0000029B1696BF10:
	1	"error"
	2	"__proto"
	3	"Error"
	4	"__index"
	5	"setmetatable"
	6	"constructor"
	7	"Method not implemented."
locals (3) for 0000029B1696BF10:
	0	this	1	21
	1	program	1	21
	2	name	1	21
upvalues (1) for 0000029B1696BF10:
	0	_ENV	0	0

main <canvas.lua:0,0> (19 instructions at 0000029B1696BF90)
3 params, 8 slots, 1 upvalue, 3 locals, 7 constants, 0 functions
	1	[110]	GETTABUP 	3 0 -1	; _ENV "error"
	2	[110]	NEWTABLE 	4 2 0
	3	[110]	LOADK    	5 -2	; "__proto"
	4	[110]	GETTABUP 	6 0 -3	; _ENV "Error"
	5	[110]	SETTABLE 	4 5 6
	6	[110]	LOADK    	5 -4	; "__index"
	7	[110]	GETTABUP 	6 0 -3	; _ENV "Error"
	8	[110]	SETTABLE 	4 5 6
	9	[110]	GETTABUP 	5 0 -5	; _ENV "setmetatable"
	10	[110]	MOVE     	6 4
	11	[110]	MOVE     	7 4
	12	[110]	CALL     	5 3 1
	13	[110]	SELF     	5 4 -6	; "constructor"
	14	[110]	TEST     	5 0
	15	[110]	JMP      	0 2	; to 18
	16	[110]	LOADK    	7 -7	; "Method not implemented."
	17	[110]	CALL     	5 3 1
	18	[110]	CALL     	3 2 1
	19	[110]	RETURN   	0 1
constants (7) for 0000029B1696BF90:
	1	"error"
	2	"__proto"
	3	"Error"
	4	"__index"
	5	"setmetatable"
	6	"constructor"
	7	"Method not implemented."
locals (3) for 0000029B1696BF90:
	0	this	1	21
	1	index	1	21
	2	pname	1	21
upvalues (1) for 0000029B1696BF90:
	0	_ENV	0	0

main <canvas.lua:0,0> (19 instructions at 0000029B1696B110)
3 params, 8 slots, 1 upvalue, 3 locals, 7 constants, 0 functions
	1	[111]	GETTABUP 	3 0 -1	; _ENV "error"
	2	[111]	NEWTABLE 	4 2 0
	3	[111]	LOADK    	5 -2	; "__proto"
	4	[111]	GETTABUP 	6 0 -3	; _ENV "Error"
	5	[111]	SETTABLE 	4 5 6
	6	[111]	LOADK    	5 -4	; "__index"
	7	[111]	GETTABUP 	6 0 -3	; _ENV "Error"
	8	[111]	SETTABLE 	4 5 6
	9	[111]	GETTABUP 	5 0 -5	; _ENV "setmetatable"
	10	[111]	MOVE     	6 4
	11	[111]	MOVE     	7 4
	12	[111]	CALL     	5 3 1
	13	[111]	SELF     	5 4 -6	; "constructor"
	14	[111]	TEST     	5 0
	15	[111]	JMP      	0 2	; to 18
	16	[111]	LOADK    	7 -7	; "Method not implemented."
	17	[111]	CALL     	5 3 1
	18	[111]	CALL     	3 2 1
	19	[111]	RETURN   	0 1
constants (7) for 0000029B1696B110:
	1	"error"
	2	"__proto"
	3	"Error"
	4	"__index"
	5	"setmetatable"
	6	"constructor"
	7	"Method not implemented."
locals (3) for 0000029B1696B110:
	0	this	1	21
	1	index	1	21
	2	pname	1	21
upvalues (1) for 0000029B1696B110:
	0	_ENV	0	0

main <canvas.lua:0,0> (19 instructions at 0000029B1696C990)
3 params, 8 slots, 1 upvalue, 3 locals, 7 constants, 0 functions
	1	[112]	GETTABUP 	3 0 -1	; _ENV "error"
	2	[112]	NEWTABLE 	4 2 0
	3	[112]	LOADK    	5 -2	; "__proto"
	4	[112]	GETTABUP 	6 0 -3	; _ENV "Error"
	5	[112]	SETTABLE 	4 5 6
	6	[112]	LOADK    	5 -4	; "__index"
	7	[112]	GETTABUP 	6 0 -3	; _ENV "Error"
	8	[112]	SETTABLE 	4 5 6
	9	[112]	GETTABUP 	5 0 -5	; _ENV "setmetatable"
	10	[112]	MOVE     	6 4
	11	[112]	MOVE     	7 4
	12	[112]	CALL     	5 3 1
	13	[112]	SELF     	5 4 -6	; "constructor"
	14	[112]	TEST     	5 0
	15	[112]	JMP      	0 2	; to 18
	16	[112]	LOADK    	7 -7	; "Method not implemented."
	17	[112]	CALL     	5 3 1
	18	[112]	CALL     	3 2 1
	19	[112]	RETURN   	0 1
constants (7) for 0000029B1696C990:
	1	"error"
	2	"__proto"
	3	"Error"
	4	"__index"
	5	"setmetatable"
	6	"constructor"
	7	"Method not implemented."
locals (3) for 0000029B1696C990:
	0	this	1	21
	1	target	1	21
	2	mode	1	21
upvalues (1) for 0000029B1696C990:
	0	_ENV	0	0

main <canvas.lua:0,0> (19 instructions at 0000029B1696C390)
2 params, 7 slots, 1 upvalue, 2 locals, 7 constants, 0 functions
	1	[113]	GETTABUP 	2 0 -1	; _ENV "error"
	2	[113]	NEWTABLE 	3 2 0
	3	[113]	LOADK    	4 -2	; "__proto"
	4	[113]	GETTABUP 	5 0 -3	; _ENV "Error"
	5	[113]	SETTABLE 	3 4 5
	6	[113]	LOADK    	4 -4	; "__index"
	7	[113]	GETTABUP 	5 0 -3	; _ENV "Error"
	8	[113]	SETTABLE 	3 4 5
	9	[113]	GETTABUP 	4 0 -5	; _ENV "setmetatable"
	10	[113]	MOVE     	5 3
	11	[113]	MOVE     	6 3
	12	[113]	CALL     	4 3 1
	13	[113]	SELF     	4 3 -6	; "constructor"
	14	[113]	TEST     	4 0
	15	[113]	JMP      	0 2	; to 18
	16	[113]	LOADK    	6 -7	; "Method not implemented."
	17	[113]	CALL     	4 3 1
	18	[113]	CALL     	2 2 1
	19	[113]	RETURN   	0 1
constants (7) for 0000029B1696C390:
	1	"error"
	2	"__proto"
	3	"Error"
	4	"__index"
	5	"setmetatable"
	6	"constructor"
	7	"Method not implemented."
locals (2) for 0000029B1696C390:
	0	this	1	21
	1	buffer	1	21
upvalues (1) for 0000029B1696C390:
	0	_ENV	0	0

main <canvas.lua:0,0> (19 instructions at 0000029B1696CB90)
1 param, 6 slots, 1 upvalue, 1 local, 7 constants, 0 functions
	1	[114]	GETTABUP 	1 0 -1	; _ENV "error"
	2	[114]	NEWTABLE 	2 2 0
	3	[114]	LOADK    	3 -2	; "__proto"
	4	[114]	GETTABUP 	4 0 -3	; _ENV "Error"
	5	[114]	SETTABLE 	2 3 4
	6	[114]	LOADK    	3 -4	; "__index"
	7	[114]	GETTABUP 	4 0 -3	; _ENV "Error"
	8	[114]	SETTABLE 	2 3 4
	9	[114]	GETTABUP 	3 0 -5	; _ENV "setmetatable"
	10	[114]	MOVE     	4 2
	11	[114]	MOVE     	5 2
	12	[114]	CALL     	3 3 1
	13	[114]	SELF     	3 2 -6	; "constructor"
	14	[114]	TEST     	3 0
	15	[114]	JMP      	0 2	; to 18
	16	[114]	LOADK    	5 -7	; "Method not implemented."
	17	[114]	CALL     	3 3 1
	18	[114]	CALL     	1 2 1
	19	[114]	RETURN   	0 1
constants (7) for 0000029B1696CB90:
	1	"error"
	2	"__proto"
	3	"Error"
	4	"__index"
	5	"setmetatable"
	6	"constructor"
	7	"Method not implemented."
locals (1) for 0000029B1696CB90:
	0	this	1	21
upvalues (1) for 0000029B1696CB90:
	0	_ENV	0	0

main <canvas.lua:0,0> (19 instructions at 0000029B1696B310)
2 params, 7 slots, 1 upvalue, 2 locals, 7 constants, 0 functions
	1	[115]	GETTABUP 	2 0 -1	; _ENV "error"
	2	[115]	NEWTABLE 	3 2 0
	3	[115]	LOADK    	4 -2	; "__proto"
	4	[115]	GETTABUP 	5 0 -3	; _ENV "Error"
	5	[115]	SETTABLE 	3 4 5
	6	[115]	LOADK    	4 -4	; "__index"
	7	[115]	GETTABUP 	5 0 -3	; _ENV "Error"
	8	[115]	SETTABLE 	3 4 5
	9	[115]	GETTABUP 	4 0 -5	; _ENV "setmetatable"
	10	[115]	MOVE     	5 3
	11	[115]	MOVE     	6 3
	12	[115]	CALL     	4 3 1
	13	[115]	SELF     	4 3 -6	; "constructor"
	14	[115]	TEST     	4 0
	15	[115]	JMP      	0 2	; to 18
	16	[115]	LOADK    	6 -7	; "Method not implemented."
	17	[115]	CALL     	4 3 1
	18	[115]	CALL     	2 2 1
	19	[115]	RETURN   	0 1
constants (7) for 0000029B1696B310:
	1	"error"
	2	"__proto"
	3	"Error"
	4	"__index"
	5	"setmetatable"
	6	"constructor"
	7	"Method not implemented."
locals (2) for 0000029B1696B310:
	0	this	1	21
	1	cap	1	21
upvalues (1) for 0000029B1696B310:
	0	_ENV	0	0

main <canvas.lua:0,0> (19 instructions at 0000029B1696B390)
2 params, 7 slots, 1 upvalue, 2 locals, 7 constants, 0 functions
	1	[116]	GETTABUP 	2 0 -1	; _ENV "error"
	2	[116]	NEWTABLE 	3 2 0
	3	[116]	LOADK    	4 -2	; "__proto"
	4	[116]	GETTABUP 	5 0 -3	; _ENV "Error"
	5	[116]	SETTABLE 	3 4 5
	6	[116]	LOADK    	4 -4	; "__index"
	7	[116]	GETTABUP 	5 0 -3	; _ENV "Error"
	8	[116]	SETTABLE 	3 4 5
	9	[116]	GETTABUP 	4 0 -5	; _ENV "setmetatable"
	10	[116]	MOVE     	5 3
	11	[116]	MOVE     	6 3
	12	[116]	CALL     	4 3 1
	13	[116]	SELF     	4 3 -6	; "constructor"
	14	[116]	TEST     	4 0
	15	[116]	JMP      	0 2	; to 18
	16	[116]	LOADK    	6 -7	; "Method not implemented."
	17	[116]	CALL     	4 3 1
	18	[116]	CALL     	2 2 1
	19	[116]	RETURN   	0 1
constants (7) for 0000029B1696B390:
	1	"error"
	2	"__proto"
	3	"Error"
	4	"__index"
	5	"setmetatable"
	6	"constructor"
	7	"Method not implemented."
locals (2) for 0000029B1696B390:
	0	this	1	21
	1	framebuffer	1	21
upvalues (1) for 0000029B1696B390:
	0	_ENV	0	0

main <canvas.lua:0,0> (19 instructions at 0000029B1696B590)
2 params, 7 slots, 1 upvalue, 2 locals, 7 constants, 0 functions
	1	[117]	GETTABUP 	2 0 -1	; _ENV "error"
	2	[117]	NEWTABLE 	3 2 0
	3	[117]	LOADK    	4 -2	; "__proto"
	4	[117]	GETTABUP 	5 0 -3	; _ENV "Error"
	5	[117]	SETTABLE 	3 4 5
	6	[117]	LOADK    	4 -4	; "__index"
	7	[117]	GETTABUP 	5 0 -3	; _ENV "Error"
	8	[117]	SETTABLE 	3 4 5
	9	[117]	GETTABUP 	4 0 -5	; _ENV "setmetatable"
	10	[117]	MOVE     	5 3
	11	[117]	MOVE     	6 3
	12	[117]	CALL     	4 3 1
	13	[117]	SELF     	4 3 -6	; "constructor"
	14	[117]	TEST     	4 0
	15	[117]	JMP      	0 2	; to 18
	16	[117]	LOADK    	6 -7	; "Method not implemented."
	17	[117]	CALL     	4 3 1
	18	[117]	CALL     	2 2 1
	19	[117]	RETURN   	0 1
constants (7) for 0000029B1696B590:
	1	"error"
	2	"__proto"
	3	"Error"
	4	"__index"
	5	"setmetatable"
	6	"constructor"
	7	"Method not implemented."
locals (2) for 0000029B1696B590:
	0	this	1	21
	1	program	1	21
upvalues (1) for 0000029B1696B590:
	0	_ENV	0	0

main <canvas.lua:0,0> (19 instructions at 0000029B1696B710)
2 params, 7 slots, 1 upvalue, 2 locals, 7 constants, 0 functions
	1	[118]	GETTABUP 	2 0 -1	; _ENV "error"
	2	[118]	NEWTABLE 	3 2 0
	3	[118]	LOADK    	4 -2	; "__proto"
	4	[118]	GETTABUP 	5 0 -3	; _ENV "Error"
	5	[118]	SETTABLE 	3 4 5
	6	[118]	LOADK    	4 -4	; "__index"
	7	[118]	GETTABUP 	5 0 -3	; _ENV "Error"
	8	[118]	SETTABLE 	3 4 5
	9	[118]	GETTABUP 	4 0 -5	; _ENV "setmetatable"
	10	[118]	MOVE     	5 3
	11	[118]	MOVE     	6 3
	12	[118]	CALL     	4 3 1
	13	[118]	SELF     	4 3 -6	; "constructor"
	14	[118]	TEST     	4 0
	15	[118]	JMP      	0 2	; to 18
	16	[118]	LOADK    	6 -7	; "Method not implemented."
	17	[118]	CALL     	4 3 1
	18	[118]	CALL     	2 2 1
	19	[118]	RETURN   	0 1
constants (7) for 0000029B1696B710:
	1	"error"
	2	"__proto"
	3	"Error"
	4	"__index"
	5	"setmetatable"
	6	"constructor"
	7	"Method not implemented."
locals (2) for 0000029B1696B710:
	0	this	1	21
	1	renderbuffer	1	21
upvalues (1) for 0000029B1696B710:
	0	_ENV	0	0

main <canvas.lua:0,0> (19 instructions at 0000029B169719D0)
2 params, 7 slots, 1 upvalue, 2 locals, 7 constants, 0 functions
	1	[119]	GETTABUP 	2 0 -1	; _ENV "error"
	2	[119]	NEWTABLE 	3 2 0
	3	[119]	LOADK    	4 -2	; "__proto"
	4	[119]	GETTABUP 	5 0 -3	; _ENV "Error"
	5	[119]	SETTABLE 	3 4 5
	6	[119]	LOADK    	4 -4	; "__index"
	7	[119]	GETTABUP 	5 0 -3	; _ENV "Error"
	8	[119]	SETTABLE 	3 4 5
	9	[119]	GETTABUP 	4 0 -5	; _ENV "setmetatable"
	10	[119]	MOVE     	5 3
	11	[119]	MOVE     	6 3
	12	[119]	CALL     	4 3 1
	13	[119]	SELF     	4 3 -6	; "constructor"
	14	[119]	TEST     	4 0
	15	[119]	JMP      	0 2	; to 18
	16	[119]	LOADK    	6 -7	; "Method not implemented."
	17	[119]	CALL     	4 3 1
	18	[119]	CALL     	2 2 1
	19	[119]	RETURN   	0 1
constants (7) for 0000029B169719D0:
	1	"error"
	2	"__proto"
	3	"Error"
	4	"__index"
	5	"setmetatable"
	6	"constructor"
	7	"Method not implemented."
locals (2) for 0000029B169719D0:
	0	this	1	21
	1	shader	1	21
upvalues (1) for 0000029B169719D0:
	0	_ENV	0	0

main <canvas.lua:0,0> (19 instructions at 0000029B16970850)
2 params, 7 slots, 1 upvalue, 2 locals, 7 constants, 0 functions
	1	[120]	GETTABUP 	2 0 -1	; _ENV "error"
	2	[120]	NEWTABLE 	3 2 0
	3	[120]	LOADK    	4 -2	; "__proto"
	4	[120]	GETTABUP 	5 0 -3	; _ENV "Error"
	5	[120]	SETTABLE 	3 4 5
	6	[120]	LOADK    	4 -4	; "__index"
	7	[120]	GETTABUP 	5 0 -3	; _ENV "Error"
	8	[120]	SETTABLE 	3 4 5
	9	[120]	GETTABUP 	4 0 -5	; _ENV "setmetatable"
	10	[120]	MOVE     	5 3
	11	[120]	MOVE     	6 3
	12	[120]	CALL     	4 3 1
	13	[120]	SELF     	4 3 -6	; "constructor"
	14	[120]	TEST     	4 0
	15	[120]	JMP      	0 2	; to 18
	16	[120]	LOADK    	6 -7	; "Method not implemented."
	17	[120]	CALL     	4 3 1
	18	[120]	CALL     	2 2 1
	19	[120]	RETURN   	0 1
constants (7) for 0000029B16970850:
	1	"error"
	2	"__proto"
	3	"Error"
	4	"__index"
	5	"setmetatable"
	6	"constructor"
	7	"Method not implemented."
locals (2) for 0000029B16970850:
	0	this	1	21
	1	texture	1	21
upvalues (1) for 0000029B16970850:
	0	_ENV	0	0

main <canvas.lua:0,0> (19 instructions at 0000029B16971DD0)
2 params, 7 slots, 1 upvalue, 2 locals, 7 constants, 0 functions
	1	[121]	GETTABUP 	2 0 -1	; _ENV "error"
	2	[121]	NEWTABLE 	3 2 0
	3	[121]	LOADK    	4 -2	; "__proto"
	4	[121]	GETTABUP 	5 0 -3	; _ENV "Error"
	5	[121]	SETTABLE 	3 4 5
	6	[121]	LOADK    	4 -4	; "__index"
	7	[121]	GETTABUP 	5 0 -3	; _ENV "Error"
	8	[121]	SETTABLE 	3 4 5
	9	[121]	GETTABUP 	4 0 -5	; _ENV "setmetatable"
	10	[121]	MOVE     	5 3
	11	[121]	MOVE     	6 3
	12	[121]	CALL     	4 3 1
	13	[121]	SELF     	4 3 -6	; "constructor"
	14	[121]	TEST     	4 0
	15	[121]	JMP      	0 2	; to 18
	16	[121]	LOADK    	6 -7	; "Method not implemented."
	17	[121]	CALL     	4 3 1
	18	[121]	CALL     	2 2 1
	19	[121]	RETURN   	0 1
constants (7) for 0000029B16971DD0:
	1	"error"
	2	"__proto"
	3	"Error"
	4	"__index"
	5	"setmetatable"
	6	"constructor"
	7	"Method not implemented."
locals (2) for 0000029B16971DD0:
	0	this	1	21
	1	width	1	21
upvalues (1) for 0000029B16971DD0:
	0	_ENV	0	0

main <canvas.lua:0,0> (19 instructions at 0000029B16970E50)
2 params, 7 slots, 1 upvalue, 2 locals, 7 constants, 0 functions
	1	[122]	GETTABUP 	2 0 -1	; _ENV "error"
	2	[122]	NEWTABLE 	3 2 0
	3	[122]	LOADK    	4 -2	; "__proto"
	4	[122]	GETTABUP 	5 0 -3	; _ENV "Error"
	5	[122]	SETTABLE 	3 4 5
	6	[122]	LOADK    	4 -4	; "__index"
	7	[122]	GETTABUP 	5 0 -3	; _ENV "Error"
	8	[122]	SETTABLE 	3 4 5
	9	[122]	GETTABUP 	4 0 -5	; _ENV "setmetatable"
	10	[122]	MOVE     	5 3
	11	[122]	MOVE     	6 3
	12	[122]	CALL     	4 3 1
	13	[122]	SELF     	4 3 -6	; "constructor"
	14	[122]	TEST     	4 0
	15	[122]	JMP      	0 2	; to 18
	16	[122]	LOADK    	6 -7	; "Method not implemented."
	17	[122]	CALL     	4 3 1
	18	[122]	CALL     	2 2 1
	19	[122]	RETURN   	0 1
constants (7) for 0000029B16970E50:
	1	"error"
	2	"__proto"
	3	"Error"
	4	"__index"
	5	"setmetatable"
	6	"constructor"
	7	"Method not implemented."
locals (2) for 0000029B16970E50:
	0	this	1	21
	1	program	1	21
upvalues (1) for 0000029B16970E50:
	0	_ENV	0	0

main <canvas.lua:0,0> (19 instructions at 0000029B16970950)
3 params, 8 slots, 1 upvalue, 3 locals, 7 constants, 0 functions
	1	[123]	GETTABUP 	3 0 -1	; _ENV "error"
	2	[123]	NEWTABLE 	4 2 0
	3	[123]	LOADK    	5 -2	; "__proto"
	4	[123]	GETTABUP 	6 0 -3	; _ENV "Error"
	5	[123]	SETTABLE 	4 5 6
	6	[123]	LOADK    	5 -4	; "__index"
	7	[123]	GETTABUP 	6 0 -3	; _ENV "Error"
	8	[123]	SETTABLE 	4 5 6
	9	[123]	GETTABUP 	5 0 -5	; _ENV "setmetatable"
	10	[123]	MOVE     	6 4
	11	[123]	MOVE     	7 4
	12	[123]	CALL     	5 3 1
	13	[123]	SELF     	5 4 -6	; "constructor"
	14	[123]	TEST     	5 0
	15	[123]	JMP      	0 2	; to 18
	16	[123]	LOADK    	7 -7	; "Method not implemented."
	17	[123]	CALL     	5 3 1
	18	[123]	CALL     	3 2 1
	19	[123]	RETURN   	0 1
constants (7) for 0000029B16970950:
	1	"error"
	2	"__proto"
	3	"Error"
	4	"__index"
	5	"setmetatable"
	6	"constructor"
	7	"Method not implemented."
locals (3) for 0000029B16970950:
	0	this	1	21
	1	pname	1	21
	2	param	1	21
upvalues (1) for 0000029B16970950:
	0	_ENV	0	0

main <canvas.lua:0,0> (19 instructions at 0000029B16971E50)
3 params, 8 slots, 1 upvalue, 3 locals, 7 constants, 0 functions
	1	[124]	GETTABUP 	3 0 -1	; _ENV "error"
	2	[124]	NEWTABLE 	4 2 0
	3	[124]	LOADK    	5 -2	; "__proto"
	4	[124]	GETTABUP 	6 0 -3	; _ENV "Error"
	5	[124]	SETTABLE 	4 5 6
	6	[124]	LOADK    	5 -4	; "__index"
	7	[124]	GETTABUP 	6 0 -3	; _ENV "Error"
	8	[124]	SETTABLE 	4 5 6
	9	[124]	GETTABUP 	5 0 -5	; _ENV "setmetatable"
	10	[124]	MOVE     	6 4
	11	[124]	MOVE     	7 4
	12	[124]	CALL     	5 3 1
	13	[124]	SELF     	5 4 -6	; "constructor"
	14	[124]	TEST     	5 0
	15	[124]	JMP      	0 2	; to 18
	16	[124]	LOADK    	7 -7	; "Method not implemented."
	17	[124]	CALL     	5 3 1
	18	[124]	CALL     	3 2 1
	19	[124]	RETURN   	0 1
constants (7) for 0000029B16971E50:
	1	"error"
	2	"__proto"
	3	"Error"
	4	"__index"
	5	"setmetatable"
	6	"constructor"
	7	"Method not implemented."
locals (3) for 0000029B16971E50:
	0	this	1	21
	1	factor	1	21
	2	units	1	21
upvalues (1) for 0000029B16971E50:
	0	_ENV	0	0

main <canvas.lua:0,0> (19 instructions at 0000029B16972450)
8 params, 13 slots, 1 upvalue, 8 locals, 7 constants, 0 functions
	1	[125]	GETTABUP 	8 0 -1	; _ENV "error"
	2	[125]	NEWTABLE 	9 2 0
	3	[125]	LOADK    	10 -2	; "__proto"
	4	[125]	GETTABUP 	11 0 -3	; _ENV "Error"
	5	[125]	SETTABLE 	9 10 11
	6	[125]	LOADK    	10 -4	; "__index"
	7	[125]	GETTABUP 	11 0 -3	; _ENV "Error"
	8	[125]	SETTABLE 	9 10 11
	9	[125]	GETTABUP 	10 0 -5	; _ENV "setmetatable"
	10	[125]	MOVE     	11 9
	11	[125]	MOVE     	12 9
	12	[125]	CALL     	10 3 1
	13	[125]	SELF     	10 9 -6	; "constructor"
	14	[125]	TEST     	10 0
	15	[125]	JMP      	0 2	; to 18
	16	[125]	LOADK    	12 -7	; "Method not implemented."
	17	[125]	CALL     	10 3 1
	18	[125]	CALL     	8 2 1
	19	[125]	RETURN   	0 1
constants (7) for 0000029B16972450:
	1	"error"
	2	"__proto"
	3	"Error"
	4	"__index"
	5	"setmetatable"
	6	"constructor"
	7	"Method not implemented."
locals (8) for 0000029B16972450:
	0	this	1	21
	1	x	1	21
	2	y	1	21
	3	width	1	21
	4	height	1	21
	5	format	1	21
	6	type	1	21
	7	pixels	1	21
upvalues (1) for 0000029B16972450:
	0	_ENV	0	0

main <canvas.lua:0,0> (19 instructions at 0000029B16971A50)
5 params, 10 slots, 1 upvalue, 5 locals, 7 constants, 0 functions
	1	[126]	GETTABUP 	5 0 -1	; _ENV "error"
	2	[126]	NEWTABLE 	6 2 0
	3	[126]	LOADK    	7 -2	; "__proto"
	4	[126]	GETTABUP 	8 0 -3	; _ENV "Error"
	5	[126]	SETTABLE 	6 7 8
	6	[126]	LOADK    	7 -4	; "__index"
	7	[126]	GETTABUP 	8 0 -3	; _ENV "Error"
	8	[126]	SETTABLE 	6 7 8
	9	[126]	GETTABUP 	7 0 -5	; _ENV "setmetatable"
	10	[126]	MOVE     	8 6
	11	[126]	MOVE     	9 6
	12	[126]	CALL     	7 3 1
	13	[126]	SELF     	7 6 -6	; "constructor"
	14	[126]	TEST     	7 0
	15	[126]	JMP      	0 2	; to 18
	16	[126]	LOADK    	9 -7	; "Method not implemented."
	17	[126]	CALL     	7 3 1
	18	[126]	CALL     	5 2 1
	19	[126]	RETURN   	0 1
constants (7) for 0000029B16971A50:
	1	"error"
	2	"__proto"
	3	"Error"
	4	"__index"
	5	"setmetatable"
	6	"constructor"
	7	"Method not implemented."
locals (5) for 0000029B16971A50:
	0	this	1	21
	1	target	1	21
	2	internalformat	1	21
	3	width	1	21
	4	height	1	21
upvalues (1) for 0000029B16971A50:
	0	_ENV	0	0

main <canvas.lua:0,0> (19 instructions at 0000029B169717D0)
3 params, 8 slots, 1 upvalue, 3 locals, 7 constants, 0 functions
	1	[127]	GETTABUP 	3 0 -1	; _ENV "error"
	2	[127]	NEWTABLE 	4 2 0
	3	[127]	LOADK    	5 -2	; "__proto"
	4	[127]	GETTABUP 	6 0 -3	; _ENV "Error"
	5	[127]	SETTABLE 	4 5 6
	6	[127]	LOADK    	5 -4	; "__index"
	7	[127]	GETTABUP 	6 0 -3	; _ENV "Error"
	8	[127]	SETTABLE 	4 5 6
	9	[127]	GETTABUP 	5 0 -5	; _ENV "setmetatable"
	10	[127]	MOVE     	6 4
	11	[127]	MOVE     	7 4
	12	[127]	CALL     	5 3 1
	13	[127]	SELF     	5 4 -6	; "constructor"
	14	[127]	TEST     	5 0
	15	[127]	JMP      	0 2	; to 18
	16	[127]	LOADK    	7 -7	; "Method not implemented."
	17	[127]	CALL     	5 3 1
	18	[127]	CALL     	3 2 1
	19	[127]	RETURN   	0 1
constants (7) for 0000029B169717D0:
	1	"error"
	2	"__proto"
	3	"Error"
	4	"__index"
	5	"setmetatable"
	6	"constructor"
	7	"Method not implemented."
locals (3) for 0000029B169717D0:
	0	this	1	21
	1	value	1	21
	2	invert	1	21
upvalues (1) for 0000029B169717D0:
	0	_ENV	0	0

main <canvas.lua:0,0> (19 instructions at 0000029B169720D0)
5 params, 10 slots, 1 upvalue, 5 locals, 7 constants, 0 functions
	1	[128]	GETTABUP 	5 0 -1	; _ENV "error"
	2	[128]	NEWTABLE 	6 2 0
	3	[128]	LOADK    	7 -2	; "__proto"
	4	[128]	GETTABUP 	8 0 -3	; _ENV "Error"
	5	[128]	SETTABLE 	6 7 8
	6	[128]	LOADK    	7 -4	; "__index"
	7	[128]	GETTABUP 	8 0 -3	; _ENV "Error"
	8	[128]	SETTABLE 	6 7 8
	9	[128]	GETTABUP 	7 0 -5	; _ENV "setmetatable"
	10	[128]	MOVE     	8 6
	11	[128]	MOVE     	9 6
	12	[128]	CALL     	7 3 1
	13	[128]	SELF     	7 6 -6	; "constructor"
	14	[128]	TEST     	7 0
	15	[128]	JMP      	0 2	; to 18
	16	[128]	LOADK    	9 -7	; "Method not implemented."
	17	[128]	CALL     	7 3 1
	18	[128]	CALL     	5 2 1
	19	[128]	RETURN   	0 1
constants (7) for 0000029B169720D0:
	1	"error"
	2	"__proto"
	3	"Error"
	4	"__index"
	5	"setmetatable"
	6	"constructor"
	7	"Method not implemented."
locals (5) for 0000029B169720D0:
	0	this	1	21
	1	x	1	21
	2	y	1	21
	3	width	1	21
	4	height	1	21
upvalues (1) for 0000029B169720D0:
	0	_ENV	0	0

main <canvas.lua:0,0> (19 instructions at 0000029B16972150)
3 params, 8 slots, 1 upvalue, 3 locals, 7 constants, 0 functions
	1	[129]	GETTABUP 	3 0 -1	; _ENV "error"
	2	[129]	NEWTABLE 	4 2 0
	3	[129]	LOADK    	5 -2	; "__proto"
	4	[129]	GETTABUP 	6 0 -3	; _ENV "Error"
	5	[129]	SETTABLE 	4 5 6
	6	[129]	LOADK    	5 -4	; "__index"
	7	[129]	GETTABUP 	6 0 -3	; _ENV "Error"
	8	[129]	SETTABLE 	4 5 6
	9	[129]	GETTABUP 	5 0 -5	; _ENV "setmetatable"
	10	[129]	MOVE     	6 4
	11	[129]	MOVE     	7 4
	12	[129]	CALL     	5 3 1
	13	[129]	SELF     	5 4 -6	; "constructor"
	14	[129]	TEST     	5 0
	15	[129]	JMP      	0 2	; to 18
	16	[129]	LOADK    	7 -7	; "Method not implemented."
	17	[129]	CALL     	5 3 1
	18	[129]	CALL     	3 2 1
	19	[129]	RETURN   	0 1
constants (7) for 0000029B16972150:
	1	"error"
	2	"__proto"
	3	"Error"
	4	"__index"
	5	"setmetatable"
	6	"constructor"
	7	"Method not implemented."
locals (3) for 0000029B16972150:
	0	this	1	21
	1	shader	1	21
	2	source	1	21
upvalues (1) for 0000029B16972150:
	0	_ENV	0	0

main <canvas.lua:0,0> (19 instructions at 0000029B169716D0)
4 params, 9 slots, 1 upvalue, 4 locals, 7 constants, 0 functions
	1	[130]	GETTABUP 	4 0 -1	; _ENV "error"
	2	[130]	NEWTABLE 	5 2 0
	3	[130]	LOADK    	6 -2	; "__proto"
	4	[130]	GETTABUP 	7 0 -3	; _ENV "Error"
	5	[130]	SETTABLE 	5 6 7
	6	[130]	LOADK    	6 -4	; "__index"
	7	[130]	GETTABUP 	7 0 -3	; _ENV "Error"
	8	[130]	SETTABLE 	5 6 7
	9	[130]	GETTABUP 	6 0 -5	; _ENV "setmetatable"
	10	[130]	MOVE     	7 5
	11	[130]	MOVE     	8 5
	12	[130]	CALL     	6 3 1
	13	[130]	SELF     	6 5 -6	; "constructor"
	14	[130]	TEST     	6 0
	15	[130]	JMP      	0 2	; to 18
	16	[130]	LOADK    	8 -7	; "Method not implemented."
	17	[130]	CALL     	6 3 1
	18	[130]	CALL     	4 2 1
	19	[130]	RETURN   	0 1
constants (7) for 0000029B169716D0:
	1	"error"
	2	"__proto"
	3	"Error"
	4	"__index"
	5	"setmetatable"
	6	"constructor"
	7	"Method not implemented."
locals (4) for 0000029B169716D0:
	0	this	1	21
	1	func	1	21
	2	ref	1	21
	3	mask	1	21
upvalues (1) for 0000029B169716D0:
	0	_ENV	0	0

main <canvas.lua:0,0> (19 instructions at 0000029B16971CD0)
5 params, 10 slots, 1 upvalue, 5 locals, 7 constants, 0 functions
	1	[131]	GETTABUP 	5 0 -1	; _ENV "error"
	2	[131]	NEWTABLE 	6 2 0
	3	[131]	LOADK    	7 -2	; "__proto"
	4	[131]	GETTABUP 	8 0 -3	; _ENV "Error"
	5	[131]	SETTABLE 	6 7 8
	6	[131]	LOADK    	7 -4	; "__index"
	7	[131]	GETTABUP 	8 0 -3	; _ENV "Error"
	8	[131]	SETTABLE 	6 7 8
	9	[131]	GETTABUP 	7 0 -5	; _ENV "setmetatable"
	10	[131]	MOVE     	8 6
	11	[131]	MOVE     	9 6
	12	[131]	CALL     	7 3 1
	13	[131]	SELF     	7 6 -6	; "constructor"
	14	[131]	TEST     	7 0
	15	[131]	JMP      	0 2	; to 18
	16	[131]	LOADK    	9 -7	; "Method not implemented."
	17	[131]	CALL     	7 3 1
	18	[131]	CALL     	5 2 1
	19	[131]	RETURN   	0 1
constants (7) for 0000029B16971CD0:
	1	"error"
	2	"__proto"
	3	"Error"
	4	"__index"
	5	"setmetatable"
	6	"constructor"
	7	"Method not implemented."
locals (5) for 0000029B16971CD0:
	0	this	1	21
	1	face	1	21
	2	func	1	21
	3	ref	1	21
	4	mask	1	21
upvalues (1) for 0000029B16971CD0:
	0	_ENV	0	0

main <canvas.lua:0,0> (19 instructions at 0000029B16971950)
2 params, 7 slots, 1 upvalue, 2 locals, 7 constants, 0 functions
	1	[132]	GETTABUP 	2 0 -1	; _ENV "error"
	2	[132]	NEWTABLE 	3 2 0
	3	[132]	LOADK    	4 -2	; "__proto"
	4	[132]	GETTABUP 	5 0 -3	; _ENV "Error"
	5	[132]	SETTABLE 	3 4 5
	6	[132]	LOADK    	4 -4	; "__index"
	7	[132]	GETTABUP 	5 0 -3	; _ENV "Error"
	8	[132]	SETTABLE 	3 4 5
	9	[132]	GETTABUP 	4 0 -5	; _ENV "setmetatable"
	10	[132]	MOVE     	5 3
	11	[132]	MOVE     	6 3
	12	[132]	CALL     	4 3 1
	13	[132]	SELF     	4 3 -6	; "constructor"
	14	[132]	TEST     	4 0
	15	[132]	JMP      	0 2	; to 18
	16	[132]	LOADK    	6 -7	; "Method not implemented."
	17	[132]	CALL     	4 3 1
	18	[132]	CALL     	2 2 1
	19	[132]	RETURN   	0 1
constants (7) for 0000029B16971950:
	1	"error"
	2	"__proto"
	3	"Error"
	4	"__index"
	5	"setmetatable"
	6	"constructor"
	7	"Method not implemented."
locals (2) for 0000029B16971950:
	0	this	1	21
	1	mask	1	21
upvalues (1) for 0000029B16971950:
	0	_ENV	0	0

main <canvas.lua:0,0> (19 instructions at 0000029B169718D0)
3 params, 8 slots, 1 upvalue, 3 locals, 7 constants, 0 functions
	1	[133]	GETTABUP 	3 0 -1	; _ENV "error"
	2	[133]	NEWTABLE 	4 2 0
	3	[133]	LOADK    	5 -2	; "__proto"
	4	[133]	GETTABUP 	6 0 -3	; _ENV "Error"
	5	[133]	SETTABLE 	4 5 6
	6	[133]	LOADK    	5 -4	; "__index"
	7	[133]	GETTABUP 	6 0 -3	; _ENV "Error"
	8	[133]	SETTABLE 	4 5 6
	9	[133]	GETTABUP 	5 0 -5	; _ENV "setmetatable"
	10	[133]	MOVE     	6 4
	11	[133]	MOVE     	7 4
	12	[133]	CALL     	5 3 1
	13	[133]	SELF     	5 4 -6	; "constructor"
	14	[133]	TEST     	5 0
	15	[133]	JMP      	0 2	; to 18
	16	[133]	LOADK    	7 -7	; "Method not implemented."
	17	[133]	CALL     	5 3 1
	18	[133]	CALL     	3 2 1
	19	[133]	RETURN   	0 1
constants (7) for 0000029B169718D0:
	1	"error"
	2	"__proto"
	3	"Error"
	4	"__index"
	5	"setmetatable"
	6	"constructor"
	7	"Method not implemented."
locals (3) for 0000029B169718D0:
	0	this	1	21
	1	face	1	21
	2	mask	1	21
upvalues (1) for 0000029B169718D0:
	0	_ENV	0	0

main <canvas.lua:0,0> (19 instructions at 0000029B16970CD0)
4 params, 9 slots, 1 upvalue, 4 locals, 7 constants, 0 functions
	1	[134]	GETTABUP 	4 0 -1	; _ENV "error"
	2	[134]	NEWTABLE 	5 2 0
	3	[134]	LOADK    	6 -2	; "__proto"
	4	[134]	GETTABUP 	7 0 -3	; _ENV "Error"
	5	[134]	SETTABLE 	5 6 7
	6	[134]	LOADK    	6 -4	; "__index"
	7	[134]	GETTABUP 	7 0 -3	; _ENV "Error"
	8	[134]	SETTABLE 	5 6 7
	9	[134]	GETTABUP 	6 0 -5	; _ENV "setmetatable"
	10	[134]	MOVE     	7 5
	11	[134]	MOVE     	8 5
	12	[134]	CALL     	6 3 1
	13	[134]	SELF     	6 5 -6	; "constructor"
	14	[134]	TEST     	6 0
	15	[134]	JMP      	0 2	; to 18
	16	[134]	LOADK    	8 -7	; "Method not implemented."
	17	[134]	CALL     	6 3 1
	18	[134]	CALL     	4 2 1
	19	[134]	RETURN   	0 1
constants (7) for 0000029B16970CD0:
	1	"error"
	2	"__proto"
	3	"Error"
	4	"__index"
	5	"setmetatable"
	6	"constructor"
	7	"Method not implemented."
locals (4) for 0000029B16970CD0:
	0	this	1	21
	1	fail	1	21
	2	zfail	1	21
	3	zpass	1	21
upvalues (1) for 0000029B16970CD0:
	0	_ENV	0	0

main <canvas.lua:0,0> (19 instructions at 0000029B169714D0)
5 params, 10 slots, 1 upvalue, 5 locals, 7 constants, 0 functions
	1	[135]	GETTABUP 	5 0 -1	; _ENV "error"
	2	[135]	NEWTABLE 	6 2 0
	3	[135]	LOADK    	7 -2	; "__proto"
	4	[135]	GETTABUP 	8 0 -3	; _ENV "Error"
	5	[135]	SETTABLE 	6 7 8
	6	[135]	LOADK    	7 -4	; "__index"
	7	[135]	GETTABUP 	8 0 -3	; _ENV "Error"
	8	[135]	SETTABLE 	6 7 8
	9	[135]	GETTABUP 	7 0 -5	; _ENV "setmetatable"
	10	[135]	MOVE     	8 6
	11	[135]	MOVE     	9 6
	12	[135]	CALL     	7 3 1
	13	[135]	SELF     	7 6 -6	; "constructor"
	14	[135]	TEST     	7 0
	15	[135]	JMP      	0 2	; to 18
	16	[135]	LOADK    	9 -7	; "Method not implemented."
	17	[135]	CALL     	7 3 1
	18	[135]	CALL     	5 2 1
	19	[135]	RETURN   	0 1
constants (7) for 0000029B169714D0:
	1	"error"
	2	"__proto"
	3	"Error"
	4	"__index"
	5	"setmetatable"
	6	"constructor"
	7	"Method not implemented."
locals (5) for 0000029B169714D0:
	0	this	1	21
	1	face	1	21
	2	fail	1	21
	3	zfail	1	21
	4	zpass	1	21
upvalues (1) for 0000029B169714D0:
	0	_ENV	0	0

main <canvas.lua:0,0> (19 instructions at 0000029B16971650)
10 params, 15 slots, 1 upvalue, 10 locals, 7 constants, 0 functions
	1	[136]	GETTABUP 	10 0 -1	; _ENV "error"
	2	[136]	NEWTABLE 	11 2 0
	3	[136]	LOADK    	12 -2	; "__proto"
	4	[136]	GETTABUP 	13 0 -3	; _ENV "Error"
	5	[136]	SETTABLE 	11 12 13
	6	[136]	LOADK    	12 -4	; "__index"
	7	[136]	GETTABUP 	13 0 -3	; _ENV "Error"
	8	[136]	SETTABLE 	11 12 13
	9	[136]	GETTABUP 	12 0 -5	; _ENV "setmetatable"
	10	[136]	MOVE     	13 11
	11	[136]	MOVE     	14 11
	12	[136]	CALL     	12 3 1
	13	[136]	SELF     	12 11 -6	; "constructor"
	14	[136]	TEST     	12 0
	15	[136]	JMP      	0 2	; to 18
	16	[136]	LOADK    	14 -7	; "Method not implemented."
	17	[136]	CALL     	12 3 1
	18	[136]	CALL     	10 2 1
	19	[136]	RETURN   	0 1
constants (7) for 0000029B16971650:
	1	"error"
	2	"__proto"
	3	"Error"
	4	"__index"
	5	"setmetatable"
	6	"constructor"
	7	"Method not implemented."
locals (10) for 0000029B16971650:
	0	this	1	21
	1	target	1	21
	2	level	1	21
	3	internalformat	1	21
	4	width	1	21
	5	height	1	21
	6	border	1	21
	7	format	1	21
	8	type	1	21
	9	pixels	1	21
upvalues (1) for 0000029B16971650:
	0	_ENV	0	0

main <canvas.lua:0,0> (19 instructions at 0000029B16972250)
4 params, 9 slots, 1 upvalue, 4 locals, 7 constants, 0 functions
	1	[137]	GETTABUP 	4 0 -1	; _ENV "error"
	2	[137]	NEWTABLE 	5 2 0
	3	[137]	LOADK    	6 -2	; "__proto"
	4	[137]	GETTABUP 	7 0 -3	; _ENV "Error"
	5	[137]	SETTABLE 	5 6 7
	6	[137]	LOADK    	6 -4	; "__index"
	7	[137]	GETTABUP 	7 0 -3	; _ENV "Error"
	8	[137]	SETTABLE 	5 6 7
	9	[137]	GETTABUP 	6 0 -5	; _ENV "setmetatable"
	10	[137]	MOVE     	7 5
	11	[137]	MOVE     	8 5
	12	[137]	CALL     	6 3 1
	13	[137]	SELF     	6 5 -6	; "constructor"
	14	[137]	TEST     	6 0
	15	[137]	JMP      	0 2	; to 18
	16	[137]	LOADK    	8 -7	; "Method not implemented."
	17	[137]	CALL     	6 3 1
	18	[137]	CALL     	4 2 1
	19	[137]	RETURN   	0 1
constants (7) for 0000029B16972250:
	1	"error"
	2	"__proto"
	3	"Error"
	4	"__index"
	5	"setmetatable"
	6	"constructor"
	7	"Method not implemented."
locals (4) for 0000029B16972250:
	0	this	1	21
	1	target	1	21
	2	pname	1	21
	3	param	1	21
upvalues (1) for 0000029B16972250:
	0	_ENV	0	0

main <canvas.lua:0,0> (19 instructions at 0000029B16971850)
4 params, 9 slots, 1 upvalue, 4 locals, 7 constants, 0 functions
	1	[138]	GETTABUP 	4 0 -1	; _ENV "error"
	2	[138]	NEWTABLE 	5 2 0
	3	[138]	LOADK    	6 -2	; "__proto"
	4	[138]	GETTABUP 	7 0 -3	; _ENV "Error"
	5	[138]	SETTABLE 	5 6 7
	6	[138]	LOADK    	6 -4	; "__index"
	7	[138]	GETTABUP 	7 0 -3	; _ENV "Error"
	8	[138]	SETTABLE 	5 6 7
	9	[138]	GETTABUP 	6 0 -5	; _ENV "setmetatable"
	10	[138]	MOVE     	7 5
	11	[138]	MOVE     	8 5
	12	[138]	CALL     	6 3 1
	13	[138]	SELF     	6 5 -6	; "constructor"
	14	[138]	TEST     	6 0
	15	[138]	JMP      	0 2	; to 18
	16	[138]	LOADK    	8 -7	; "Method not implemented."
	17	[138]	CALL     	6 3 1
	18	[138]	CALL     	4 2 1
	19	[138]	RETURN   	0 1
constants (7) for 0000029B16971850:
	1	"error"
	2	"__proto"
	3	"Error"
	4	"__index"
	5	"setmetatable"
	6	"constructor"
	7	"Method not implemented."
locals (4) for 0000029B16971850:
	0	this	1	21
	1	target	1	21
	2	pname	1	21
	3	param	1	21
upvalues (1) for 0000029B16971850:
	0	_ENV	0	0

main <canvas.lua:0,0> (19 instructions at 0000029B16970FD0)
10 params, 15 slots, 1 upvalue, 10 locals, 7 constants, 0 functions
	1	[139]	GETTABUP 	10 0 -1	; _ENV "error"
	2	[139]	NEWTABLE 	11 2 0
	3	[139]	LOADK    	12 -2	; "__proto"
	4	[139]	GETTABUP 	13 0 -3	; _ENV "Error"
	5	[139]	SETTABLE 	11 12 13
	6	[139]	LOADK    	12 -4	; "__index"
	7	[139]	GETTABUP 	13 0 -3	; _ENV "Error"
	8	[139]	SETTABLE 	11 12 13
	9	[139]	GETTABUP 	12 0 -5	; _ENV "setmetatable"
	10	[139]	MOVE     	13 11
	11	[139]	MOVE     	14 11
	12	[139]	CALL     	12 3 1
	13	[139]	SELF     	12 11 -6	; "constructor"
	14	[139]	TEST     	12 0
	15	[139]	JMP      	0 2	; to 18
	16	[139]	LOADK    	14 -7	; "Method not implemented."
	17	[139]	CALL     	12 3 1
	18	[139]	CALL     	10 2 1
	19	[139]	RETURN   	0 1
constants (7) for 0000029B16970FD0:
	1	"error"
	2	"__proto"
	3	"Error"
	4	"__index"
	5	"setmetatable"
	6	"constructor"
	7	"Method not implemented."
locals (10) for 0000029B16970FD0:
	0	this	1	21
	1	target	1	21
	2	level	1	21
	3	xoffset	1	21
	4	yoffset	1	21
	5	width	1	21
	6	height	1	21
	7	format	1	21
	8	type	1	21
	9	pixels	1	21
upvalues (1) for 0000029B16970FD0:
	0	_ENV	0	0

main <canvas.lua:0,0> (19 instructions at 0000029B16971550)
3 params, 8 slots, 1 upvalue, 3 locals, 7 constants, 0 functions
	1	[140]	GETTABUP 	3 0 -1	; _ENV "error"
	2	[140]	NEWTABLE 	4 2 0
	3	[140]	LOADK    	5 -2	; "__proto"
	4	[140]	GETTABUP 	6 0 -3	; _ENV "Error"
	5	[140]	SETTABLE 	4 5 6
	6	[140]	LOADK    	5 -4	; "__index"
	7	[140]	GETTABUP 	6 0 -3	; _ENV "Error"
	8	[140]	SETTABLE 	4 5 6
	9	[140]	GETTABUP 	5 0 -5	; _ENV "setmetatable"
	10	[140]	MOVE     	6 4
	11	[140]	MOVE     	7 4
	12	[140]	CALL     	5 3 1
	13	[140]	SELF     	5 4 -6	; "constructor"
	14	[140]	TEST     	5 0
	15	[140]	JMP      	0 2	; to 18
	16	[140]	LOADK    	7 -7	; "Method not implemented."
	17	[140]	CALL     	5 3 1
	18	[140]	CALL     	3 2 1
	19	[140]	RETURN   	0 1
constants (7) for 0000029B16971550:
	1	"error"
	2	"__proto"
	3	"Error"
	4	"__index"
	5	"setmetatable"
	6	"constructor"
	7	"Method not implemented."
locals (3) for 0000029B16971550:
	0	this	1	21
	1	location	1	21
	2	x	1	21
upvalues (1) for 0000029B16971550:
	0	_ENV	0	0

main <canvas.lua:0,0> (19 instructions at 0000029B16972050)
3 params, 8 slots, 1 upvalue, 3 locals, 7 constants, 0 functions
	1	[141]	GETTABUP 	3 0 -1	; _ENV "error"
	2	[141]	NEWTABLE 	4 2 0
	3	[141]	LOADK    	5 -2	; "__proto"
	4	[141]	GETTABUP 	6 0 -3	; _ENV "Error"
	5	[141]	SETTABLE 	4 5 6
	6	[141]	LOADK    	5 -4	; "__index"
	7	[141]	GETTABUP 	6 0 -3	; _ENV "Error"
	8	[141]	SETTABLE 	4 5 6
	9	[141]	GETTABUP 	5 0 -5	; _ENV "setmetatable"
	10	[141]	MOVE     	6 4
	11	[141]	MOVE     	7 4
	12	[141]	CALL     	5 3 1
	13	[141]	SELF     	5 4 -6	; "constructor"
	14	[141]	TEST     	5 0
	15	[141]	JMP      	0 2	; to 18
	16	[141]	LOADK    	7 -7	; "Method not implemented."
	17	[141]	CALL     	5 3 1
	18	[141]	CALL     	3 2 1
	19	[141]	RETURN   	0 1
constants (7) for 0000029B16972050:
	1	"error"
	2	"__proto"
	3	"Error"
	4	"__index"
	5	"setmetatable"
	6	"constructor"
	7	"Method not implemented."
locals (3) for 0000029B16972050:
	0	this	1	21
	1	location	1	21
	2	v	1	21
upvalues (1) for 0000029B16972050:
	0	_ENV	0	0

main <canvas.lua:0,0> (19 instructions at 0000029B16972350)
3 params, 8 slots, 1 upvalue, 3 locals, 7 constants, 0 functions
	1	[142]	GETTABUP 	3 0 -1	; _ENV "error"
	2	[142]	NEWTABLE 	4 2 0
	3	[142]	LOADK    	5 -2	; "__proto"
	4	[142]	GETTABUP 	6 0 -3	; _ENV "Error"
	5	[142]	SETTABLE 	4 5 6
	6	[142]	LOADK    	5 -4	; "__index"
	7	[142]	GETTABUP 	6 0 -3	; _ENV "Error"
	8	[142]	SETTABLE 	4 5 6
	9	[142]	GETTABUP 	5 0 -5	; _ENV "setmetatable"
	10	[142]	MOVE     	6 4
	11	[142]	MOVE     	7 4
	12	[142]	CALL     	5 3 1
	13	[142]	SELF     	5 4 -6	; "constructor"
	14	[142]	TEST     	5 0
	15	[142]	JMP      	0 2	; to 18
	16	[142]	LOADK    	7 -7	; "Method not implemented."
	17	[142]	CALL     	5 3 1
	18	[142]	CALL     	3 2 1
	19	[142]	RETURN   	0 1
constants (7) for 0000029B16972350:
	1	"error"
	2	"__proto"
	3	"Error"
	4	"__index"
	5	"setmetatable"
	6	"constructor"
	7	"Method not implemented."
locals (3) for 0000029B16972350:
	0	this	1	21
	1	location	1	21
	2	x	1	21
upvalues (1) for 0000029B16972350:
	0	_ENV	0	0

main <canvas.lua:0,0> (19 instructions at 0000029B16971B50)
3 params, 8 slots, 1 upvalue, 3 locals, 7 constants, 0 functions
	1	[143]	GETTABUP 	3 0 -1	; _ENV "error"
	2	[143]	NEWTABLE 	4 2 0
	3	[143]	LOADK    	5 -2	; "__proto"
	4	[143]	GETTABUP 	6 0 -3	; _ENV "Error"
	5	[143]	SETTABLE 	4 5 6
	6	[143]	LOADK    	5 -4	; "__index"
	7	[143]	GETTABUP 	6 0 -3	; _ENV "Error"
	8	[143]	SETTABLE 	4 5 6
	9	[143]	GETTABUP 	5 0 -5	; _ENV "setmetatable"
	10	[143]	MOVE     	6 4
	11	[143]	MOVE     	7 4
	12	[143]	CALL     	5 3 1
	13	[143]	SELF     	5 4 -6	; "constructor"
	14	[143]	TEST     	5 0
	15	[143]	JMP      	0 2	; to 18
	16	[143]	LOADK    	7 -7	; "Method not implemented."
	17	[143]	CALL     	5 3 1
	18	[143]	CALL     	3 2 1
	19	[143]	RETURN   	0 1
constants (7) for 0000029B16971B50:
	1	"error"
	2	"__proto"
	3	"Error"
	4	"__index"
	5	"setmetatable"
	6	"constructor"
	7	"Method not implemented."
locals (3) for 0000029B16971B50:
	0	this	1	21
	1	location	1	21
	2	v	1	21
upvalues (1) for 0000029B16971B50:
	0	_ENV	0	0

main <canvas.lua:0,0> (19 instructions at 0000029B16971250)
4 params, 9 slots, 1 upvalue, 4 locals, 7 constants, 0 functions
	1	[144]	GETTABUP 	4 0 -1	; _ENV "error"
	2	[144]	NEWTABLE 	5 2 0
	3	[144]	LOADK    	6 -2	; "__proto"
	4	[144]	GETTABUP 	7 0 -3	; _ENV "Error"
	5	[144]	SETTABLE 	5 6 7
	6	[144]	LOADK    	6 -4	; "__index"
	7	[144]	GETTABUP 	7 0 -3	; _ENV "Error"
	8	[144]	SETTABLE 	5 6 7
	9	[144]	GETTABUP 	6 0 -5	; _ENV "setmetatable"
	10	[144]	MOVE     	7 5
	11	[144]	MOVE     	8 5
	12	[144]	CALL     	6 3 1
	13	[144]	SELF     	6 5 -6	; "constructor"
	14	[144]	TEST     	6 0
	15	[144]	JMP      	0 2	; to 18
	16	[144]	LOADK    	8 -7	; "Method not implemented."
	17	[144]	CALL     	6 3 1
	18	[144]	CALL     	4 2 1
	19	[144]	RETURN   	0 1
constants (7) for 0000029B16971250:
	1	"error"
	2	"__proto"
	3	"Error"
	4	"__index"
	5	"setmetatable"
	6	"constructor"
	7	"Method not implemented."
locals (4) for 0000029B16971250:
	0	this	1	21
	1	location	1	21
	2	x	1	21
	3	y	1	21
upvalues (1) for 0000029B16971250:
	0	_ENV	0	0

main <canvas.lua:0,0> (19 instructions at 0000029B16971350)
3 params, 8 slots, 1 upvalue, 3 locals, 7 constants, 0 functions
	1	[145]	GETTABUP 	3 0 -1	; _ENV "error"
	2	[145]	NEWTABLE 	4 2 0
	3	[145]	LOADK    	5 -2	; "__proto"
	4	[145]	GETTABUP 	6 0 -3	; _ENV "Error"
	5	[145]	SETTABLE 	4 5 6
	6	[145]	LOADK    	5 -4	; "__index"
	7	[145]	GETTABUP 	6 0 -3	; _ENV "Error"
	8	[145]	SETTABLE 	4 5 6
	9	[145]	GETTABUP 	5 0 -5	; _ENV "setmetatable"
	10	[145]	MOVE     	6 4
	11	[145]	MOVE     	7 4
	12	[145]	CALL     	5 3 1
	13	[145]	SELF     	5 4 -6	; "constructor"
	14	[145]	TEST     	5 0
	15	[145]	JMP      	0 2	; to 18
	16	[145]	LOADK    	7 -7	; "Method not implemented."
	17	[145]	CALL     	5 3 1
	18	[145]	CALL     	3 2 1
	19	[145]	RETURN   	0 1
constants (7) for 0000029B16971350:
	1	"error"
	2	"__proto"
	3	"Error"
	4	"__index"
	5	"setmetatable"
	6	"constructor"
	7	"Method not implemented."
locals (3) for 0000029B16971350:
	0	this	1	21
	1	location	1	21
	2	v	1	21
upvalues (1) for 0000029B16971350:
	0	_ENV	0	0

main <canvas.lua:0,0> (19 instructions at 0000029B16971450)
4 params, 9 slots, 1 upvalue, 4 locals, 7 constants, 0 functions
	1	[146]	GETTABUP 	4 0 -1	; _ENV "error"
	2	[146]	NEWTABLE 	5 2 0
	3	[146]	LOADK    	6 -2	; "__proto"
	4	[146]	GETTABUP 	7 0 -3	; _ENV "Error"
	5	[146]	SETTABLE 	5 6 7
	6	[146]	LOADK    	6 -4	; "__index"
	7	[146]	GETTABUP 	7 0 -3	; _ENV "Error"
	8	[146]	SETTABLE 	5 6 7
	9	[146]	GETTABUP 	6 0 -5	; _ENV "setmetatable"
	10	[146]	MOVE     	7 5
	11	[146]	MOVE     	8 5
	12	[146]	CALL     	6 3 1
	13	[146]	SELF     	6 5 -6	; "constructor"
	14	[146]	TEST     	6 0
	15	[146]	JMP      	0 2	; to 18
	16	[146]	LOADK    	8 -7	; "Method not implemented."
	17	[146]	CALL     	6 3 1
	18	[146]	CALL     	4 2 1
	19	[146]	RETURN   	0 1
constants (7) for 0000029B16971450:
	1	"error"
	2	"__proto"
	3	"Error"
	4	"__index"
	5	"setmetatable"
	6	"constructor"
	7	"Method not implemented."
locals (4) for 0000029B16971450:
	0	this	1	21
	1	location	1	21
	2	x	1	21
	3	y	1	21
upvalues (1) for 0000029B16971450:
	0	_ENV	0	0

main <canvas.lua:0,0> (19 instructions at 0000029B16972750)
3 params, 8 slots, 1 upvalue, 3 locals, 7 constants, 0 functions
	1	[147]	GETTABUP 	3 0 -1	; _ENV "error"
	2	[147]	NEWTABLE 	4 2 0
	3	[147]	LOADK    	5 -2	; "__proto"
	4	[147]	GETTABUP 	6 0 -3	; _ENV "Error"
	5	[147]	SETTABLE 	4 5 6
	6	[147]	LOADK    	5 -4	; "__index"
	7	[147]	GETTABUP 	6 0 -3	; _ENV "Error"
	8	[147]	SETTABLE 	4 5 6
	9	[147]	GETTABUP 	5 0 -5	; _ENV "setmetatable"
	10	[147]	MOVE     	6 4
	11	[147]	MOVE     	7 4
	12	[147]	CALL     	5 3 1
	13	[147]	SELF     	5 4 -6	; "constructor"
	14	[147]	TEST     	5 0
	15	[147]	JMP      	0 2	; to 18
	16	[147]	LOADK    	7 -7	; "Method not implemented."
	17	[147]	CALL     	5 3 1
	18	[147]	CALL     	3 2 1
	19	[147]	RETURN   	0 1
constants (7) for 0000029B16972750:
	1	"error"
	2	"__proto"
	3	"Error"
	4	"__index"
	5	"setmetatable"
	6	"constructor"
	7	"Method not implemented."
locals (3) for 0000029B16972750:
	0	this	1	21
	1	location	1	21
	2	v	1	21
upvalues (1) for 0000029B16972750:
	0	_ENV	0	0

main <canvas.lua:0,0> (19 instructions at 0000029B16971750)
5 params, 10 slots, 1 upvalue, 5 locals, 7 constants, 0 functions
	1	[148]	GETTABUP 	5 0 -1	; _ENV "error"
	2	[148]	NEWTABLE 	6 2 0
	3	[148]	LOADK    	7 -2	; "__proto"
	4	[148]	GETTABUP 	8 0 -3	; _ENV "Error"
	5	[148]	SETTABLE 	6 7 8
	6	[148]	LOADK    	7 -4	; "__index"
	7	[148]	GETTABUP 	8 0 -3	; _ENV "Error"
	8	[148]	SETTABLE 	6 7 8
	9	[148]	GETTABUP 	7 0 -5	; _ENV "setmetatable"
	10	[148]	MOVE     	8 6
	11	[148]	MOVE     	9 6
	12	[148]	CALL     	7 3 1
	13	[148]	SELF     	7 6 -6	; "constructor"
	14	[148]	TEST     	7 0
	15	[148]	JMP      	0 2	; to 18
	16	[148]	LOADK    	9 -7	; "Method not implemented."
	17	[148]	CALL     	7 3 1
	18	[148]	CALL     	5 2 1
	19	[148]	RETURN   	0 1
constants (7) for 0000029B16971750:
	1	"error"
	2	"__proto"
	3	"Error"
	4	"__index"
	5	"setmetatable"
	6	"constructor"
	7	"Method not implemented."
locals (5) for 0000029B16971750:
	0	this	1	21
	1	location	1	21
	2	x	1	21
	3	y	1	21
	4	z	1	21
upvalues (1) for 0000029B16971750:
	0	_ENV	0	0

main <canvas.lua:0,0> (19 instructions at 0000029B169711D0)
3 params, 8 slots, 1 upvalue, 3 locals, 7 constants, 0 functions
	1	[149]	GETTABUP 	3 0 -1	; _ENV "error"
	2	[149]	NEWTABLE 	4 2 0
	3	[149]	LOADK    	5 -2	; "__proto"
	4	[149]	GETTABUP 	6 0 -3	; _ENV "Error"
	5	[149]	SETTABLE 	4 5 6
	6	[149]	LOADK    	5 -4	; "__index"
	7	[149]	GETTABUP 	6 0 -3	; _ENV "Error"
	8	[149]	SETTABLE 	4 5 6
	9	[149]	GETTABUP 	5 0 -5	; _ENV "setmetatable"
	10	[149]	MOVE     	6 4
	11	[149]	MOVE     	7 4
	12	[149]	CALL     	5 3 1
	13	[149]	SELF     	5 4 -6	; "constructor"
	14	[149]	TEST     	5 0
	15	[149]	JMP      	0 2	; to 18
	16	[149]	LOADK    	7 -7	; "Method not implemented."
	17	[149]	CALL     	5 3 1
	18	[149]	CALL     	3 2 1
	19	[149]	RETURN   	0 1
constants (7) for 0000029B169711D0:
	1	"error"
	2	"__proto"
	3	"Error"
	4	"__index"
	5	"setmetatable"
	6	"constructor"
	7	"Method not implemented."
locals (3) for 0000029B169711D0:
	0	this	1	21
	1	location	1	21
	2	v	1	21
upvalues (1) for 0000029B169711D0:
	0	_ENV	0	0

main <canvas.lua:0,0> (19 instructions at 0000029B16975960)
5 params, 10 slots, 1 upvalue, 5 locals, 7 constants, 0 functions
	1	[150]	GETTABUP 	5 0 -1	; _ENV "error"
	2	[150]	NEWTABLE 	6 2 0
	3	[150]	LOADK    	7 -2	; "__proto"
	4	[150]	GETTABUP 	8 0 -3	; _ENV "Error"
	5	[150]	SETTABLE 	6 7 8
	6	[150]	LOADK    	7 -4	; "__index"
	7	[150]	GETTABUP 	8 0 -3	; _ENV "Error"
	8	[150]	SETTABLE 	6 7 8
	9	[150]	GETTABUP 	7 0 -5	; _ENV "setmetatable"
	10	[150]	MOVE     	8 6
	11	[150]	MOVE     	9 6
	12	[150]	CALL     	7 3 1
	13	[150]	SELF     	7 6 -6	; "constructor"
	14	[150]	TEST     	7 0
	15	[150]	JMP      	0 2	; to 18
	16	[150]	LOADK    	9 -7	; "Method not implemented."
	17	[150]	CALL     	7 3 1
	18	[150]	CALL     	5 2 1
	19	[150]	RETURN   	0 1
constants (7) for 0000029B16975960:
	1	"error"
	2	"__proto"
	3	"Error"
	4	"__index"
	5	"setmetatable"
	6	"constructor"
	7	"Method not implemented."
locals (5) for 0000029B16975960:
	0	this	1	21
	1	location	1	21
	2	x	1	21
	3	y	1	21
	4	z	1	21
upvalues (1) for 0000029B16975960:
	0	_ENV	0	0

main <canvas.lua:0,0> (19 instructions at 0000029B16975460)
3 params, 8 slots, 1 upvalue, 3 locals, 7 constants, 0 functions
	1	[151]	GETTABUP 	3 0 -1	; _ENV "error"
	2	[151]	NEWTABLE 	4 2 0
	3	[151]	LOADK    	5 -2	; "__proto"
	4	[151]	GETTABUP 	6 0 -3	; _ENV "Error"
	5	[151]	SETTABLE 	4 5 6
	6	[151]	LOADK    	5 -4	; "__index"
	7	[151]	GETTABUP 	6 0 -3	; _ENV "Error"
	8	[151]	SETTABLE 	4 5 6
	9	[151]	GETTABUP 	5 0 -5	; _ENV "setmetatable"
	10	[151]	MOVE     	6 4
	11	[151]	MOVE     	7 4
	12	[151]	CALL     	5 3 1
	13	[151]	SELF     	5 4 -6	; "constructor"
	14	[151]	TEST     	5 0
	15	[151]	JMP      	0 2	; to 18
	16	[151]	LOADK    	7 -7	; "Method not implemented."
	17	[151]	CALL     	5 3 1
	18	[151]	CALL     	3 2 1
	19	[151]	RETURN   	0 1
constants (7) for 0000029B16975460:
	1	"error"
	2	"__proto"
	3	"Error"
	4	"__index"
	5	"setmetatable"
	6	"constructor"
	7	"Method not implemented."
locals (3) for 0000029B16975460:
	0	this	1	21
	1	location	1	21
	2	v	1	21
upvalues (1) for 0000029B16975460:
	0	_ENV	0	0

main <canvas.lua:0,0> (19 instructions at 0000029B16975860)
6 params, 11 slots, 1 upvalue, 6 locals, 7 constants, 0 functions
	1	[152]	GETTABUP 	6 0 -1	; _ENV "error"
	2	[152]	NEWTABLE 	7 2 0
	3	[152]	LOADK    	8 -2	; "__proto"
	4	[152]	GETTABUP 	9 0 -3	; _ENV "Error"
	5	[152]	SETTABLE 	7 8 9
	6	[152]	LOADK    	8 -4	; "__index"
	7	[152]	GETTABUP 	9 0 -3	; _ENV "Error"
	8	[152]	SETTABLE 	7 8 9
	9	[152]	GETTABUP 	8 0 -5	; _ENV "setmetatable"
	10	[152]	MOVE     	9 7
	11	[152]	MOVE     	10 7
	12	[152]	CALL     	8 3 1
	13	[152]	SELF     	8 7 -6	; "constructor"
	14	[152]	TEST     	8 0
	15	[152]	JMP      	0 2	; to 18
	16	[152]	LOADK    	10 -7	; "Method not implemented."
	17	[152]	CALL     	8 3 1
	18	[152]	CALL     	6 2 1
	19	[152]	RETURN   	0 1
constants (7) for 0000029B16975860:
	1	"error"
	2	"__proto"
	3	"Error"
	4	"__index"
	5	"setmetatable"
	6	"constructor"
	7	"Method not implemented."
locals (6) for 0000029B16975860:
	0	this	1	21
	1	location	1	21
	2	x	1	21
	3	y	1	21
	4	z	1	21
	5	w	1	21
upvalues (1) for 0000029B16975860:
	0	_ENV	0	0

main <canvas.lua:0,0> (19 instructions at 0000029B16975560)
3 params, 8 slots, 1 upvalue, 3 locals, 7 constants, 0 functions
	1	[153]	GETTABUP 	3 0 -1	; _ENV "error"
	2	[153]	NEWTABLE 	4 2 0
	3	[153]	LOADK    	5 -2	; "__proto"
	4	[153]	GETTABUP 	6 0 -3	; _ENV "Error"
	5	[153]	SETTABLE 	4 5 6
	6	[153]	LOADK    	5 -4	; "__index"
	7	[153]	GETTABUP 	6 0 -3	; _ENV "Error"
	8	[153]	SETTABLE 	4 5 6
	9	[153]	GETTABUP 	5 0 -5	; _ENV "setmetatable"
	10	[153]	MOVE     	6 4
	11	[153]	MOVE     	7 4
	12	[153]	CALL     	5 3 1
	13	[153]	SELF     	5 4 -6	; "constructor"
	14	[153]	TEST     	5 0
	15	[153]	JMP      	0 2	; to 18
	16	[153]	LOADK    	7 -7	; "Method not implemented."
	17	[153]	CALL     	5 3 1
	18	[153]	CALL     	3 2 1
	19	[153]	RETURN   	0 1
constants (7) for 0000029B16975560:
	1	"error"
	2	"__proto"
	3	"Error"
	4	"__index"
	5	"setmetatable"
	6	"constructor"
	7	"Method not implemented."
locals (3) for 0000029B16975560:
	0	this	1	21
	1	location	1	21
	2	v	1	21
upvalues (1) for 0000029B16975560:
	0	_ENV	0	0

main <canvas.lua:0,0> (19 instructions at 0000029B169744E0)
6 params, 11 slots, 1 upvalue, 6 locals, 7 constants, 0 functions
	1	[154]	GETTABUP 	6 0 -1	; _ENV "error"
	2	[154]	NEWTABLE 	7 2 0
	3	[154]	LOADK    	8 -2	; "__proto"
	4	[154]	GETTABUP 	9 0 -3	; _ENV "Error"
	5	[154]	SETTABLE 	7 8 9
	6	[154]	LOADK    	8 -4	; "__index"
	7	[154]	GETTABUP 	9 0 -3	; _ENV "Error"
	8	[154]	SETTABLE 	7 8 9
	9	[154]	GETTABUP 	8 0 -5	; _ENV "setmetatable"
	10	[154]	MOVE     	9 7
	11	[154]	MOVE     	10 7
	12	[154]	CALL     	8 3 1
	13	[154]	SELF     	8 7 -6	; "constructor"
	14	[154]	TEST     	8 0
	15	[154]	JMP      	0 2	; to 18
	16	[154]	LOADK    	10 -7	; "Method not implemented."
	17	[154]	CALL     	8 3 1
	18	[154]	CALL     	6 2 1
	19	[154]	RETURN   	0 1
constants (7) for 0000029B169744E0:
	1	"error"
	2	"__proto"
	3	"Error"
	4	"__index"
	5	"setmetatable"
	6	"constructor"
	7	"Method not implemented."
locals (6) for 0000029B169744E0:
	0	this	1	21
	1	location	1	21
	2	x	1	21
	3	y	1	21
	4	z	1	21
	5	w	1	21
upvalues (1) for 0000029B169744E0:
	0	_ENV	0	0

main <canvas.lua:0,0> (19 instructions at 0000029B16974F60)
3 params, 8 slots, 1 upvalue, 3 locals, 7 constants, 0 functions
	1	[155]	GETTABUP 	3 0 -1	; _ENV "error"
	2	[155]	NEWTABLE 	4 2 0
	3	[155]	LOADK    	5 -2	; "__proto"
	4	[155]	GETTABUP 	6 0 -3	; _ENV "Error"
	5	[155]	SETTABLE 	4 5 6
	6	[155]	LOADK    	5 -4	; "__index"
	7	[155]	GETTABUP 	6 0 -3	; _ENV "Error"
	8	[155]	SETTABLE 	4 5 6
	9	[155]	GETTABUP 	5 0 -5	; _ENV "setmetatable"
	10	[155]	MOVE     	6 4
	11	[155]	MOVE     	7 4
	12	[155]	CALL     	5 3 1
	13	[155]	SELF     	5 4 -6	; "constructor"
	14	[155]	TEST     	5 0
	15	[155]	JMP      	0 2	; to 18
	16	[155]	LOADK    	7 -7	; "Method not implemented."
	17	[155]	CALL     	5 3 1
	18	[155]	CALL     	3 2 1
	19	[155]	RETURN   	0 1
constants (7) for 0000029B16974F60:
	1	"error"
	2	"__proto"
	3	"Error"
	4	"__index"
	5	"setmetatable"
	6	"constructor"
	7	"Method not implemented."
locals (3) for 0000029B16974F60:
	0	this	1	21
	1	location	1	21
	2	v	1	21
upvalues (1) for 0000029B16974F60:
	0	_ENV	0	0

main <canvas.lua:0,0> (19 instructions at 0000029B16974560)
4 params, 9 slots, 1 upvalue, 4 locals, 7 constants, 0 functions
	1	[156]	GETTABUP 	4 0 -1	; _ENV "error"
	2	[156]	NEWTABLE 	5 2 0
	3	[156]	LOADK    	6 -2	; "__proto"
	4	[156]	GETTABUP 	7 0 -3	; _ENV "Error"
	5	[156]	SETTABLE 	5 6 7
	6	[156]	LOADK    	6 -4	; "__index"
	7	[156]	GETTABUP 	7 0 -3	; _ENV "Error"
	8	[156]	SETTABLE 	5 6 7
	9	[156]	GETTABUP 	6 0 -5	; _ENV "setmetatable"
	10	[156]	MOVE     	7 5
	11	[156]	MOVE     	8 5
	12	[156]	CALL     	6 3 1
	13	[156]	SELF     	6 5 -6	; "constructor"
	14	[156]	TEST     	6 0
	15	[156]	JMP      	0 2	; to 18
	16	[156]	LOADK    	8 -7	; "Method not implemented."
	17	[156]	CALL     	6 3 1
	18	[156]	CALL     	4 2 1
	19	[156]	RETURN   	0 1
constants (7) for 0000029B16974560:
	1	"error"
	2	"__proto"
	3	"Error"
	4	"__index"
	5	"setmetatable"
	6	"constructor"
	7	"Method not implemented."
locals (4) for 0000029B16974560:
	0	this	1	21
	1	location	1	21
	2	transpose	1	21
	3	value	1	21
upvalues (1) for 0000029B16974560:
	0	_ENV	0	0

main <canvas.lua:0,0> (19 instructions at 0000029B169758E0)
4 params, 9 slots, 1 upvalue, 4 locals, 7 constants, 0 functions
	1	[157]	GETTABUP 	4 0 -1	; _ENV "error"
	2	[157]	NEWTABLE 	5 2 0
	3	[157]	LOADK    	6 -2	; "__proto"
	4	[157]	GETTABUP 	7 0 -3	; _ENV "Error"
	5	[157]	SETTABLE 	5 6 7
	6	[157]	LOADK    	6 -4	; "__index"
	7	[157]	GETTABUP 	7 0 -3	; _ENV "Error"
	8	[157]	SETTABLE 	5 6 7
	9	[157]	GETTABUP 	6 0 -5	; _ENV "setmetatable"
	10	[157]	MOVE     	7 5
	11	[157]	MOVE     	8 5
	12	[157]	CALL     	6 3 1
	13	[157]	SELF     	6 5 -6	; "constructor"
	14	[157]	TEST     	6 0
	15	[157]	JMP      	0 2	; to 18
	16	[157]	LOADK    	8 -7	; "Method not implemented."
	17	[157]	CALL     	6 3 1
	18	[157]	CALL     	4 2 1
	19	[157]	RETURN   	0 1
constants (7) for 0000029B169758E0:
	1	"error"
	2	"__proto"
	3	"Error"
	4	"__index"
	5	"setmetatable"
	6	"constructor"
	7	"Method not implemented."
locals (4) for 0000029B169758E0:
	0	this	1	21
	1	location	1	21
	2	transpose	1	21
	3	value	1	21
upvalues (1) for 0000029B169758E0:
	0	_ENV	0	0

main <canvas.lua:0,0> (19 instructions at 0000029B16973EE0)
4 params, 9 slots, 1 upvalue, 4 locals, 7 constants, 0 functions
	1	[158]	GETTABUP 	4 0 -1	; _ENV "error"
	2	[158]	NEWTABLE 	5 2 0
	3	[158]	LOADK    	6 -2	; "__proto"
	4	[158]	GETTABUP 	7 0 -3	; _ENV "Error"
	5	[158]	SETTABLE 	5 6 7
	6	[158]	LOADK    	6 -4	; "__index"
	7	[158]	GETTABUP 	7 0 -3	; _ENV "Error"
	8	[158]	SETTABLE 	5 6 7
	9	[158]	GETTABUP 	6 0 -5	; _ENV "setmetatable"
	10	[158]	MOVE     	7 5
	11	[158]	MOVE     	8 5
	12	[158]	CALL     	6 3 1
	13	[158]	SELF     	6 5 -6	; "constructor"
	14	[158]	TEST     	6 0
	15	[158]	JMP      	0 2	; to 18
	16	[158]	LOADK    	8 -7	; "Method not implemented."
	17	[158]	CALL     	6 3 1
	18	[158]	CALL     	4 2 1
	19	[158]	RETURN   	0 1
constants (7) for 0000029B16973EE0:
	1	"error"
	2	"__proto"
	3	"Error"
	4	"__index"
	5	"setmetatable"
	6	"constructor"
	7	"Method not implemented."
locals (4) for 0000029B16973EE0:
	0	this	1	21
	1	location	1	21
	2	transpose	1	21
	3	value	1	21
upvalues (1) for 0000029B16973EE0:
	0	_ENV	0	0

main <canvas.lua:0,0> (19 instructions at 0000029B16974660)
2 params, 7 slots, 1 upvalue, 2 locals, 7 constants, 0 functions
	1	[159]	GETTABUP 	2 0 -1	; _ENV "error"
	2	[159]	NEWTABLE 	3 2 0
	3	[159]	LOADK    	4 -2	; "__proto"
	4	[159]	GETTABUP 	5 0 -3	; _ENV "Error"
	5	[159]	SETTABLE 	3 4 5
	6	[159]	LOADK    	4 -4	; "__index"
	7	[159]	GETTABUP 	5 0 -3	; _ENV "Error"
	8	[159]	SETTABLE 	3 4 5
	9	[159]	GETTABUP 	4 0 -5	; _ENV "setmetatable"
	10	[159]	MOVE     	5 3
	11	[159]	MOVE     	6 3
	12	[159]	CALL     	4 3 1
	13	[159]	SELF     	4 3 -6	; "constructor"
	14	[159]	TEST     	4 0
	15	[159]	JMP      	0 2	; to 18
	16	[159]	LOADK    	6 -7	; "Method not implemented."
	17	[159]	CALL     	4 3 1
	18	[159]	CALL     	2 2 1
	19	[159]	RETURN   	0 1
constants (7) for 0000029B16974660:
	1	"error"
	2	"__proto"
	3	"Error"
	4	"__index"
	5	"setmetatable"
	6	"constructor"
	7	"Method not implemented."
locals (2) for 0000029B16974660:
	0	this	1	21
	1	program	1	21
upvalues (1) for 0000029B16974660:
	0	_ENV	0	0

main <canvas.lua:0,0> (19 instructions at 0000029B169745E0)
2 params, 7 slots, 1 upvalue, 2 locals, 7 constants, 0 functions
	1	[160]	GETTABUP 	2 0 -1	; _ENV "error"
	2	[160]	NEWTABLE 	3 2 0
	3	[160]	LOADK    	4 -2	; "__proto"
	4	[160]	GETTABUP 	5 0 -3	; _ENV "Error"
	5	[160]	SETTABLE 	3 4 5
	6	[160]	LOADK    	4 -4	; "__index"
	7	[160]	GETTABUP 	5 0 -3	; _ENV "Error"
	8	[160]	SETTABLE 	3 4 5
	9	[160]	GETTABUP 	4 0 -5	; _ENV "setmetatable"
	10	[160]	MOVE     	5 3
	11	[160]	MOVE     	6 3
	12	[160]	CALL     	4 3 1
	13	[160]	SELF     	4 3 -6	; "constructor"
	14	[160]	TEST     	4 0
	15	[160]	JMP      	0 2	; to 18
	16	[160]	LOADK    	6 -7	; "Method not implemented."
	17	[160]	CALL     	4 3 1
	18	[160]	CALL     	2 2 1
	19	[160]	RETURN   	0 1
constants (7) for 0000029B169745E0:
	1	"error"
	2	"__proto"
	3	"Error"
	4	"__index"
	5	"setmetatable"
	6	"constructor"
	7	"Method not implemented."
locals (2) for 0000029B169745E0:
	0	this	1	21
	1	program	1	21
upvalues (1) for 0000029B169745E0:
	0	_ENV	0	0

main <canvas.lua:0,0> (19 instructions at 0000029B169754E0)
3 params, 8 slots, 1 upvalue, 3 locals, 7 constants, 0 functions
	1	[161]	GETTABUP 	3 0 -1	; _ENV "error"
	2	[161]	NEWTABLE 	4 2 0
	3	[161]	LOADK    	5 -2	; "__proto"
	4	[161]	GETTABUP 	6 0 -3	; _ENV "Error"
	5	[161]	SETTABLE 	4 5 6
	6	[161]	LOADK    	5 -4	; "__index"
	7	[161]	GETTABUP 	6 0 -3	; _ENV "Error"
	8	[161]	SETTABLE 	4 5 6
	9	[161]	GETTABUP 	5 0 -5	; _ENV "setmetatable"
	10	[161]	MOVE     	6 4
	11	[161]	MOVE     	7 4
	12	[161]	CALL     	5 3 1
	13	[161]	SELF     	5 4 -6	; "constructor"
	14	[161]	TEST     	5 0
	15	[161]	JMP      	0 2	; to 18
	16	[161]	LOADK    	7 -7	; "Method not implemented."
	17	[161]	CALL     	5 3 1
	18	[161]	CALL     	3 2 1
	19	[161]	RETURN   	0 1
constants (7) for 0000029B169754E0:
	1	"error"
	2	"__proto"
	3	"Error"
	4	"__index"
	5	"setmetatable"
	6	"constructor"
	7	"Method not implemented."
locals (3) for 0000029B169754E0:
	0	this	1	21
	1	index	1	21
	2	x	1	21
upvalues (1) for 0000029B169754E0:
	0	_ENV	0	0

main <canvas.lua:0,0> (19 instructions at 0000029B16974960)
3 params, 8 slots, 1 upvalue, 3 locals, 7 constants, 0 functions
	1	[162]	GETTABUP 	3 0 -1	; _ENV "error"
	2	[162]	NEWTABLE 	4 2 0
	3	[162]	LOADK    	5 -2	; "__proto"
	4	[162]	GETTABUP 	6 0 -3	; _ENV "Error"
	5	[162]	SETTABLE 	4 5 6
	6	[162]	LOADK    	5 -4	; "__index"
	7	[162]	GETTABUP 	6 0 -3	; _ENV "Error"
	8	[162]	SETTABLE 	4 5 6
	9	[162]	GETTABUP 	5 0 -5	; _ENV "setmetatable"
	10	[162]	MOVE     	6 4
	11	[162]	MOVE     	7 4
	12	[162]	CALL     	5 3 1
	13	[162]	SELF     	5 4 -6	; "constructor"
	14	[162]	TEST     	5 0
	15	[162]	JMP      	0 2	; to 18
	16	[162]	LOADK    	7 -7	; "Method not implemented."
	17	[162]	CALL     	5 3 1
	18	[162]	CALL     	3 2 1
	19	[162]	RETURN   	0 1
constants (7) for 0000029B16974960:
	1	"error"
	2	"__proto"
	3	"Error"
	4	"__index"
	5	"setmetatable"
	6	"constructor"
	7	"Method not implemented."
locals (3) for 0000029B16974960:
	0	this	1	21
	1	index	1	21
	2	values	1	21
upvalues (1) for 0000029B16974960:
	0	_ENV	0	0

main <canvas.lua:0,0> (19 instructions at 0000029B169746E0)
4 params, 9 slots, 1 upvalue, 4 locals, 7 constants, 0 functions
	1	[163]	GETTABUP 	4 0 -1	; _ENV "error"
	2	[163]	NEWTABLE 	5 2 0
	3	[163]	LOADK    	6 -2	; "__proto"
	4	[163]	GETTABUP 	7 0 -3	; _ENV "Error"
	5	[163]	SETTABLE 	5 6 7
	6	[163]	LOADK    	6 -4	; "__index"
	7	[163]	GETTABUP 	7 0 -3	; _ENV "Error"
	8	[163]	SETTABLE 	5 6 7
	9	[163]	GETTABUP 	6 0 -5	; _ENV "setmetatable"
	10	[163]	MOVE     	7 5
	11	[163]	MOVE     	8 5
	12	[163]	CALL     	6 3 1
	13	[163]	SELF     	6 5 -6	; "constructor"
	14	[163]	TEST     	6 0
	15	[163]	JMP      	0 2	; to 18
	16	[163]	LOADK    	8 -7	; "Method not implemented."
	17	[163]	CALL     	6 3 1
	18	[163]	CALL     	4 2 1
	19	[163]	RETURN   	0 1
constants (7) for 0000029B169746E0:
	1	"error"
	2	"__proto"
	3	"Error"
	4	"__index"
	5	"setmetatable"
	6	"constructor"
	7	"Method not implemented."
locals (4) for 0000029B169746E0:
	0	this	1	21
	1	index	1	21
	2	x	1	21
	3	y	1	21
upvalues (1) for 0000029B169746E0:
	0	_ENV	0	0

main <canvas.lua:0,0> (19 instructions at 0000029B16975060)
3 params, 8 slots, 1 upvalue, 3 locals, 7 constants, 0 functions
	1	[164]	GETTABUP 	3 0 -1	; _ENV "error"
	2	[164]	NEWTABLE 	4 2 0
	3	[164]	LOADK    	5 -2	; "__proto"
	4	[164]	GETTABUP 	6 0 -3	; _ENV "Error"
	5	[164]	SETTABLE 	4 5 6
	6	[164]	LOADK    	5 -4	; "__index"
	7	[164]	GETTABUP 	6 0 -3	; _ENV "Error"
	8	[164]	SETTABLE 	4 5 6
	9	[164]	GETTABUP 	5 0 -5	; _ENV "setmetatable"
	10	[164]	MOVE     	6 4
	11	[164]	MOVE     	7 4
	12	[164]	CALL     	5 3 1
	13	[164]	SELF     	5 4 -6	; "constructor"
	14	[164]	TEST     	5 0
	15	[164]	JMP      	0 2	; to 18
	16	[164]	LOADK    	7 -7	; "Method not implemented."
	17	[164]	CALL     	5 3 1
	18	[164]	CALL     	3 2 1
	19	[164]	RETURN   	0 1
constants (7) for 0000029B16975060:
	1	"error"
	2	"__proto"
	3	"Error"
	4	"__index"
	5	"setmetatable"
	6	"constructor"
	7	"Method not implemented."
locals (3) for 0000029B16975060:
	0	this	1	21
	1	index	1	21
	2	values	1	21
upvalues (1) for 0000029B16975060:
	0	_ENV	0	0

main <canvas.lua:0,0> (19 instructions at 0000029B169756E0)
5 params, 10 slots, 1 upvalue, 5 locals, 7 constants, 0 functions
	1	[165]	GETTABUP 	5 0 -1	; _ENV "error"
	2	[165]	NEWTABLE 	6 2 0
	3	[165]	LOADK    	7 -2	; "__proto"
	4	[165]	GETTABUP 	8 0 -3	; _ENV "Error"
	5	[165]	SETTABLE 	6 7 8
	6	[165]	LOADK    	7 -4	; "__index"
	7	[165]	GETTABUP 	8 0 -3	; _ENV "Error"
	8	[165]	SETTABLE 	6 7 8
	9	[165]	GETTABUP 	7 0 -5	; _ENV "setmetatable"
	10	[165]	MOVE     	8 6
	11	[165]	MOVE     	9 6
	12	[165]	CALL     	7 3 1
	13	[165]	SELF     	7 6 -6	; "constructor"
	14	[165]	TEST     	7 0
	15	[165]	JMP      	0 2	; to 18
	16	[165]	LOADK    	9 -7	; "Method not implemented."
	17	[165]	CALL     	7 3 1
	18	[165]	CALL     	5 2 1
	19	[165]	RETURN   	0 1
constants (7) for 0000029B169756E0:
	1	"error"
	2	"__proto"
	3	"Error"
	4	"__index"
	5	"setmetatable"
	6	"constructor"
	7	"Method not implemented."
locals (5) for 0000029B169756E0:
	0	this	1	21
	1	index	1	21
	2	x	1	21
	3	y	1	21
	4	z	1	21
upvalues (1) for 0000029B169756E0:
	0	_ENV	0	0

main <canvas.lua:0,0> (19 instructions at 0000029B16975D60)
3 params, 8 slots, 1 upvalue, 3 locals, 7 constants, 0 functions
	1	[166]	GETTABUP 	3 0 -1	; _ENV "error"
	2	[166]	NEWTABLE 	4 2 0
	3	[166]	LOADK    	5 -2	; "__proto"
	4	[166]	GETTABUP 	6 0 -3	; _ENV "Error"
	5	[166]	SETTABLE 	4 5 6
	6	[166]	LOADK    	5 -4	; "__index"
	7	[166]	GETTABUP 	6 0 -3	; _ENV "Error"
	8	[166]	SETTABLE 	4 5 6
	9	[166]	GETTABUP 	5 0 -5	; _ENV "setmetatable"
	10	[166]	MOVE     	6 4
	11	[166]	MOVE     	7 4
	12	[166]	CALL     	5 3 1
	13	[166]	SELF     	5 4 -6	; "constructor"
	14	[166]	TEST     	5 0
	15	[166]	JMP      	0 2	; to 18
	16	[166]	LOADK    	7 -7	; "Method not implemented."
	17	[166]	CALL     	5 3 1
	18	[166]	CALL     	3 2 1
	19	[166]	RETURN   	0 1
constants (7) for 0000029B16975D60:
	1	"error"
	2	"__proto"
	3	"Error"
	4	"__index"
	5	"setmetatable"
	6	"constructor"
	7	"Method not implemented."
locals (3) for 0000029B16975D60:
	0	this	1	21
	1	index	1	21
	2	values	1	21
upvalues (1) for 0000029B16975D60:
	0	_ENV	0	0

main <canvas.lua:0,0> (19 instructions at 0000029B169751E0)
6 params, 11 slots, 1 upvalue, 6 locals, 7 constants, 0 functions
	1	[167]	GETTABUP 	6 0 -1	; _ENV "error"
	2	[167]	NEWTABLE 	7 2 0
	3	[167]	LOADK    	8 -2	; "__proto"
	4	[167]	GETTABUP 	9 0 -3	; _ENV "Error"
	5	[167]	SETTABLE 	7 8 9
	6	[167]	LOADK    	8 -4	; "__index"
	7	[167]	GETTABUP 	9 0 -3	; _ENV "Error"
	8	[167]	SETTABLE 	7 8 9
	9	[167]	GETTABUP 	8 0 -5	; _ENV "setmetatable"
	10	[167]	MOVE     	9 7
	11	[167]	MOVE     	10 7
	12	[167]	CALL     	8 3 1
	13	[167]	SELF     	8 7 -6	; "constructor"
	14	[167]	TEST     	8 0
	15	[167]	JMP      	0 2	; to 18
	16	[167]	LOADK    	10 -7	; "Method not implemented."
	17	[167]	CALL     	8 3 1
	18	[167]	CALL     	6 2 1
	19	[167]	RETURN   	0 1
constants (7) for 0000029B169751E0:
	1	"error"
	2	"__proto"
	3	"Error"
	4	"__index"
	5	"setmetatable"
	6	"constructor"
	7	"Method not implemented."
locals (6) for 0000029B169751E0:
	0	this	1	21
	1	index	1	21
	2	x	1	21
	3	y	1	21
	4	z	1	21
	5	w	1	21
upvalues (1) for 0000029B169751E0:
	0	_ENV	0	0

main <canvas.lua:0,0> (19 instructions at 0000029B169759E0)
3 params, 8 slots, 1 upvalue, 3 locals, 7 constants, 0 functions
	1	[168]	GETTABUP 	3 0 -1	; _ENV "error"
	2	[168]	NEWTABLE 	4 2 0
	3	[168]	LOADK    	5 -2	; "__proto"
	4	[168]	GETTABUP 	6 0 -3	; _ENV "Error"
	5	[168]	SETTABLE 	4 5 6
	6	[168]	LOADK    	5 -4	; "__index"
	7	[168]	GETTABUP 	6 0 -3	; _ENV "Error"
	8	[168]	SETTABLE 	4 5 6
	9	[168]	GETTABUP 	5 0 -5	; _ENV "setmetatable"
	10	[168]	MOVE     	6 4
	11	[168]	MOVE     	7 4
	12	[168]	CALL     	5 3 1
	13	[168]	SELF     	5 4 -6	; "constructor"
	14	[168]	TEST     	5 0
	15	[168]	JMP      	0 2	; to 18
	16	[168]	LOADK    	7 -7	; "Method not implemented."
	17	[168]	CALL     	5 3 1
	18	[168]	CALL     	3 2 1
	19	[168]	RETURN   	0 1
constants (7) for 0000029B169759E0:
	1	"error"
	2	"__proto"
	3	"Error"
	4	"__index"
	5	"setmetatable"
	6	"constructor"
	7	"Method not implemented."
locals (3) for 0000029B169759E0:
	0	this	1	21
	1	index	1	21
	2	values	1	21
upvalues (1) for 0000029B169759E0:
	0	_ENV	0	0

main <canvas.lua:0,0> (19 instructions at 0000029B16975760)
7 params, 12 slots, 1 upvalue, 7 locals, 7 constants, 0 functions
	1	[169]	GETTABUP 	7 0 -1	; _ENV "error"
	2	[169]	NEWTABLE 	8 2 0
	3	[169]	LOADK    	9 -2	; "__proto"
	4	[169]	GETTABUP 	10 0 -3	; _ENV "Error"
	5	[169]	SETTABLE 	8 9 10
	6	[169]	LOADK    	9 -4	; "__index"
	7	[169]	GETTABUP 	10 0 -3	; _ENV "Error"
	8	[169]	SETTABLE 	8 9 10
	9	[169]	GETTABUP 	9 0 -5	; _ENV "setmetatable"
	10	[169]	MOVE     	10 8
	11	[169]	MOVE     	11 8
	12	[169]	CALL     	9 3 1
	13	[169]	SELF     	9 8 -6	; "constructor"
	14	[169]	TEST     	9 0
	15	[169]	JMP      	0 2	; to 18
	16	[169]	LOADK    	11 -7	; "Method not implemented."
	17	[169]	CALL     	9 3 1
	18	[169]	CALL     	7 2 1
	19	[169]	RETURN   	0 1
constants (7) for 0000029B16975760:
	1	"error"
	2	"__proto"
	3	"Error"
	4	"__index"
	5	"setmetatable"
	6	"constructor"
	7	"Method not implemented."
locals (7) for 0000029B16975760:
	0	this	1	21
	1	index	1	21
	2	size	1	21
	3	type	1	21
	4	normalized	1	21
	5	stride	1	21
	6	offset	1	21
upvalues (1) for 0000029B16975760:
	0	_ENV	0	0

main <canvas.lua:0,0> (19 instructions at 0000029B16975BE0)
5 params, 10 slots, 1 upvalue, 5 locals, 7 constants, 0 functions
	1	[170]	GETTABUP 	5 0 -1	; _ENV "error"
	2	[170]	NEWTABLE 	6 2 0
	3	[170]	LOADK    	7 -2	; "__proto"
	4	[170]	GETTABUP 	8 0 -3	; _ENV "Error"
	5	[170]	SETTABLE 	6 7 8
	6	[170]	LOADK    	7 -4	; "__index"
	7	[170]	GETTABUP 	8 0 -3	; _ENV "Error"
	8	[170]	SETTABLE 	6 7 8
	9	[170]	GETTABUP 	7 0 -5	; _ENV "setmetatable"
	10	[170]	MOVE     	8 6
	11	[170]	MOVE     	9 6
	12	[170]	CALL     	7 3 1
	13	[170]	SELF     	7 6 -6	; "constructor"
	14	[170]	TEST     	7 0
	15	[170]	JMP      	0 2	; to 18
	16	[170]	LOADK    	9 -7	; "Method not implemented."
	17	[170]	CALL     	7 3 1
	18	[170]	CALL     	5 2 1
	19	[170]	RETURN   	0 1
constants (7) for 0000029B16975BE0:
	1	"error"
	2	"__proto"
	3	"Error"
	4	"__index"
	5	"setmetatable"
	6	"constructor"
	7	"Method not implemented."
locals (5) for 0000029B16975BE0:
	0	this	1	21
	1	x	1	21
	2	y	1	21
	3	width	1	21
	4	height	1	21
upvalues (1) for 0000029B16975BE0:
	0	_ENV	0	0
